Workbook
Name Baseline: UW!$C$441
Name Beta1: '[7]BBSW Curve'!$G$3
Name Beta1: 'BBSW Curve'!$G$3
Name Beta1: 'BBSW Curve'!$G$3
Name Beta2: '[7]BBSW Curve'!$G$4
Name Beta2: 'BBSW Curve'!$G$4
Name Beta2: 'BBSW Curve'!$G$4
Name Beta3: '[7]BBSW Curve'!$G$5
Name Beta3: 'BBSW Curve'!$G$5
Name Beta3: 'BBSW Curve'!$G$5
Name Beta4: '[7]BBSW Curve'!$G$6
Name Beta4: 'BBSW Curve'!$G$6
Name Beta4: 'BBSW Curve'!$G$6
Name Cash_on_Deposit_YesNo: [7]UW!$J$61
Name Cash_on_Deposit_YesNo: UW!$J$61
Name ddAccountClass: OFFSET( '[1]Dropdown Lists'!$AA$3,0,0,'[1]Dropdown Lists'!$AC$1,1)
Name ddFinPeriodID: OFFSET('[1]Dropdown Lists'!$D$3,0,0,'[1]Dropdown Lists'!$E$1,1)
Name ddSubAccountCode: OFFSET('[1]Dropdown Lists'!$W$3,0,0,'[1]Dropdown Lists'!$Y$1,3)
Name Debt: UW!$A$779
Name Dev_Budget: 'Dev Bdgt'!$C$2
Name Expense_Calcs: '[2]Model Inputs & Calcs'!$B$42:$N$65
Name Expense_Details: UW!$C$554
Name Expense_Match: '[2]Model Inputs & Calcs'!$B$42:$B$65
Name Expense_Yr_Match: '[2]Model Inputs & Calcs'!$B$42:$N$42
Name Home: UW!$D$4
Name IFS: [7]UW!#REF!
Name IFS: UW!#REF!
Name Lambda1: '[7]BBSW Curve'!$G$7
Name Lambda1: 'BBSW Curve'!$G$7
Name Lambda1: 'BBSW Curve'!$G$7
Name Lambda2: '[7]BBSW Curve'!$G$8
Name Lambda2: 'BBSW Curve'!$G$8
Name Lambda2: 'BBSW Curve'!$G$8
Name Lease_End_Date: [3]UW!$A$400
Name Mth_Bud: 'Mthly Bdgt'!$B$2:$P$706
Name Mth_Bud: 'Mthly Bdgt'!$B$2:$P$706
Name MthBud: '[3]Mthly Bdgt'!$B$2:$P$706
Name nActualLedger: [1]Global!$C$2
Name nBudgetLedger: [4]!tblBudgetLedger[Budget Ledger]
Name nConnection: [5]Global!$A$2
Name NoSubAccount: '[1]Dropdown Lists'!$BD$2
Name On_Deposit_Equity_Amount: [7]UW!$E$45
Name On_Deposit_Equity_Amount: UW!$E$45
Name On_Deposit_Equity_InDate: [7]UW!$J$62
Name On_Deposit_Equity_InDate: UW!$J$62
Name On_Deposit_Equity_OutDate: [7]UW!$J$63
Name On_Deposit_Equity_OutDate: UW!$J$63
Name Proforma_Annual: UW!$C$76
Name Proforma_Monthly: UW!$D$612
Name Sensitivity: UW!$B$867
Name Start_Mth: [7]UW!$D$95
Name Start_Mth: UW!$D$95
Name Start_Mth: UW!$D$95
Name StartMth: [3]UW!$D$95
Name Total_Equity: [7]UW!$M$13
Name Total_Equity: UW!$M$13
Name Unit_Mix: 'Comps & Unit Mix'!$AV$206
Name UnitMix: '[6]Comps & Unit Mix'!#REF!

Sheet Notes
A2: - Add sensitivity to DU GPR (cell d106)
A3: -link concessions (one time) to lease-up
A4: - create output page
A5: - use Gympie P/L for expense line reference
A6: - create lease up component for expansions
A7: - Add RV GPR to Property and Budget Tabs
A8: - Add Warehouse Income to DCF and Property, Budget
A9: - Add secondary Dev Budget
A10: - remove bad debt from expense ratio?
A11: - Add Other real estate income to Mthly Bdgt
A12: - Add another refinance assumption
A13: - Add RV Parking in Unit Mix
... A35: - "Mth_Bud" = VLOOKUP Chart for Concessions Calc

Sheet Output
F2: 1-km | G2: 3-km | H2: 5-km | K2: =UW!C6 -> Property Description | O2: Metrics Summary - 10 Year | U2: ='Return Distr.'!B127 -> Unitholder Position | X2: ='Return Distr.'!H127 -> 1 | Y2: ='Return Distr.'!I127 -> 2 | Z2: ='Return Distr.'!J127 -> 3 | AA2: ='Return Distr.'!K127 -> 4 | AB2: ='Return Distr.'!L127 -> 5 | AC2: ='Return Distr.'!M127 -> 6 | AD2: ='Return Distr.'!N127 -> 7 | AE2: ='Return Distr.'!O127 -> 8 | ... AG2: ='Return Distr.'!Q127 -> 10
C3: Population | F3: =UW!N59 -> 0 | G3: =UW!N60 -> 0 | H3: =UW!N61 -> 0 | K3: =UW!C7 -> Property Name | M3: =UW!D7 -> 0 | O3: =UW!#REF! -> #REF! | Q3: =UW!#REF! -> #REF!
C4: Number of Households | F4: 3311 | G4: 34218 | H4: 94547 | K4: Address | M4: =CONCATENATE(UW!D8,", ", UW!D9," ",UW!D10) -> , | O4: =UW!#REF! -> #REF! | Q4: =UW!#REF! -> #REF! | U4: ='Return Distr.'!B129 -> Net Property Income | X4: ='Return Distr.'!H129 -> 0 | Y4: ='Return Distr.'!I129 -> 0 | Z4: ='Return Distr.'!J129 -> 0 | AA4: ='Return Distr.'!K129 -> 0 | AB4: ='Return Distr.'!L129 -> 0 | AC4: ='Return Distr.'!M129 -> 0 | AD4: ='Return Distr.'!N129 -> 0 | AE4: ='Return Distr.'!O129 -> 0 | ... AG4: ='Return Distr.'!Q129 -> 0
C5: Average Household Size | F5: =F3/F4 -> 0 | G5: 3.01 | H5: 2.95 | K5: =UW!C12 -> Parcel Size | L5: =UW!#REF! -> #REF! | M5: =UW!D12 -> 0 | O5: =UW!#REF! -> #REF! | Q5: =UW!#REF! -> #REF! | U5: ='Return Distr.'!B130 -> Total Property Related Costs | X5: ='Return Distr.'!H130 -> -141154.2 | Y5: ='Return Distr.'!I130 -> -148182.53 | Z5: ='Return Distr.'!J130 -> -155561.7 | AA5: ='Return Distr.'!K130 -> -163309.22 | AB5: ='Return Distr.'!L130 -> -171443.51 | AC5: ='Return Distr.'!M130 -> -179983.88 | AD5: ='Return Distr.'!N130 -> -188950.64 | AE5: ='Return Distr.'!O130 -> -198365.09 | ... AG5: ='Return Distr.'!Q130 -> -218627.67
C6: Households That Rent | F6: =UW!N53 -> 0 | G6: =UW!N54 -> 0 | H6: =UW!N55 -> 0 | K6: =UW!C16 -> Traffic Count | L6: =UW!G16 -> 0 | M6: =UW!D16 -> 0 | O6: =UW!I16 -> Equity Multiple | Q6: =UW!J16 -> #DIV/0! | U6: ='Return Distr.'!B131 -> Net Income | X6: ='Return Distr.'!H131 -> -141154.2 | Y6: ='Return Distr.'!I131 -> -148182.53 | Z6: ='Return Distr.'!J131 -> -155561.7 | AA6: ='Return Distr.'!K131 -> -163309.22 | AB6: ='Return Distr.'!L131 -> -171443.51 | AC6: ='Return Distr.'!M131 -> -179983.88 | AD6: ='Return Distr.'!N131 -> -188950.64 | AE6: ='Return Distr.'!O131 -> -198365.09 | ... AG6: ='Return Distr.'!Q131 -> -218627.67
C7: % of Households That Rent | F7: =F6/F4 -> 0 | G7: =G6/G4 -> 0 | H7: =H6/H4 -> 0 | K7: =UW!C17 -> Renovated | M7: =UW!D17 -> 0 | O7: =CONCATENATE("Land ",UW!I17) -> Land Stab. YoC - Untrended | Q7: =UW!J17 -> #DIV/0!
C8: Storage Supply | F8: =UW!N50 -> 1400 | G8: =UW!N51 -> 7490 | H8: =UW!N52 -> 7490 | K8: =UW!C18 -> Manager Apartment? | M8: =UW!D18 -> 0 | O8: =UW!I18 -> Stab. YoC - Untrended (Norm.) | Q8: =UW!J18 -> #DIV/0! | U8: ='Return Distr.'!B133 -> Indirect Costs
C9: Storage Supply Per Capita | F9: =F8/F3 -> #DIV/0! | G9: =G8/G3 -> #DIV/0! | H9: =H8/H3 -> #DIV/0! | K9: =UW!C19 -> Rental Summary | M9: =UW!D19 -> 0 | O9: =UW!I19 -> Stab. YoC - Trended | Q9: =UW!J19 -> #DIV/0! | U9: ='Return Distr.'!B135 -> Interest | X9: ='Return Distr.'!H135 -> #DIV/0! | Y9: ='Return Distr.'!I135 -> #DIV/0! | Z9: ='Return Distr.'!J135 -> #DIV/0! | AA9: ='Return Distr.'!K135 -> 50.549895 | AB9: ='Return Distr.'!L135 -> 0 | AC9: ='Return Distr.'!M135 -> 0 | AD9: ='Return Distr.'!N135 -> 0 | AE9: ='Return Distr.'!O135 -> 0 | ... AG9: ='Return Distr.'!Q135 -> 0
K10: =UW!C20 -> Gross SM (Entire Facility) | M10: =UW!#REF! -> #REF! | O10: =UW!I20 -> Stab. YoC - Trended (Norm.) | Q10: =UW!J20 -> #DIV/0! | U10: ='Return Distr.'!B136 -> Fund Management Fee | X10: ='Return Distr.'!H136 -> 0 | Y10: ='Return Distr.'!I136 -> 0 | Z10: ='Return Distr.'!J136 -> 0 | AA10: ='Return Distr.'!K136 -> 0 | AB10: ='Return Distr.'!L136 -> 0 | AC10: ='Return Distr.'!M136 -> 0 | AD10: ='Return Distr.'!N136 -> 0 | AE10: ='Return Distr.'!O136 -> 0 | ... AG10: ='Return Distr.'!Q136 -> 0
K11: Construction Type | M11: Dado - steel frame/tilt up | U11: ='Return Distr.'!B137 -> Total Indirect Costs | X11: ='Return Distr.'!H137 -> #DIV/0! | Y11: ='Return Distr.'!I137 -> #DIV/0! | Z11: ='Return Distr.'!J137 -> #DIV/0! | AA11: ='Return Distr.'!K137 -> #DIV/0! | AB11: ='Return Distr.'!L137 -> #DIV/0! | AC11: ='Return Distr.'!M137 -> #DIV/0! | AD11: ='Return Distr.'!N137 -> #DIV/0! | AE11: ='Return Distr.'!O137 -> #DIV/0! | ... AG11: ='Return Distr.'!Q137 -> #DIV/0!
K12: =UW!C21 -> Net Rentable SM (Storage Only) | M12: =UW!#REF! -> #REF! | O12: Submarket
K13: =UW!C22 -> # Storage Units | M13: =UW!#REF! -> #REF! | O13: Surrounding Uses | Q13: Industrial/Residential/Retail | U13: ='Return Distr.'!B139 -> Total Reserve Drawdown | X13: ='Return Distr.'!H139 -> #DIV/0! | Y13: ='Return Distr.'!I139 -> #DIV/0! | Z13: ='Return Distr.'!J139 -> #DIV/0! | AA13: ='Return Distr.'!K139 -> #DIV/0! | AB13: ='Return Distr.'!L139 -> #DIV/0! | AC13: ='Return Distr.'!M139 -> #DIV/0! | AD13: ='Return Distr.'!N139 -> #DIV/0! | AE13: ='Return Distr.'!O139 -> #DIV/0! | ... AG13: ='Return Distr.'!Q139 -> #DIV/0!
K14: =UW!C23 -> Average Unit Size (Storage) | M14: =UW!#REF! -> #REF! | O14: =UW!L51 -> Supply (3-km) | Q14: =G9 -> #DIV/0! | U14: ='Return Distr.'!B141 -> Distributable Income | X14: ='Return Distr.'!H141 -> #DIV/0! | Y14: ='Return Distr.'!I141 -> #DIV/0! | Z14: ='Return Distr.'!J141 -> #DIV/0! | AA14: ='Return Distr.'!K141 -> #DIV/0! | AB14: ='Return Distr.'!L141 -> #DIV/0! | AC14: ='Return Distr.'!M141 -> #DIV/0! | AD14: ='Return Distr.'!N141 -> #DIV/0! | AE14: ='Return Distr.'!O141 -> #DIV/0! | ... AG14: ='Return Distr.'!Q141 -> #DIV/0!
K15: =UW!C25 -> Occupancy | L15: =UW!D27 -> No | M15: =UW!D20 -> 0 | O15: =UW!L52 -> Supply (5-km) | Q15: =H9 -> #DIV/0!
K16: =UW!C26 -> Asking Rents | M16: =UW!D21 -> 0 | O16: =UW!L54 -> HH that Rent (3-km) | Q16: =G7 -> 0 | U16: ='Return Distr.'!B143 -> Equity Repatriation | X16: ='Return Distr.'!H143 -> 0 | Y16: ='Return Distr.'!I143 -> 0 | Z16: ='Return Distr.'!J143 -> #DIV/0! | AA16: ='Return Distr.'!K143 -> 835.53546 | AB16: ='Return Distr.'!L143 -> 0 | AC16: ='Return Distr.'!M143 -> 0 | AD16: ='Return Distr.'!N143 -> 0 | AE16: ='Return Distr.'!O143 -> 0 | ... AG16: ='Return Distr.'!Q143 -> 0
K17: =UW!F21 -> Net Rentable SM (Office) | M17: =UW!D22 -> 0 | O17: =UW!L55 -> HH that Rent (5-km) | Q17: =H7 -> 0 | U17: ='Return Distr.'!#REF! -> #REF! | X17: ='Return Distr.'!#REF! -> #REF! | Y17: ='Return Distr.'!#REF! -> #REF! | Z17: ='Return Distr.'!#REF! -> #REF! | AA17: ='Return Distr.'!#REF! -> #REF! | AB17: ='Return Distr.'!#REF! -> #REF! | AC17: ='Return Distr.'!#REF! -> #REF! | AD17: ='Return Distr.'!#REF! -> #REF! | AE17: ='Return Distr.'!#REF! -> #REF! | ... AG17: ='Return Distr.'!#REF! -> #REF!
K18: =UW!F28 -> Warehouse NLA | M18: =UW!G28 -> 0 | O18: =UW!L60 -> Population (3-km) | Q18: =UW!N60 -> 0
K19: =UW!F29 -> # Warehouse Units | M19: =UW!G29 -> 15 | O19: =UW!L61 -> Population (5-km) | Q19: =UW!N61 -> 0 | U19: ='Return Distr.'!B144 -> Equity | X19: ='Return Distr.'!H144 -> #DIV/0! | Y19: ='Return Distr.'!I144 -> #DIV/0! | Z19: ='Return Distr.'!J144 -> #DIV/0! | AA19: ='Return Distr.'!K144 -> #DIV/0! | AB19: ='Return Distr.'!L144 -> #DIV/0! | AC19: ='Return Distr.'!M144 -> #DIV/0! | AD19: ='Return Distr.'!N144 -> #DIV/0! | AE19: ='Return Distr.'!O144 -> #DIV/0! | ... AG19: ='Return Distr.'!Q144 -> #DIV/0!
K20: Gross Potential Rent (Storage) | L20: =UW!D26 -> #DIV/0! | M20: =UW!G33 -> 0
U21: ='Return Distr.'!B146 -> Distributions Per Unit | X21: ='Return Distr.'!H146 -> #DIV/0! | Y21: ='Return Distr.'!I146 -> #DIV/0! | Z21: ='Return Distr.'!J146 -> #DIV/0! | AA21: ='Return Distr.'!K146 -> #DIV/0! | AB21: ='Return Distr.'!L146 -> #DIV/0! | AC21: ='Return Distr.'!M146 -> #DIV/0! | AD21: ='Return Distr.'!N146 -> #DIV/0! | AE21: ='Return Distr.'!O146 -> #DIV/0! | ... AG21: ='Return Distr.'!Q146 -> #DIV/0!
U22: ='Return Distr.'!B147 -> Distributions Per Unit (%) | X22: ='Return Distr.'!H147 -> #DIV/0! | Y22: ='Return Distr.'!I147 -> #DIV/0! | Z22: ='Return Distr.'!J147 -> #DIV/0! | AA22: ='Return Distr.'!K147 -> #DIV/0! | AB22: ='Return Distr.'!L147 -> #DIV/0! | AC22: ='Return Distr.'!M147 -> #DIV/0! | AD22: ='Return Distr.'!N147 -> #DIV/0! | AE22: ='Return Distr.'!O147 -> #DIV/0! | ... AG22: ='Return Distr.'!Q147 -> #DIV/0!
U23: Debt | X23: ='Return Distr.'!H148 -> #DIV/0! | Y23: ='Return Distr.'!I148 -> #DIV/0! | Z23: ='Return Distr.'!J148 -> -835.53546 | AA23: ='Return Distr.'!K148 -> -835.53546 | AB23: ='Return Distr.'!L148 -> 0 | AC23: ='Return Distr.'!M148 -> 0 | AD23: ='Return Distr.'!N148 -> 0 | AE23: ='Return Distr.'!O148 -> 0 | ... AG23: ='Return Distr.'!Q148 -> 0
K24: Property | O24: Loan | P24: =UW!E40 -> Initial Loan | Q24: Refi 1 | R24: Refi 2 | U24: ='Return Distr.'!B149 -> LVR | X24: ='Return Distr.'!H149 -> #DIV/0! | Y24: ='Return Distr.'!I149 -> #DIV/0! | Z24: ='Return Distr.'!J149 -> 0.44987406 | AA24: ='Return Distr.'!K149 -> 0.84045144 | AB24: ='Return Distr.'!L149 -> #DIV/0! | AC24: ='Return Distr.'!M149 -> #DIV/0! | AD24: ='Return Distr.'!N149 -> #DIV/0! | AE24: ='Return Distr.'!O149 -> #DIV/0! | ... AG24: ='Return Distr.'!Q149 -> #DIV/0!
K25: =UW!C12 -> Parcel Size | L25: =UW!#REF! -> #REF! | M25: =UW!D12 -> 0 | O25: =UW!D47 -> Total Loan | P25: =UW!E47 -> #DIV/0! | Q25: =UW!F47 -> -835.53546 | R25: =UW!G47 -> 0
K26: Total Building Size | L26: =UW!D21 -> 0 | M26: =UW!D20 -> 0 | O26: =UW!D49 -> Origination Fee | P26: =UW!E49 -> 0 | Q26: =UW!F49 -> 0 | R26: =UW!G49 -> 0 | U26: ='Return Distr.'!B151 -> Capital Value (DCF) | X26: ='Return Distr.'!H151 -> -3307.0063 | Y26: ='Return Distr.'!I151 -> -2627.9427 | Z26: ='Return Distr.'!J151 -> -1857.2653 | AA26: ='Return Distr.'!K151 -> -994.15079 | AB26: ='Return Distr.'!L151 -> 0 | AC26: ='Return Distr.'!M151 -> 0 | AD26: ='Return Distr.'!N151 -> 0 | AE26: ='Return Distr.'!O151 -> 0 | ... AG26: ='Return Distr.'!Q151 -> 0
K27: NLA Breakdown | L27: =UW!D21 -> 0 | M27: =UW!G29 -> 15 | O27: =UW!D52 -> Basis | P27: =UW!E52 -> BBSY | Q27: =UW!F52 -> BBSY | R27: =UW!G52 -> BBSY | U27: ='Return Distr.'!B152 -> Capital Value (Cap Rate) | X27: ='Return Distr.'!H152 -> 0 | Y27: ='Return Distr.'!I152 -> 0 | Z27: ='Return Distr.'!J152 -> 0 | AA27: ='Return Distr.'!K152 -> 0 | AB27: ='Return Distr.'!L152 -> 0 | AC27: ='Return Distr.'!M152 -> 0 | AD27: ='Return Distr.'!N152 -> 0 | AE27: ='Return Distr.'!O152 -> 0 | ... AG27: ='Return Distr.'!Q152 -> 0
K28: Units | L28: =UW!D22 -> 0 | M28: =UW!G28 -> 0 | O28: =UW!D53 -> Type | P28: =UW!E53 -> Floating | Q28: =UW!F53 -> Floating | R28: =UW!G53 -> Floating
K29: =K20 -> Gross Potential Rent (Storage) | L29: =L20 -> #DIV/0! | M29: =M20 -> 0 | O29: =UW!D54 -> Index (term average) | P29: =UW!E54 -> 0.039 | Q29: =UW!F54 -> 0.039 | R29: =UW!G54 -> 0.039 | U29: NTA Timeline (DCF Value) | X29: =X42 -> 1 | Y29: =Y42 -> 2 | Z29: =Z42 -> 3 | AA29: =AA42 -> 4 | AB29: =AB42 -> 5 | AC29: =AC42 -> 6 | AD29: =AD42 -> 7 | AE29: =AE42 -> 8 | ... AG29: =AG42 -> 10
O30: =UW!D55 -> Spread | P30: =UW!E55 -> 0.0215 | Q30: =UW!F55 -> 0.0215 | R30: =UW!G55 -> 0.0215 | U30: NTA per Unit | X30: ='Return Distr.'!H153 -> #DIV/0! | Y30: ='Return Distr.'!I153 -> #DIV/0! | Z30: ='Return Distr.'!J153 -> #DIV/0! | AA30: ='Return Distr.'!K153 -> #DIV/0! | AB30: ='Return Distr.'!L153 -> #DIV/0! | AC30: ='Return Distr.'!M153 -> #DIV/0! | AD30: ='Return Distr.'!N153 -> #DIV/0! | AE30: ='Return Distr.'!O153 -> #DIV/0! | ... AG30: ='Return Distr.'!Q153 -> #DIV/0!
O31: =UW!D56 -> Rate | P31: =UW!E56 -> 0.0605 | Q31: =UW!F56 -> 0.0605 | R31: =UW!G56 -> 0.0605
K32: Purchase | O32: =UW!D58 -> I/O Years | P32: =UW!E58 -> 2.75 | Q32: =UW!F58 -> 1.25 | R32: =UW!G58 -> 0 | U32: ='Return Distr.'!B153 -> Net Tangible Assets (DCF Value) | X32: 1 | Y32: =X32+1 -> 2 | Z32: =Y32+1 -> 3 | AA32: =Z32+1 -> 4 | AB32: =AA32+1 -> 5 | AC32: =AB32+1 -> 6 | AD32: =AC32+1 -> 7 | AE32: =AD32+1 -> 8 | AF32: =AE32+1 -> 9 | AG32: =AF32+1 -> 10
K33: =UW!L16 -> Purchase Price | L33: =M33/($L$27+$M$27) -> 0 | M33: =UW!M16 -> 0 | O33: =UW!D62 -> Start Date | P33: =UW!E62 -> 46112 | Q33: =UW!F62 -> 47149 | R33: =UW!G62 -> 48638 | U33: ='Return Distr.'!B156 -> 10 | V33: ='Return Distr.'!C156 -> #VALUE! | W33: ='Return Distr.'!G156 -> #DIV/0! | X33: ='Return Distr.'!H156 -> #DIV/0! | Y33: ='Return Distr.'!I156 -> #DIV/0! | Z33: ='Return Distr.'!J156 -> #DIV/0! | AA33: ='Return Distr.'!K156 -> #DIV/0! | AB33: ='Return Distr.'!L156 -> #DIV/0! | AC33: ='Return Distr.'!M156 -> #DIV/0! | AD33: ='Return Distr.'!N156 -> #DIV/0! | ... AG33: ='Return Distr.'!Q156 -> #DIV/0!
K34: Total Consideration w/o Reserves | L34: =M34/($L$27+$M$27) -> #DIV/0! | M34: =UW!M31-(UW!M26-UW!M41)-UW!M30 -> #DIV/0! | O34: =UW!D63 -> Payoff Month | P34: =UW!E63 -> 33 | Q34: =UW!F63 -> 48 | R34: =UW!G63 -> 48 | U34: ='Return Distr.'!B157 -> 7 | V34: ='Return Distr.'!C157 -> #VALUE! | W34: ='Return Distr.'!G157 -> #DIV/0! | X34: ='Return Distr.'!H157 -> #DIV/0! | Y34: ='Return Distr.'!I157 -> #DIV/0! | Z34: ='Return Distr.'!J157 -> #DIV/0! | AA34: ='Return Distr.'!K157 -> #DIV/0! | AB34: ='Return Distr.'!L157 -> #DIV/0! | AC34: ='Return Distr.'!M157 -> #DIV/0! | AD34: ='Return Distr.'!N157 -> #DIV/0!
K35: Total Consideration w/ Reserves | L35: =M35/($L$27+$M$27) -> #DIV/0! | M35: =UW!M37 -> #DIV/0! | U35: ='Return Distr.'!B158 -> 5 | V35: ='Return Distr.'!C158 -> #VALUE! | W35: ='Return Distr.'!G158 -> #DIV/0! | X35: ='Return Distr.'!H158 -> #DIV/0! | Y35: ='Return Distr.'!I158 -> #DIV/0! | Z35: ='Return Distr.'!J158 -> #DIV/0! | AA35: ='Return Distr.'!K158 -> #DIV/0! | AB35: ='Return Distr.'!L158 -> #DIV/0!
K36: Projected Closing Date | M36: =UW!I12 -> 46112 | O36: =UW!I46 -> Fee Structure
O37: =UW!I48 -> Shares Issued | R37: =UW!J48 -> NA | X37: 1 | Y37: =X37+1 -> 2 | Z37: =Y37+1 -> 3 | AA37: =Z37+1 -> 4 | AB37: =AA37+1 -> 5 | AC37: =AB37+1 -> 6 | AD37: =AC37+1 -> 7 | AE37: =AD37+1 -> 8 | AF37: =AE37+1 -> 9 | AG37: =AF37+1 -> 10
K38: Disposition | O38: =UW!I49 -> Share Price | R38: =UW!J49 -> 1 | U38: ='Return Distr.'!B162 -> 10 | V38: ='Return Distr.'!C162 -> #VALUE! | W38: ='Return Distr.'!G162 -> #DIV/0! | X38: ='Return Distr.'!H162 -> #DIV/0! | Y38: ='Return Distr.'!I162 -> #DIV/0! | Z38: ='Return Distr.'!J162 -> #DIV/0! | AA38: ='Return Distr.'!K162 -> #DIV/0! | AB38: ='Return Distr.'!L162 -> #DIV/0! | AC38: ='Return Distr.'!M162 -> 0 | AD38: ='Return Distr.'!N162 -> 0 | ... AG38: ='Return Distr.'!Q162 -> 0
K39: =UW!I29 -> Gross Sale | L39: =M39/($L$27+$M$27) -> 0 | M39: =UW!J29 -> 0 | O39: =UW!I50 -> Asset Management Fee | R39: =UW!J50 -> 0.008 | U39: ='Return Distr.'!B163 -> 7 | V39: ='Return Distr.'!C163 -> #VALUE! | W39: ='Return Distr.'!G163 -> #DIV/0! | X39: ='Return Distr.'!H163 -> #DIV/0! | Y39: ='Return Distr.'!I163 -> #DIV/0! | Z39: ='Return Distr.'!J163 -> #DIV/0! | AA39: ='Return Distr.'!K163 -> #DIV/0! | AB39: ='Return Distr.'!L163 -> #DIV/0! | AC39: ='Return Distr.'!M163 -> 0 | AD39: ='Return Distr.'!N163 -> 0
K40: =UW!I31 -> Net Sale | L40: =M40/($L$27+$M$27) -> 0 | M40: =UW!J31 -> 0 | O40: =UW!I51 -> Acquisition Fee | R40: =UW!J51 -> 0 | U40: ='Return Distr.'!B164 -> 5 | V40: ='Return Distr.'!C164 -> #VALUE! | W40: ='Return Distr.'!G164 -> #DIV/0! | X40: ='Return Distr.'!H164 -> #DIV/0! | Y40: ='Return Distr.'!I164 -> #DIV/0! | Z40: ='Return Distr.'!J164 -> #DIV/0! | AA40: ='Return Distr.'!K164 -> #DIV/0! | AB40: ='Return Distr.'!L164 -> #DIV/0!
K41: =UW!I34 -> Net Proceeds | L41: =M41/($L$27+$M$27) -> #DIV/0! | M41: =UW!J34 -> #DIV/0! | O41: =UW!I52 -> Development Fee | R41: =UW!J52 -> 0.05
K42: =UW!I39 -> Sale Price Val Option | L42: =UW!J39 -> Cap Rate | M42: =Val!E8 -> 0 | O42: =UW!I53 -> Construction Mgmt Fee | R42: =UW!J53 -> 0.009 | X42: 1 | Y42: =X42+1 -> 2 | Z42: =Y42+1 -> 3 | AA42: =Z42+1 -> 4 | AB42: =AA42+1 -> 5 | AC42: =AB42+1 -> 6 | AD42: =AC42+1 -> 7 | AE42: =AD42+1 -> 8 | AF42: =AE42+1 -> 9 | AG42: =AF42+1 -> 10
O43: =UW!I54 -> Property Mgmt Fee | R43: =UW!J54 -> 0.07 | U43: ='Return Distr.'!B168 -> 10 | V43: ='Return Distr.'!C168 -> #VALUE! | W43: ='Return Distr.'!G168 -> -80525 | X43: ='Return Distr.'!H168 -> #DIV/0! | Y43: ='Return Distr.'!I168 -> #DIV/0! | Z43: ='Return Distr.'!J168 -> #DIV/0! | AA43: ='Return Distr.'!K168 -> #DIV/0! | AB43: ='Return Distr.'!L168 -> #DIV/0! | AC43: ='Return Distr.'!M168 -> 0 | AD43: ='Return Distr.'!N168 -> 0 | ... AG43: ='Return Distr.'!Q168 -> 0
O44: =UW!I56 -> Property Mgmt Setup | R44: =UW!J56 -> 0 | U44: ='Return Distr.'!B169 -> 7 | V44: ='Return Distr.'!C169 -> #VALUE! | W44: ='Return Distr.'!G169 -> -80525 | X44: ='Return Distr.'!H169 -> #DIV/0! | Y44: ='Return Distr.'!I169 -> #DIV/0! | Z44: ='Return Distr.'!J169 -> #DIV/0! | AA44: ='Return Distr.'!K169 -> #DIV/0! | AB44: ='Return Distr.'!L169 -> #DIV/0! | AC44: ='Return Distr.'!M169 -> 0 | AD44: ='Return Distr.'!N169 -> 0
U45: ='Return Distr.'!B170 -> 5 | V45: ='Return Distr.'!C170 -> #VALUE! | W45: ='Return Distr.'!G170 -> -80525 | X45: ='Return Distr.'!H170 -> #DIV/0! | Y45: ='Return Distr.'!I170 -> #DIV/0! | Z45: ='Return Distr.'!J170 -> #DIV/0! | AA45: ='Return Distr.'!K170 -> #DIV/0! | AB45: ='Return Distr.'!L170 -> #DIV/0!
K48: Sources - Purchase Price | O48: % of Purchase Price | P48: % of Equity | U48: Sensitivity Analysis - Cap Rates
K49: Initial Debt | M49: 0 | O49: =M49/$M$51 -> #DIV/0! | P49: N/A | U49: =UW!C870 -> Exit Cap Rate: | V49: =UW!D870 -> -0.015 | W49: =UW!E870 -> -0.01 | X49: =UW!F870 -> -0.005 | Y49: =UW!G870 -> 0 | Z49: =UW!H870 -> 0.005 | AA49: =UW!I870 -> 0.01 | AB49: =UW!J870 -> 0.015
K50: Down Payment | M50: =UW!M16 -> 0 | O50: =M50/$M$51 -> #DIV/0! | P50: =M50/$M$82 -> #DIV/0! | U50: =UW!C871 -> XIRR-Levered (Deal) | V50: =UW!D871 -> #N/A | W50: =UW!E871 -> #N/A | X50: =UW!F871 -> #N/A | Y50: =UW!G871 -> #N/A | Z50: =UW!H871 -> #N/A | AA50: =UW!I871 -> #N/A | AB50: =UW!J871 -> #N/A
K51: Total Purchase Price | M51: =SUM(M49:M50) -> 0 | O51: =SUM(O49:O50) -> #DIV/0! | U51: =UW!C873 -> XIRR-Levered (Project) | V51: =UW!D873 -> #N/A | W51: =UW!E873 -> #N/A | X51: =UW!F873 -> #N/A | Y51: =UW!G873 -> #N/A | Z51: =UW!H873 -> #N/A | AA51: =UW!I873 -> #N/A | AB51: =UW!J873 -> #N/A
U52: =UW!C874 -> XIRR-Unlevered (Project) | V52: =UW!D874 -> #N/A | W52: =UW!E874 -> #N/A | X52: =UW!F874 -> #N/A | Y52: =UW!G874 -> #N/A | Z52: =UW!H874 -> #N/A | AA52: =UW!I874 -> #N/A | AB52: =UW!J874 -> #N/A
K53: Sources - Total Purchase | O53: % of Total Purchase | P53: % of Equity | U53: =UW!C875 -> Equity Multiple | V53: =UW!D875 -> #N/A | W53: =UW!E875 -> #N/A | X53: =UW!F875 -> #N/A | Y53: =UW!G875 -> #N/A | Z53: =UW!H875 -> #N/A | AA53: =UW!I875 -> #N/A | AB53: =UW!J875 -> #N/A
K54: Initial Debt | M54: =UW!M12 -> #DIV/0! | O54: =M54/$M$56 -> #DIV/0! | P54: N/A | U54: =UW!C876 -> DCF Value | V54: =UW!D876 -> #N/A | W54: =UW!E876 -> #N/A | X54: =UW!F876 -> #N/A | Y54: =UW!G876 -> #N/A | Z54: =UW!H876 -> #N/A | AA54: =UW!I876 -> #N/A | AB54: =UW!J876 -> #N/A
K55: Equity | M55: =M58-M54 -> #DIV/0! | O55: =M55/$M$56 -> #DIV/0! | P55: =M55/$M$82 -> #DIV/0! | U55: =UW!C877 -> Cap Rate Var for Sensitivity | V55: =UW!D877 -> 0.005
K56: Total Sources | M56: =SUM(M54:M55) -> #DIV/0! | O56: =SUM(O54:O55) -> #DIV/0!
K57: Uses - Total Purchase | O57: % of Total Purchase | P57: % of Equity | U57: =UW!C876 -> DCF Value
K58: =UW!L16 -> Purchase Price | M58: =UW!M16 -> 0 | O58: =M58/$M$66 -> #DIV/0! | P58: =M58/$M$82 -> #DIV/0! | U58: =UW!C880 -> Exit Cap Rate: | V58: =UW!D880 -> -0.015 | W58: =UW!E880 -> -0.01 | X58: =UW!F880 -> -0.005 | Y58: =UW!G880 -> 0 | Z58: =UW!H880 -> 0.005 | AA58: =UW!I880 -> 0.01 | AB58: =UW!J880 -> 0.015
K59: =UW!L17 -> Acquisition Fee | M59: =UW!M17 -> 0 | O59: =M59/$M$66 -> #DIV/0! | P59: =M59/$M$82 -> #DIV/0! | U59: =UW!C881 -> Gross Sale | V59: =UW!D881 -> #DIV/0! | W59: =UW!E881 -> #DIV/0! | X59: =UW!F881 -> #DIV/0! | Y59: =UW!G881 -> #DIV/0! | Z59: =UW!H881 -> #DIV/0! | AA59: =UW!I881 -> #DIV/0! | AB59: =UW!J881 -> #DIV/0!
K60: =UW!L18 -> Loan Fees | M60: =UW!M18 -> #DIV/0! | O60: =M60/$M$66 -> #DIV/0! | P60: =M60/$M$82 -> #DIV/0! | U60: =UW!C882 -> Sales Costs | V60: =UW!D882 -> #DIV/0! | W60: =UW!E882 -> #DIV/0! | X60: =UW!F882 -> #DIV/0! | Y60: =UW!G882 -> #DIV/0! | Z60: =UW!H882 -> #DIV/0! | AA60: =UW!I882 -> #DIV/0! | AB60: =UW!J882 -> #DIV/0!
K61: =UW!L20 -> Establishment Costs | M61: =UW!M20 -> 0 | O61: =M61/$M$66 -> #DIV/0! | P61: =M61/$M$82 -> #DIV/0! | U61: =UW!C883 -> Net Sale | V61: =UW!D883 -> #DIV/0! | W61: =UW!E883 -> #DIV/0! | X61: =UW!F883 -> #DIV/0! | Y61: =UW!G883 -> #DIV/0! | Z61: =UW!H883 -> #DIV/0! | AA61: =UW!I883 -> #DIV/0! | AB61: =UW!J883 -> #DIV/0!
K62: =UW!L21 -> Distribution Costs | M62: =UW!M21 -> 0 | O62: =M62/$M$66 -> #DIV/0! | P62: =M62/$M$82 -> #DIV/0! | U62: =UW!C884 -> Loan Repayment | V62: =UW!D884 -> 835.53546 | W62: =UW!E884 -> 835.53546 | X62: =UW!F884 -> 835.53546 | Y62: =UW!G884 -> 835.53546 | Z62: =UW!H884 -> 835.53546 | AA62: =UW!I884 -> 835.53546 | AB62: =UW!J884 -> 835.53546
K63: =UW!L22 -> Due Diligence | M63: =UW!M22 -> 100000 | O63: =M63/$M$66 -> #DIV/0! | P63: =M63/$M$82 -> #DIV/0! | U63: =UW!C885 -> Return of Equity | V63: =UW!D885 -> #DIV/0! | W63: =UW!E885 -> #DIV/0! | X63: =UW!F885 -> #DIV/0! | Y63: =UW!G885 -> #DIV/0! | Z63: =UW!H885 -> #DIV/0! | AA63: =UW!I885 -> #DIV/0! | AB63: =UW!J885 -> #DIV/0!
K64: =UW!L23 -> Conversion Costs | M64: =UW!M23 -> 0 | O64: =M64/$M$66 -> #DIV/0! | P64: =M64/$M$82 -> #DIV/0! | U64: =UW!C886 -> Net Sales Proceeds | V64: =UW!D886 -> #DIV/0! | W64: =UW!E886 -> #DIV/0! | X64: =UW!F886 -> #DIV/0! | Y64: =UW!G886 -> #DIV/0! | Z64: =UW!H886 -> #DIV/0! | AA64: =UW!I886 -> #DIV/0! | AB64: =UW!J886 -> #DIV/0!
K65: =UW!L25 -> Transer/Stamp Duty/GST | M65: =UW!M25 -> -19475 | O65: =M65/$M$66 -> #DIV/0! | P65: =M65/$M$82 -> #DIV/0!
K66: =UW!L31 -> Total Uses: | M66: =SUM(M58:M65) -> #DIV/0! | O66: =SUM(O58:O65) -> #DIV/0! | U66: =UW!C885 -> Return of Equity
U67: =UW!C889 -> Asking Rates: | V67: =UW!D889 -> #DIV/0! | W67: =UW!E889 -> #DIV/0! | X67: =UW!F889 -> #DIV/0! | Y67: =UW!G889 -> #DIV/0! | Z67: =UW!H889 -> #DIV/0! | AA67: =UW!I889 -> #DIV/0! | AB67: =UW!J889 -> #DIV/0!
K68: Construction | O68: % of Total Project | P68: % of Equity | U68: =UW!C890 -> IRR - Levered (Deal Level) | V68: =UW!D890 -> #DIV/0! | W68: =UW!E890 -> #DIV/0! | X68: =UW!F890 -> #DIV/0! | Y68: =UW!G890 -> #DIV/0! | Z68: =UW!H890 -> #DIV/0! | AA68: =UW!I890 -> #DIV/0! | AB68: =UW!J890 -> #DIV/0!
K69: Construction Funded by Debt | M69: =UW!M40 -> 0 | O69: =M69/$M$79 -> #DIV/0! | P69: N/A | U69: =UW!C891 -> IRR - Levered (Project Level) | V69: =UW!D891 -> #DIV/0! | W69: =UW!E891 -> #DIV/0! | X69: =UW!F891 -> #DIV/0! | Y69: =UW!G891 -> #DIV/0! | Z69: =UW!H891 -> #DIV/0! | AA69: =UW!I891 -> #DIV/0! | AB69: =UW!J891 -> #DIV/0!
K70: Construction Funded by Equity | M70: =UW!M41 -> 0 | O70: =M70/$M$79 -> #DIV/0! | P70: =M70/$M$82 -> #DIV/0! | U70: =UW!C892 -> IRR - Unlevered | V70: =UW!D892 -> #DIV/0! | W70: =UW!E892 -> #DIV/0! | X70: =UW!F892 -> #DIV/0! | Y70: =UW!G892 -> #DIV/0! | Z70: =UW!H892 -> #DIV/0! | AA70: =UW!I892 -> #DIV/0! | AB70: =UW!J892 -> #DIV/0!
K71: Total Cost of Construction | M71: =UW!M42 -> 0 | O71: =M71/$M$79 -> #DIV/0! | P71: N/A | U71: =UW!C893 -> Equity Multiple: | V71: =UW!D893 -> #DIV/0! | W71: =UW!E893 -> #DIV/0! | X71: =UW!F893 -> #DIV/0! | Y71: =UW!G893 -> #DIV/0! | Z71: =UW!H893 -> #DIV/0! | AA71: =UW!I893 -> #DIV/0! | AB71: =UW!J893 -> #DIV/0!
K72: Total Cost of Construction + Land | M72: =UW!M43 -> 0 | O72: =M72/$M$79 -> #DIV/0! | P72: N/A | U72: =UW!C894 -> Yield on Cost | V72: =UW!D894 -> #DIV/0! | W72: =UW!E894 -> #DIV/0! | X72: =UW!F894 -> #DIV/0! | Y72: =UW!G894 -> #DIV/0! | Z72: =UW!H894 -> #DIV/0! | AA72: =UW!I894 -> #DIV/0! | AB72: =UW!J894 -> #DIV/0!
K73: Construction + Land + Closing Costs | M73: =UW!M44 -> 0 | O73: =M73/$M$79 -> #DIV/0! | P73: N/A | U73: =UW!C895 -> Asking Rate Sensitivity | V73: =UW!D895 -> 0.05
K75: Total Consideration | O75: % of Total Project | P75: % of Equity | U75: =UW!C894 -> Yield on Cost
K76: Interest Reserve (Debt) | M76: =UW!M30 -> #DIV/0! | O76: =M76/$M$79 -> #DIV/0! | P76: N/A | U76: =UW!C898 -> Construction Cost | V76: =UW!D898 -> 25646877 | W76: =UW!E898 -> 25896877 | X76: =UW!F898 -> 26146877 | Y76: =UW!G898 -> 26396877 | Z76: =UW!H898 -> 26646877 | AA76: =UW!I898 -> 26896877 | AB76: =UW!J898 -> 27146877
K77: Operating Reserve (Equity) | M77: =UW!M26-UW!M41 -> #DIV/0! | O77: =M77/$M$79 -> #DIV/0! | P77: =M77/$M$82 -> #DIV/0! | U77: =UW!C899 -> IRR - Levered (Deal Level) | V77: =UW!D899 -> 0 | W77: =UW!E899 -> 0 | X77: =UW!F899 -> 0 | Y77: =UW!G899 -> 0 | Z77: =UW!H899 -> 0 | AA77: =UW!I899 -> 0 | AB77: =UW!J899 -> 0
K78: Total Reserves | M78: =SUM(M76:M77) -> #DIV/0! | O78: =M78/$M$79 -> #DIV/0! | P78: N/A | U78: =UW!C900 -> IRR - Levered (Project Level) | V78: =UW!D900 -> 0 | W78: =UW!E900 -> 0 | X78: =UW!F900 -> 0 | Y78: =UW!G900 -> 0 | Z78: =UW!H900 -> 0 | AA78: =UW!I900 -> 0 | AB78: =UW!J900 -> 0
K79: Total Consideration | M79: =M78+M73 -> #DIV/0! | O79: =O78+O73 -> #DIV/0! | U79: =UW!C901 -> IRR - Unlevered | V79: =UW!D901 -> 0 | W79: =UW!E901 -> 0 | X79: =UW!F901 -> 0 | Y79: =UW!G901 -> 0 | Z79: =UW!H901 -> 0 | AA79: =UW!I901 -> 0 | AB79: =UW!J901 -> 0
U80: =UW!C902 -> Equity Multiple: | V80: =UW!D902 -> 0 | W80: =UW!E902 -> 0 | X80: =UW!F902 -> 0 | Y80: =UW!G902 -> 0 | Z80: =UW!H902 -> 0 | AA80: =UW!I902 -> 0 | AB80: =UW!J902 -> 0
K81: Total Sources | O81: % of Total Costs | P81: % of Equity | U81: =UW!C903 -> Yield on Cost | V81: =UW!D903 -> 0 | W81: =UW!E903 -> 0 | X81: =UW!F903 -> 0 | Y81: =UW!G903 -> 0 | Z81: =UW!H903 -> 0 | AA81: =UW!I903 -> 0 | AB81: =UW!J903 -> 0
K82: Equity | M82: =M70+M55+M77+SUM(M59:M65) -> #DIV/0! | O82: =M82/$M$84 -> #DIV/0! | P82: =M82/$M$82 -> #DIV/0! | U82: =UW!C904 -> Construction Price Sensitivity | V82: =UW!D904 -> 250000
K83: Debt | M83: =M76+M69+M54 -> #DIV/0! | O83: =M83/$M$84 -> #DIV/0!
K84: Total Sources | M84: =SUM(M82:M83) -> #DIV/0! | O84: =SUM(O82:O83) -> #DIV/0!

Sheet Expansion
C2: Expansion
C3: GFA | D3: ='Unit Mix Generator'!P19 -> 0
C4: NLA | D4: ='Unit Mix Generator'!Q19 -> 0
C5: Av Size | D5: ='Unit Mix Generator'!C7 -> 0
C6: # of Units | D6: =D4/D5 -> #DIV/0!
C7: Starting Occ. | D7: =E16 -> 0
C8: Stabilisation | D8: 0.85 | F8: =D10/12 -> 1
C9: Occ Month | D9: =OFFSET($D$14,,1+COUNTIF($E$16:$O$16,D16)) -> 0 | E9: **12 months construction from 14 April 2021 cross referenced on UW page
C10: Stabilisation Month | D10: =OFFSET($D$15,,11-COUNTIF($E$16:$N$16,$O$16)) -> 12
C11: Discount Exp | D11: 0.1
C13: Lease-Up Timeline Expansion | E13: 1 | F13: =E13+1 -> 2 | G13: =F13+1 -> 3 | H13: =G13+1 -> 4 | I13: =H13+1 -> 5 | J13: =I13+1 -> 6 | K13: =J13+1 -> 7 | L13: =K13+1 -> 8 | M13: =L13+1 -> 9 | ... O13: =N13+1 -> 11
C14: Start Month | D14: =IF(E17>0,E14,IF(F17>0,F14,IF(G17>0,G14,IF(H17>0,H14,IF(I17>0,I14))))) -> FALSE | E14: 1 | F14: =E15+1 -> 13 | G14: =F15+1 -> 19 | H14: 46 | I14: 49 | J14: =I15+1 -> 61 | K14: =J15+1 -> 73 | L14: =K15+1 -> 85 | M14: =L15+1 -> 94 | N14: =M15+1 -> 109 | O14: =N15+1 -> 121
C15: End Month | E15: 12 | F15: 18 | G15: 36 | H15: 48 | I15: 60 | J15: 72 | K15: 84 | L15: 93 | M15: 108 | N15: 120 | O15: 132
C16: Year End Occupancy | E16: 0 | F16: 0 | G16: 0 | H16: 0 | I16: 0 | J16: 0 | K16: 0 | L16: 0 | M16: 0 | N16: 0 | O16: 0
C17: Average Monthly Lease-Up | E17: =(E16-D7)/(E15-E14)*$D$4 -> 0 | F17: =(F16-E16)/(F15-F14)*$D$4 -> 0 | G17: =(G16-F16)/(G15-G14)*$D$4 -> 0 | H17: =(H16-G16)/(H15-H14)*$D$4 -> 0 | I17: =(I16-H16)/(I15-I14)*$D$4 -> 0 | J17: =(J16-I16)/(J15-J14)*$D$4 -> 0 | K17: =(K16-J16)/(K15-K14)*$D$4 -> 0 | L17: =(L16-K16)/(L15-L14)*$D$4 -> 0 | M17: =(M16-L16)/(M15-M14)*$D$4 -> 0 | ... O17: =(O16-N16)/(O15-O14)*$D$4 -> 0
C18: Annual Lease-Up | E18: =E17*12 -> 0 | F18: =F17*12 -> 0 | G18: =G17*12 -> 0 | H18: =H17*12 -> 0 | I18: =I17*12 -> 0 | J18: =J17*12 -> 0 | K18: =K17*12 -> 0 | L18: =L17*12 -> 0 | ... O18: =O17*12 -> 0
C19: Avg Units/Month | E19: =E17/$D$5 -> #DIV/0! | F19: =F17/$D$5 -> #DIV/0! | G19: =G17/$D$5 -> #DIV/0! | H19: =H17/$D$5 -> #DIV/0! | I19: =I17/$D$5 -> #DIV/0! | J19: =J17/$D$5 -> #DIV/0! | K19: =K17/$D$5 -> #DIV/0! | L19: =L17/$D$5 -> #DIV/0! | ... O19: =O17/$D$5 -> #DIV/0!
C21: Revenue Assumptions | E21: 1 | F21: =E21+1 -> 2 | G21: =F21+1 -> 3 | H21: =G21+1 -> 4 | I21: =H21+1 -> 5 | J21: =I21+1 -> 6 | K21: =J21+1 -> 7 | L21: =K21+1 -> 8 | M21: =L21+1 -> 9 | ... O21: =N21+1 -> 11
C22: Discount (recurring) | E22: =-A212 -> 0 | F22: 0.3 | G22: 0.25 | H22: 0.2 | I22: 0.2 | J22: 0.15 | K22: 0.12 | L22: 0.1 | M22: 0.1 | N22: 0.1 | O22: 0.1
C25: Occupancy Growth | E25: {=IF(AND(E$28>=$D$9,E$28<=$D$10),INDEX($E$19:$O$19,,MATCH(E$27,$E$13:$O$13,0)),0)*$D$5/$D$4} -> #DIV/0! | F25: {=IF(AND(F$28>=$D$9,F$28<=$D$10),INDEX($E$19:$O$19,,MATCH(F$27,$E$13:$O$13,0)),0)*$D$5/$D$4} -> #DIV/0! | G25: {=IF(AND(G$28>=$D$9,G$28<=$D$10),INDEX($E$19:$O$19,,MATCH(G$27,$E$13:$O$13,0)),0)*$D$5/$D$4} -> #DIV/0! | H25: {=IF(AND(H$28>=$D$9,H$28<=$D$10),INDEX($E$19:$O$19,,MATCH(H$27,$E$13:$O$13,0)),0)*$D$5/$D$4} -> #DIV/0! | I25: {=IF(AND(I$28>=$D$9,I$28<=$D$10),INDEX($E$19:$O$19,,MATCH(I$27,$E$13:$O$13,0)),0)*$D$5/$D$4} -> #DIV/0! | J25: {=IF(AND(J$28>=$D$9,J$28<=$D$10),INDEX($E$19:$O$19,,MATCH(J$27,$E$13:$O$13,0)),0)*$D$5/$D$4} -> #DIV/0! | K25: {=IF(AND(K$28>=$D$9,K$28<=$D$10),INDEX($E$19:$O$19,,MATCH(K$27,$E$13:$O$13,0)),0)*$D$5/$D$4} -> #DIV/0! | L25: {=IF(AND(L$28>=$D$9,L$28<=$D$10),INDEX($E$19:$O$19,,MATCH(L$27,$E$13:$O$13,0)),0)*$D$5/$D$4} -> #DIV/0! | ... EF25: {=IF(AND(EF$28>=$D$9,EF$28<=$D$10),INDEX($E$19:$O$19,,MATCH(EF$27,$E$13:$O$13,0)),0)*$D$5/$D$4} -> #DIV/0!
C26: Year End Occ | E26: =E25 -> #DIV/0! | F26: =F25+E26 -> #DIV/0! | G26: =G25+F26 -> #DIV/0! | H26: =H25+G26 -> #DIV/0! | I26: =I25+H26 -> #DIV/0! | J26: =J25+I26 -> #DIV/0! | K26: =K25+J26 -> #DIV/0! | L26: =L25+K26 -> #DIV/0! | M26: =M25+L26 -> #DIV/0! | ... EF26: =EF25+EE26 -> #DIV/0!
C27: Year | E27: =ROUNDUP(E28/12,0) -> 1 | F27: =ROUNDUP(F28/12,0) -> 1 | G27: =ROUNDUP(G28/12,0) -> 1 | H27: =ROUNDUP(H28/12,0) -> 1 | I27: =ROUNDUP(I28/12,0) -> 1 | J27: =ROUNDUP(J28/12,0) -> 1 | K27: =ROUNDUP(K28/12,0) -> 1 | L27: =ROUNDUP(L28/12,0) -> 1 | ... EF27: =ROUNDUP(EF28/12,0) -> 11
C28: Month | E28: 1 | F28: =E28+1 -> 2 | G28: =F28+1 -> 3 | H28: =G28+1 -> 4 | I28: =H28+1 -> 5 | J28: =I28+1 -> 6 | K28: =J28+1 -> 7 | L28: =K28+1 -> 8 | M28: =L28+1 -> 9 | ... EF28: =EE28+1 -> 132
C29: Revenue
C30: GPR | E30: {=INDEX(UW!$E$613:$EF$613,,MATCH(E28,UW!$E$612:$EF$612,0))/UW!$D$21*$D$4} -> #DIV/0! | F30: {=INDEX(UW!$E$613:$EF$613,,MATCH(F28,UW!$E$612:$EF$612,0))/UW!$D$21*$D$4} -> #DIV/0! | G30: {=INDEX(UW!$E$613:$EF$613,,MATCH(G28,UW!$E$612:$EF$612,0))/UW!$D$21*$D$4} -> #DIV/0! | H30: {=INDEX(UW!$E$613:$EF$613,,MATCH(H28,UW!$E$612:$EF$612,0))/UW!$D$21*$D$4} -> #DIV/0! | I30: {=INDEX(UW!$E$613:$EF$613,,MATCH(I28,UW!$E$612:$EF$612,0))/UW!$D$21*$D$4} -> #DIV/0! | J30: {=INDEX(UW!$E$613:$EF$613,,MATCH(J28,UW!$E$612:$EF$612,0))/UW!$D$21*$D$4} -> #DIV/0! | K30: {=INDEX(UW!$E$613:$EF$613,,MATCH(K28,UW!$E$612:$EF$612,0))/UW!$D$21*$D$4} -> #DIV/0! | L30: {=INDEX(UW!$E$613:$EF$613,,MATCH(L28,UW!$E$612:$EF$612,0))/UW!$D$21*$D$4} -> #DIV/0! | ... EF30: {=INDEX(UW!$E$613:$EF$613,,MATCH(EF28,UW!$E$612:$EF$612,0))/UW!$D$21*$D$4} -> #DIV/0!
C31: Vacancy | E31: =-IF(E$28<$D$9,E$30,(1-E$26)*E$30) -> #DIV/0! | F31: =-IF(F$28<$D$9,F$30,(1-F$26)*F$30) -> #DIV/0! | G31: =-IF(G$28<$D$9,G$30,(1-G$26)*G$30) -> #DIV/0! | H31: =-IF(H$28<$D$9,H$30,(1-H$26)*H$30) -> #DIV/0! | I31: =-IF(I$28<$D$9,I$30,(1-I$26)*I$30) -> #DIV/0! | J31: =-IF(J$28<$D$9,J$30,(1-J$26)*J$30) -> #DIV/0! | K31: =-IF(K$28<$D$9,K$30,(1-K$26)*K$30) -> #DIV/0! | L31: =-IF(L$28<$D$9,L$30,(1-L$26)*L$30) -> #DIV/0! | ... EF31: =-IF(EF$28<$D$9,EF$30,(1-EF$26)*EF$30) -> #DIV/0!
C32: Gross Rental Income | E32: =SUM(E30:E31) -> #DIV/0! | F32: =SUM(F30:F31) -> #DIV/0! | G32: =SUM(G30:G31) -> #DIV/0! | H32: =SUM(H30:H31) -> #DIV/0! | I32: =SUM(I30:I31) -> #DIV/0! | J32: =SUM(J30:J31) -> #DIV/0! | K32: =SUM(K30:K31) -> #DIV/0! | L32: =SUM(L30:L31) -> #DIV/0! | ... EF32: =SUM(EF30:EF31) -> #DIV/0!
C33: Discount (Recurring) | E33: =-E32*SUMIF($E$21:$O$21,E$27,$E$22:$O$22) -> #DIV/0! | F33: =-F32*SUMIF($E$21:$O$21,F$27,$E$22:$O$22) -> #DIV/0! | G33: =-G32*SUMIF($E$21:$O$21,G$27,$E$22:$O$22) -> #DIV/0! | H33: =-H32*SUMIF($E$21:$O$21,H$27,$E$22:$O$22) -> #DIV/0! | I33: =-I32*SUMIF($E$21:$O$21,I$27,$E$22:$O$22) -> #DIV/0! | J33: =-J32*SUMIF($E$21:$O$21,J$27,$E$22:$O$22) -> #DIV/0! | K33: =-K32*SUMIF($E$21:$O$21,K$27,$E$22:$O$22) -> #DIV/0! | L33: =-L32*SUMIF($E$21:$O$21,L$27,$E$22:$O$22) -> #DIV/0! | ... EF33: =-EF32*SUMIF($E$21:$O$21,EF$27,$E$22:$O$22) -> #DIV/0!
C34: Net Rental Income (Yield | E34: =SUM(E32:E33) -> #DIV/0! | F34: =SUM(F32:F33) -> #DIV/0! | G34: =SUM(G32:G33) -> #DIV/0! | H34: =SUM(H32:H33) -> #DIV/0! | I34: =SUM(I32:I33) -> #DIV/0! | J34: =SUM(J32:J33) -> #DIV/0! | K34: =SUM(K32:K33) -> #DIV/0! | L34: =SUM(L32:L33) -> #DIV/0! | ... EF34: =SUM(EF32:EF33) -> #DIV/0!
C35: Net Yield | E35: =IFERROR(E34/($D$4*E26)*12,"-") -> - | F35: =IFERROR(F34/($D$4*F26)*12,"-") -> - | G35: =IFERROR(G34/($D$4*G26)*12,"-") -> - | H35: =IFERROR(H34/($D$4*H26)*12,"-") -> - | I35: =IFERROR(I34/($D$4*I26)*12,"-") -> - | J35: =IFERROR(J34/($D$4*J26)*12,"-") -> - | K35: =IFERROR(K34/($D$4*K26)*12,"-") -> - | L35: =IFERROR(L34/($D$4*L26)*12,"-") -> - | ... EF35: =IFERROR(EF34/($D$4*EF26)*12,"-") -> -

Sheet Store Budget

Sheet UW
C1: Proforma_Annual | D1: Expense_Details | E1: Debt | F1: Dev_Budget | G1: IFS
C2: Baseline | D2: Proforma_Monthly | E2: Unit_Mix | F2: Sensitivity
B4: Dashboard
C6: Property Description | I6: Purchase Price | M6: Cap Rate | P6: Stamp Duty Calculator
C7: Property Name | F7: Location (scale: 1-5) | J7: Amount | K7: =IF(D13='Model Inputs & Calcs'!B17,"Per Hectare","Per SM") -> Per SM | L7: =IF(D13='Model Inputs & Calcs'!B17,"Per SM","Per NRSM") -> Per NRSM | M7: Seller | N7: Baseline | P7: What State Is The Property? | Q7: QLD
C8: Street Address | F8: Visibility (scale: 1-5) | I8: Asking Price | K8: =IF($D$13='Model Inputs & Calcs'!$B$17,J8/$D$12,J8/$D$20) -> #DIV/0! | L8: =IF($D$13='Model Inputs & Calcs'!$B$17,$J$8/$E$12,J8/$D$21) -> #DIV/0! | M8: =IFERROR($H$550/$J$8,"NA") -> NA | N8: =IFERROR($D$550/$J$8,"NA") -> NA | P8: QLD | Q8: =IF($Q$15="Yes",38025+0.0575*(UW!J9-1000000),(38025+0.0575*(UW!J9*1.1-1000000))) -> -19475
C9: City | F9: Curb Appeal (scale: 1-5) | I9: Offer Price | K9: =IF($D$13='Model Inputs & Calcs'!$B$17,J9/$D$12,J9/$D$20) -> #DIV/0! | L9: =IF($D$13='Model Inputs & Calcs'!$B$17,$J$9/$E$12,J9/$D$21) -> #DIV/0! | M9: =$H$550/J9 -> #DIV/0! | N9: =$D$550/$J$9 -> #DIV/0! | P9: NSW | Q9: =IF($Q$15="Yes",40490+0.055*(UW!J9-1000000),40490+0.055*(UW!J9*1.1-1000000)) -> -14510
C10: State, Postal | F10: Access (scale: 1-5) | P10: VIC | Q10: =IF($Q$15="Yes",0.055*UW!J9,0.055*UW!J9*1.1) -> 0
C11: Parcel # | F11: # of Buildings | I11: Projected Closing Date | K11: Absentee Owner Surcharge | L11: Sources | N11: Per NRSM | P11: SA | Q11: =IF($Q$15="Yes",21330+0.055*(UW!J9-500000),21330+0.055*(UW!J9-500000)*1.1) -> -8920
C12: Parcel Size | D12: 0 | E12: =D12*10000 -> 0 | F12: # of Stories | I12: 46112 | K12: Yes | L12: Initial Debt | M12: =E47 -> #DIV/0! | N12: =M12/$D$21 -> #DIV/0! | O12: =M12/M14 -> #DIV/0! | P12: WA | Q12: =IF($Q$15="Yes",19665+0.0515*(UW!J9-500000),19665+0.0515*(UW!J9-500000)*1.1) -> -8660
C13: Investment Type | D13: Existing | F13: # of Elevators | L13: Equity | M13: =M31-M12 -> #DIV/0! | N13: =M13/$D$21 -> #DIV/0! | O13: =M13/M14 -> #DIV/0! | P13: NT | Q13: TBD
C14: Broker | F14: Broker Name | I14: Metrics | K14: Fees | L14: Total Sources: | M14: =SUM(M12:M13) -> #DIV/0! | N14: =M14/$D$21 -> #DIV/0! | P14: TAS | Q14: =IF($Q$15="Yes",27810+0.045*(UW!J9-725000),27810+0.045*(UW!J9-725000)*1.1) -> -8077.5
C15: Zoning | F15: Flood Zone | I15: IRR (Post fees & taxes) | J15: =XIRR($D$756:$EF$756,$D$607:$EF$607) -> #DIV/0! | K15: Yes | L15: Uses | N15: Per NRSM | P15: Going Concern? | Q15: No
C16: Traffic Count | F16: Traffic Count Street | I16: Equity Multiple | J16: =SUM(E755:EF755)/Total_Equity -> #DIV/0! | L16: Purchase Price | M16: =J9 -> 0 | N16: =M16/$D$21 -> #DIV/0!
C17: Renovated | F17: Software | I17: Stab. YoC - Untrended | J17: =Sheet1!C10/UW!M14 -> #DIV/0! | K17: FOS incl. in valuation | L17: Acquisition Fee | M17: =J51*J9 -> 0 | N17: =M17/$D$21 -> #DIV/0! | P17: Unlevered Equity Loaded
C18: Manager Apartment? | F18: Year Built | I18: Stab. YoC - Untrended (Norm.) | J18: =Sheet1!C13/UW!M14 -> #DIV/0! | K18: No | L18: Loan Fees | M18: =M12*(E49+E50) -> #DIV/0! | N18: =M18/$D$21 -> #DIV/0! | P18: Total Uses | Q18: =UW!M31 -> #DIV/0!
C19: Rental Summary | I19: Stab. YoC - Trended | J19: =(OFFSET(D714,,J25)*12)/M14 -> #DIV/0! | L19: GST Required | M19: 0 | N19: =M19/$D$21 -> #DIV/0! | P19: Minus Interest Reserve | Q19: =-SUM(UW!E411:O411) -> #DIV/0!
C20: Gross SM (Entire Facility) | D20: ='Unit Mix Generator'!P19 -> 0 | E20: =D21+D28+G28+G21+D34 -> 0 | F20: Office? | G20: No | I20: Stab. YoC - Trended (Norm.) | J20: =((OFFSET(D714,,J25)+OFFSET(D709,,J25)+OFFSET(D710,,J25))*12)/M14 -> #DIV/0! | K20: ManCo | L20: Establishment Costs | M20: =D557 -> 0 | N20: =M20/$D$21 -> #DIV/0! | P20: Minus Loan Fees | Q20: =-UW!M18 -> #DIV/0!
C21: Net Rentable SM (Storage Only) | D21: =IF($C$444='Model Inputs & Calcs'!$B$5,$C$451,'Comps & Unit Mix'!AW328) -> 0 | E21: =E20/D20 -> #DIV/0! | F21: Net Rentable SM (Office) | G21: ='Comps & Unit Mix'!AW426 -> 0 | I21: Exit YoC | J21: =OFFSET(D714,,J36)*12/M14 -> #DIV/0! | K21: No | L21: Distribution Costs | M21: =D558 -> 0 | N21: =M21/$D$21 -> #DIV/0! | P21: Minus Assump/Prepay/Defease | Q21: =-UW!M19 -> 0
C22: # Storage Units | D22: =IF($C$444='Model Inputs & Calcs'!$B$5,C452,'Comps & Unit Mix'!AV328) -> 0 | E22: =(D25*D21+D31*D28)/E20 -> #DIV/0! | F22: # Office Units | G22: ='Comps & Unit Mix'!AV426 -> 0 | I22: Exit YoC (Norm.) | J22: =(OFFSET(D714,,J36)+OFFSET(D709,,J25)+OFFSET(D710,,J25))*12/M14 -> #DIV/0! | L22: Due Diligence | M22: =D559 -> 100000 | N22: =M22/$D$21 -> #DIV/0! | P22: Equity Required | Q22: =SUM(Q18:Q21) -> #DIV/0!
C23: Average Unit Size (Storage) | D23: =D21/D22 -> #DIV/0! | F23: Average Office Size | G23: =G21/G22 -> #DIV/0! | I23: Exit Cap Rate | J23: =Val!E7 -> 0 | L23: Conversion Costs | M23: =D560 -> 0 | N23: =M23/$D$21 -> #DIV/0! | P23: Unlevered Equity Loaded | Q23: =Q22 -> #DIV/0!
C24: Average Monthly Lease Up (m2) | D24: =SUM(E92:O92)/(G95-E95) -> 0 | F24: Term? | G24: Month to Month | I24: Stab. Occupancy | J24: =MAX(E97:O97) -> 0 | L24: Capex | M24: =D561 -> 0
C25: Occupancy | D25: =IF($C$444='Model Inputs & Calcs'!$B$5,$C$450,IF($C$444='Model Inputs & Calcs'!$B$6,$D$218,"")) -> 0 | E25: =D219 -> #DIV/0! | F25: Occupancy | G25: ='Comps & Unit Mix'!AR426/'Comps & Unit Mix'!AW426 -> #DIV/0! | I25: Stab. Month | J25: =IF(E97=J24,E96,IF(F97=J24,F96,IF(G97=J24,G96,IF(H97=J24,H96,IF(I97=J24,I96))))) -> 12 | L25: Transer/Stamp Duty/GST | M25: =INDEX(UW!Q8:Q14,(MATCH(UW!Q7,UW!P8:P14,0))) -> -19475 | N25: =M25/$D$21 -> #DIV/0! | P25: Remaining Equity Contribution after Refi 1
C26: Asking Rents | D26: =D455/D21 -> #DIV/0! | E26: =IFERROR(D461/SUM('Comps & Unit Mix'!AR209:AR326),"-") -> - | F26: Asking Rents (Office) | G26: ='Comps & Unit Mix'!BE427 -> 0 | L26: Constr/OpEx/Intrst (Equity) | M26: =SUM($E$748:$EF$748)-M30-M28-M27 -> #DIV/0! | N26: =M26/$D$21 -> #DIV/0! | P26: Return (Addtl Contr) of Equity | Q26: =C57+M29 -> #DIV/0!
C27: RV/Parking? | D27: No | F27: Warehouse? | G27: No | L27: Const Holdback (Debt) | M27: =E43 -> 0 | N27: =M27/$D$21 -> #DIV/0! | P27: Year Returned | Q27: =CEILING(UW!E63,12)/12 -> 3 | R27: =E63 -> 33
C28: RV/Parking NLA | D28: ='Comps & Unit Mix'!AW439 -> 0 | E28: 0% on Exp. Start | F28: Warehouse NLA | G28: ='Workstore Sales'!C6 -> 0 | I28: Sale | L28: Op Ex Holdback (Debt) | M28: =E44 -> 0 | N28: =M28/$D$21 -> #DIV/0! | P28: Remaining Loaded Equity | Q28: =UW!M35-Q26 -> #DIV/0!
C29: # Parking Spaces | D29: ='Comps & Unit Mix'!AV439 -> 0 | F29: # Warehouse Units | G29: ='Workstore Sales'!C2 -> 15 | I29: Gross Sale | J29: =IF($J$39='Model Inputs & Calcs'!$C$5,OFFSET(Val!$C$99,,UW!J36),OFFSET(Val!$C$98,,UW!$J$36)) -> 0 | L29: Interest Reserve (Equity) | M29: =E45 -> 0 | N29: =M29/$D$21 -> #DIV/0!
C30: Average Parking Size | D30: =IFERROR(D28/D29,0) -> 0 | F30: Average Warehouse Size | G30: ='Workstore Sales'!C5 -> 0 | I30: Sales Costs | J30: =-J29*SUM(J37:J38) -> 0 | L30: Interest Reserve (Debt) | M30: =E46 -> #DIV/0! | N30: =M30/$D$21 -> #DIV/0! | P30: Remaining Equity Contribution after Refi 2
C31: Occupancy | D31: =IFERROR('Comps & Unit Mix'!AY440,"0") -> 0 | E31: =D624 -> 0 | F31: Occupancy | G31: =IFERROR('Comps & Unit Mix'!AR414/'Comps & Unit Mix'!AW414,0) -> 0 | I31: Net Sale | J31: =SUM(J29:J30) -> 0 | L31: Total Uses: | M31: =SUM(M16:M30) -> #DIV/0! | N31: =M31/$D$21 -> #DIV/0! | P31: Return (Addtl Contr) of Equity | Q31: =UW!C64 -> 835.53546
C32: Asking Rents (RV/Parking) | D32: =IFERROR('Comps & Unit Mix'!BE440,"0") -> 0 | F32: Sale Rate (Warehouse) | G32: ='Workstore Sales'!C3 -> 5300 | I32: Loan Repayment | J32: =-HLOOKUP($J$36,$E$855:$DT$860,6,FALSE) -> 835.53546 | N32: Per NSRM | P32: Year Returned | Q32: =CEILING(UW!F63,12)/12 -> 4 | R32: =F63 -> 48
C33: Expansion? | D33: No | F33: #Expansion Units | G33: =IF(D33="Yes",'Comps & Unit Mix'!AV399,0) -> 0 | I33: Return of Equity | J33: =-Total_Equity -> #DIV/0! | L33: Equity | M33: =M13 -> #DIV/0! | N33: =M33/$D$21 -> #DIV/0! | P33: Remaining Loaded Equity | Q33: =Q28-Q31 -> #DIV/0!
C34: Expansion NLA | D34: =IF(D33="Yes",'Comps & Unit Mix'!AW399,0) -> 0 | E34: ='Comps & Unit Mix'!AY400 -> 0 | F34: Average Expansion Size | G34: =D34/G33 -> #DIV/0! | I34: Net Proceeds | J34: =SUM(J31:J33) -> #DIV/0!
C35: Notes: | I35: Disposition Assumptions | L35: Equity | M35: =SUM(M33:M34) -> #DIV/0! | N35: =M35/$D$21 -> #DIV/0! | P35: Site Cover | Q35: =('Unit Mix Generator'!P14+D28+'Workstore Sales'!C33)/UW!E12 -> #DIV/0!
I36: Sale Year | J36: {=OFFSET(Val!C15,,(MATCH('Model Inputs & Calcs'!C12,Val!$D$16:$EE$16,0)),,)} -> 48 | L36: Debt | M36: =M12 -> #DIV/0! | N36: =M36/$D$21 -> #DIV/0! | P36: WACC | Q36: =((M36/M37)*E56)+((M35/M37)*#REF!) -> #DIV/0!
I37: Sales Broker Commission | J37: 0.01 | L37: Total Consideration: | M37: =SUM(M35:M36) -> #DIV/0! | N37: =M37/$D$21 -> #DIV/0!
I38: Cost of Sales | J38: 0.0025 | P38: =C770 -> Perfomance Fee Calculations (Paid at Sale)
I39: Sale Price Val Option | J39: Cap Rate | L39: Construction | P39: =C771 -> NPV | Q39: =D771 -> #DIV/0!
C40: Debt | E40: Initial Loan | F40: Refinance Loan 1 | G40: Refinance Loan 2 | I40: Hurdle Rate | J40: 0.1 | L40: Construction (Debt) | M40: =M27 -> 0 | N40: =M40/$D$21 -> #DIV/0! | P40: =C772 -> Duration of Investment | Q40: =D772 -> 4.0027397
D41: Debt Type | E41: Permanent | F41: Permanent | G41: Permanent | I41: Hurdle Rate Reference | L41: Construction (Equity) | M41: =M42-M40 -> 0 | N41: =M41/$D$21 -> #DIV/0! | P41: =C773 -> Total Realisation Value | Q41: =D773 -> #DIV/0!
C42: Holdback Structure | D42: Initial Loan Amount | E42: =UW!J9*UW!C49 -> 0 | F42: =IF(C52="yes",C54*C55,0) -> -835.53546 | G42: =IF(C59="yes",C61*C62,0) -> 0 | I42: A+ Stabilized = 8% | J42: Development = 15% | L42: Ttl Construction Cost | M42: =IF(OR($D$13='Model Inputs & Calcs'!$B$17,$D$13='Model Inputs & Calcs'!$B$16),'Dev Bdgt'!E57,0) -> 0 | N42: =M42/$D$21 -> #DIV/0! | P42: =C774 -> Hurdle Realisation Value | Q42: =D774 -> #DIV/0!
C43: Debt | D43: Constr. Holdback | E43: =IF(C43='Model Inputs & Calcs'!B3,0,IF(OR(UW!D13='Model Inputs & Calcs'!B17,UW!D13='Model Inputs & Calcs'!B16),UW!C50*UW!M43,0)) -> 0 | F43: 0 | G43: 0 | I43: Stabilized = 10% | L43: Ttl Const Cost & Land | M43: =IF(OR($D$13='Model Inputs & Calcs'!$B$17,$D$13='Model Inputs & Calcs'!$B$16),'Dev Bdgt'!E58,0) -> 0 | N43: =M43/$D$21 -> #DIV/0! | P43: =C775 -> Surplus Value | Q43: =D775 -> #DIV/0!
C44: Equity | D44: Op Ex Holdback | E44: =IF($C$44='Model Inputs & Calcs'!$B$4,SUM($E$730:$DT$730),0) -> 0 | F44: 0 | G44: 0 | I44: Lease Up = 12% | L44: Total Const, Land, Close | M44: =IF(OR($D$13='Model Inputs & Calcs'!$B$17,$D$13='Model Inputs & Calcs'!$B$16),M43+SUM(M17:M25),0) -> 0 | N44: =M44/$D$21 -> #DIV/0! | P44: =C776 -> Participation rate | Q44: =D776 -> 0
C45: Debt | D45: Interest Reserve (Cash on Deposit) | E45: =IF(C45='Model Inputs & Calcs'!B3,-SUM(OFFSET(D719,,D863+1,,E63-(E63-On_Deposit_Equity_OutDate))),) -> 0 | P45: =C777 -> Performance Fee | Q45: =D777 -> #DIV/0!
C46: Debt | D46: Interest Reserve | E46: =IF($C$46='Model Inputs & Calcs'!$B$4,SUM(OFFSET(D731,,,,D863+1)),0) -> #DIV/0! | F46: 0 | G46: 0 | I46: Fee Structure | L46: Submarket | P46: Asset Management Fee | Q46: =SUM(E743:CJ743) -> 0
C47: =Val!D27 -> -3307.0063 | D47: Total Loan | E47: =E43+E46+E42 -> #DIV/0! | F47: =SUM(F42:F46) -> -835.53546 | G47: =SUM(G42:G46) -> 0 | I47: Fund | J47: APGSS18 | L47: Market Radius
C48: Maximum LTV | D48: Closing Costs | E48: 0 | F48: 0 | G48: 0 | I48: Shares Issued | J48: =IFERROR(M35/J49,"NA") -> NA | L48: Comp Set Occupancy
C49: 0.6 | D49: Origination Fee | E49: =IF($K$15="Yes",0,0.4%) -> 0 | F49: =IF($K$15="Yes",0,0.4%) -> 0 | G49: =IF($K$15="Yes",0,0.4%) -> 0 | I49: Share Price | J49: 1 | L49: Comp Set Asking Rent
C50: 0.415 | D50: Mort. Broker Fee | E50: 0 | F50: 0 | G50: 0 | I50: Asset Management Fee | J50: =IF(K15="Yes",0.8%,0%) -> 0.008 | L50: Supply (1-km) | N50: 1400
C51: Takeout Loan 1 | D51: Assump/Prepay/Defease | E51: 0 | F51: 0 | G51: 0 | I51: Acquisition Fee | J51: =IF(K15="Yes",0%,2%) -> 0 | L51: Supply (3-km) | N51: 7490
C52: Yes | D52: Basis | E52: BBSY | F52: BBSY | G52: BBSY | I52: Development Fee | J52: =IF(K15="yes",5%,0%) -> 0.05 | L52: Supply (5-km) | N52: 7490
C53: Takeout Loan 1 LTV | D53: Type | E53: Floating | F53: Floating | G53: Floating | I53: Construction Mgmt Fee | J53: ='Dev Bdgt'!D49 -> 0.009 | L53: HH that Rent (1-km) | N53: 0
C54: 0.65 | D54: Index (term average) | E54: 0.039 | F54: =E54 -> 0.039 | G54: =F54 -> 0.039 | I54: Property Mgmt Fee | J54: =IF(K15="Yes",7%,0%) -> 0.07 | L54: HH that Rent (3-km) | N54: 0
C55: =MAX(OFFSET(Val!$C$98,,E63),OFFSET(Val!$C$99,,F56)) -> -1285.4392 | D55: Spread | E55: 0.0215 | F55: 0.0215 | G55: 0.0215 | I55: Minimum PM Fee/Month | J55: =IF(K15="Yes",3500,0) -> 3500 | L55: HH that Rent (5-km) | N55: 0
C56: Cashout | D56: Rate | E56: =E54+E55 -> 0.0605 | F56: =F55+F54 -> 0.0605 | G56: =G55+G54 -> 0.0605 | I56: Property Mgmt Setup | J56: =D602 -> 0 | L56: Med HH Income (1-km) | N56: 0
C57: =$F$47*(1-SUM(F49:F51))-F48-OFFSET($D$860,,$E$63) -> #DIV/0! | D57: Amortization Years | E57: 25 | F57: 25 | G57: 25 | I57: Performance Fee | J57: 0 | L57: Med HH Income (3-km) | N57: 0
C58: Takeout Loan 2 | D58: I/O Years | E58: =E63/12 -> 2.75 | F58: =(F63-E63)/12 -> 1.25 | G58: =(G63-F63)/12 -> 0 | I58: Tenant Ins Net Rate | J58: 0 | L58: Med HH Income (5-km) | N58: 0
C59: No | D59: LTV (Purchase Price) | E59: =IF(D13='Model Inputs & Calcs'!B17,E47/C47,E47/J9) -> #DIV/0! | F59: =IFERROR(F47/C55,"-") -> 0.65 | G59: =IFERROR(G47/C62,"-") -> - | L59: Population (1-km) | N59: 0
C60: Takeout Loan 2 LTV | D60: LTV (DCF Value) | E60: =IF($D$13='Model Inputs & Calcs'!$B$17,"NA",E$47/$C$47) -> #DIV/0! | F60: =IF($D$13='Model Inputs & Calcs'!$B$17,"NA",F$47/$C$55) -> 0.65 | G60: =IF($D$13='Model Inputs & Calcs'!$B$17,"NA",G$47/$J$17) -> #DIV/0! | L60: Population (3-km) | N60: 0
C61: 0.45 | D61: LTC | E61: =E$47/$M$42 -> #DIV/0! | F61: =F$47/$M$31 -> #DIV/0! | G61: =G$47/$M$31 -> #DIV/0! | I61: Cash on Deposit (1=yes,0=no) | J61: 0 | L61: Population (5-km) | N61: 0
C62: =MAX(OFFSET(Val!$C$98,,F63),OFFSET(Val!$C$99,,F63)) -> 0 | D62: Start Date | E62: =I12 -> 46112 | F62: =EOMONTH(E62,E63+1) -> 47149 | G62: =EOMONTH(F62,F63+1) -> 48638 | I62: On Deposit Equity In (month) | J62: ='Dev Bdgt'!F14+'Dev Bdgt'!G14-1 -> 20 | K62: <-- only have entries if J61=1 | L62: Population Growth (3-km '18-'23) | N62: 0
C63: Cashout | D63: Payoff Month | E63: {=OFFSET(Val!C15,,(MATCH('Model Inputs & Calcs'!C11,Val!$D$16:$EE$16,0)),,)} -> 33 | F63: =J36 -> 48 | G63: =J36 -> 48 | I63: On Deposit Equity Duration (monthly) | J63: 6 | K63: <-- only have entries if J61=1 | L63: CMA Ranking (Australia) | N63: 0
C64: =$G$47*(1-SUM(G49:G51))-G48-OFFSET($D$860,,$F$63) -> 835.53546 | D64: Minumum ICR | E64: {=MIN(IF($E$689:$EF$689<=E$63,$E$722:$EF$722))} -> 0 | F64: {=MIN(IF($E$689:$EF$689>E63,IF($E$689:$EF$689<=F$63,$E$722:$EF$722)))} -> 3077.3891 | G64: {=MIN(IF($E$689:$EF$689>F63,IF($E$689:$EF$689<=G$63,$E$722:$EF$722)))} -> 0 | I64: GST Required Out (month) | J64: 1
D65: Maximum ICR | E65: {=MAX(IF($E$689:$EF$689<=E$63,$E$722:$EF$722))} -> 0 | F65: {=MAX(IF($E$689:$EF$689>E64,IF($E$689:$EF$689<=F$63,$E$722:$EF$722)))} -> 3230.654 | G65: {=MAX(IF($E$689:$EF$689>F64,IF($E$689:$EF$689<=G$63,$E$722:$EF$722)))} -> 0
C67: =C433 -> Returns | D67: =D433 -> Averages: | E67: =E433 -> 1 | F67: =F433 -> 2 | G67: =G433 -> 3 | H67: =H433 -> 4 | I67: =I433 -> 5 | J67: =J433 -> 6 | ... O67: =O433 -> 11
C68: =C434 -> CoC - Levered | D68: =D434 -> #DIV/0! | E68: =E434 -> #DIV/0! | F68: =F434 -> #DIV/0! | G68: =G434 -> #DIV/0! | H68: =H434 -> #DIV/0! | I68: =I434 -> #DIV/0! | J68: =J434 -> #DIV/0! | ... O68: =O434 -> #DIV/0!
C69: =C435 -> CoC - Unlevered | D69: =D435 -> #DIV/0! | E69: =E435 -> #DIV/0! | F69: =F435 -> #DIV/0! | G69: =G435 -> #DIV/0! | H69: =H435 -> #DIV/0! | I69: =I435 -> #DIV/0! | J69: =J435 -> #DIV/0! | ... O69: =O435 -> #DIV/0!
C70: Stabilised Yield (Unlevered) | D70: =D436 -> #DIV/0! | E70: =E436 -> #DIV/0! | F70: =F436 -> #DIV/0! | G70: =G436 -> #DIV/0! | H70: =H436 -> #DIV/0! | I70: =I436 -> #DIV/0! | J70: =J436 -> #DIV/0! | K70: =K436 -> #DIV/0! | ... O70: =O436 -> #DIV/0!
C71: =C437 -> ROI - Levered | D71: =D437 -> #DIV/0! | E71: =E437 -> #DIV/0! | F71: =F437 -> #DIV/0! | G71: =G437 -> #DIV/0! | H71: =H437 -> #DIV/0! | I71: =I437 -> #DIV/0! | J71: =J437 -> #DIV/0! | ... O71: =O437 -> #DIV/0!
C72: =C438 -> ROI - Unlevered | D72: =D438 -> #DIV/0! | E72: =E438 -> #DIV/0! | F72: =F438 -> #DIV/0! | G72: =G438 -> #DIV/0! | H72: =H438 -> #DIV/0! | I72: =I438 -> #DIV/0! | J72: =J438 -> #DIV/0! | ... O72: =O438 -> #DIV/0!
B76: Proforma - Annual | D76: Year Ending: | E76: =EOMONTH(I12,12) -> 46477 | F76: =EOMONTH(E76,12) -> 46843 | G76: =EOMONTH(F76,12) -> 47208 | H76: =EOMONTH(G76,12) -> 47573 | I76: =EOMONTH(H76,12) -> 47938 | J76: =EOMONTH(I76,12) -> 48304 | K76: =EOMONTH(J76,12) -> 48669 | L76: =EOMONTH(K76,12) -> 49034 | M76: =EOMONTH(L76,12) -> 49399 | ... O76: =EOMONTH(N76,12) -> 50130
A78: STORAGE | C78: Monthly Net Lease-Up | E78: 1 | F78: =E78+1 -> 2 | G78: =F78+1 -> 3 | H78: =G78+1 -> 4 | I78: =H78+1 -> 5 | J78: =I78+1 -> 6 | K78: =J78+1 -> 7 | L78: =K78+1 -> 8 | M78: =L78+1 -> 9 | ... O78: =N78+1 -> 11
C79: =EOMONTH(I12,1) -> 46142 | E79: =IF(OR(D$78*12+'Model Inputs & Calcs'!$F3<E$95,D$78*12+'Model Inputs & Calcs'!$F3>E$96),0,E$98/$D$23) -> #DIV/0! | F79: =IF(OR(E$78*12+'Model Inputs & Calcs'!$F3<F$95,E$78*12+'Model Inputs & Calcs'!$F3>F$96),0,F$98/$D$23) -> #DIV/0! | G79: =IF(OR(F$78*12+'Model Inputs & Calcs'!$F3<G$95,F$78*12+'Model Inputs & Calcs'!$F3>G$96),0,G$98/$D$23) -> #DIV/0! | H79: =IF(OR(G$78*12+'Model Inputs & Calcs'!$F3<H$95,G$78*12+'Model Inputs & Calcs'!$F3>H$96),0,H$98/$D$23) -> #DIV/0! | I79: =IF(OR(H$78*12+'Model Inputs & Calcs'!$F3<I$95,H$78*12+'Model Inputs & Calcs'!$F3>I$96),0,I$98/$D$23) -> #DIV/0! | J79: =IF(OR(I$78*12+'Model Inputs & Calcs'!$F3<J$95,I$78*12+'Model Inputs & Calcs'!$F3>J$96),0,J$98/$D$23) -> #DIV/0! | K79: =IF(OR(J$78*12+'Model Inputs & Calcs'!$F3<K$95,J$78*12+'Model Inputs & Calcs'!$F3>K$96),0,K$98/$D$23) -> #DIV/0! | L79: =IF(OR(K$78*12+'Model Inputs & Calcs'!$F3<L$95,K$78*12+'Model Inputs & Calcs'!$F3>L$96),0,L$98/$D$23) -> #DIV/0! | ... O79: =IF(OR(N$78*12+'Model Inputs & Calcs'!$F3<O$95,N$78*12+'Model Inputs & Calcs'!$F3>O$96),0,O$98/$D$23) -> #DIV/0!
C80: =EOMONTH(C79,1) -> 46173 | E80: =IF(OR(D$78*12+'Model Inputs & Calcs'!$F4<E$95,D$78*12+'Model Inputs & Calcs'!$F4>E$96),0,E$98/$D$23) -> #DIV/0! | F80: =IF(OR(E$78*12+'Model Inputs & Calcs'!$F4<F$95,E$78*12+'Model Inputs & Calcs'!$F4>F$96),0,F$98/$D$23) -> #DIV/0! | G80: =IF(OR(F$78*12+'Model Inputs & Calcs'!$F4<G$95,F$78*12+'Model Inputs & Calcs'!$F4>G$96),0,G$98/$D$23) -> #DIV/0! | H80: =IF(OR(G$78*12+'Model Inputs & Calcs'!$F4<H$95,G$78*12+'Model Inputs & Calcs'!$F4>H$96),0,H$98/$D$23) -> #DIV/0! | I80: =IF(OR(H$78*12+'Model Inputs & Calcs'!$F4<I$95,H$78*12+'Model Inputs & Calcs'!$F4>I$96),0,I$98/$D$23) -> #DIV/0! | J80: =IF(OR(I$78*12+'Model Inputs & Calcs'!$F4<J$95,I$78*12+'Model Inputs & Calcs'!$F4>J$96),0,J$98/$D$23) -> #DIV/0! | K80: =IF(OR(J$78*12+'Model Inputs & Calcs'!$F4<K$95,J$78*12+'Model Inputs & Calcs'!$F4>K$96),0,K$98/$D$23) -> #DIV/0! | L80: =IF(OR(K$78*12+'Model Inputs & Calcs'!$F4<L$95,K$78*12+'Model Inputs & Calcs'!$F4>L$96),0,L$98/$D$23) -> #DIV/0! | ... O80: =IF(OR(N$78*12+'Model Inputs & Calcs'!$F4<O$95,N$78*12+'Model Inputs & Calcs'!$F4>O$96),0,O$98/$D$23) -> #DIV/0!
C81: =EOMONTH(C80,1) -> 46203 | E81: =IF(OR(D$78*12+'Model Inputs & Calcs'!$F5<E$95,D$78*12+'Model Inputs & Calcs'!$F5>E$96),0,E$98/$D$23) -> #DIV/0! | F81: =IF(OR(E$78*12+'Model Inputs & Calcs'!$F5<F$95,E$78*12+'Model Inputs & Calcs'!$F5>F$96),0,F$98/$D$23) -> #DIV/0! | G81: =IF(OR(F$78*12+'Model Inputs & Calcs'!$F5<G$95,F$78*12+'Model Inputs & Calcs'!$F5>G$96),0,G$98/$D$23) -> #DIV/0! | H81: =IF(OR(G$78*12+'Model Inputs & Calcs'!$F5<H$95,G$78*12+'Model Inputs & Calcs'!$F5>H$96),0,H$98/$D$23) -> #DIV/0! | I81: =IF(OR(H$78*12+'Model Inputs & Calcs'!$F5<I$95,H$78*12+'Model Inputs & Calcs'!$F5>I$96),0,I$98/$D$23) -> #DIV/0! | J81: =IF(OR(I$78*12+'Model Inputs & Calcs'!$F5<J$95,I$78*12+'Model Inputs & Calcs'!$F5>J$96),0,J$98/$D$23) -> #DIV/0! | K81: =IF(OR(J$78*12+'Model Inputs & Calcs'!$F5<K$95,J$78*12+'Model Inputs & Calcs'!$F5>K$96),0,K$98/$D$23) -> #DIV/0! | L81: =IF(OR(K$78*12+'Model Inputs & Calcs'!$F5<L$95,K$78*12+'Model Inputs & Calcs'!$F5>L$96),0,L$98/$D$23) -> #DIV/0! | ... O81: =IF(OR(N$78*12+'Model Inputs & Calcs'!$F5<O$95,N$78*12+'Model Inputs & Calcs'!$F5>O$96),0,O$98/$D$23) -> #DIV/0!
C82: =EOMONTH(C81,1) -> 46234 | E82: =IF(OR(D$78*12+'Model Inputs & Calcs'!$F6<E$95,D$78*12+'Model Inputs & Calcs'!$F6>E$96),0,E$98/$D$23) -> #DIV/0! | F82: =IF(OR(E$78*12+'Model Inputs & Calcs'!$F6<F$95,E$78*12+'Model Inputs & Calcs'!$F6>F$96),0,F$98/$D$23) -> #DIV/0! | G82: =IF(OR(F$78*12+'Model Inputs & Calcs'!$F6<G$95,F$78*12+'Model Inputs & Calcs'!$F6>G$96),0,G$98/$D$23) -> #DIV/0! | H82: =IF(OR(G$78*12+'Model Inputs & Calcs'!$F6<H$95,G$78*12+'Model Inputs & Calcs'!$F6>H$96),0,H$98/$D$23) -> #DIV/0! | I82: =IF(OR(H$78*12+'Model Inputs & Calcs'!$F6<I$95,H$78*12+'Model Inputs & Calcs'!$F6>I$96),0,I$98/$D$23) -> #DIV/0! | J82: =IF(OR(I$78*12+'Model Inputs & Calcs'!$F6<J$95,I$78*12+'Model Inputs & Calcs'!$F6>J$96),0,J$98/$D$23) -> #DIV/0! | K82: =IF(OR(J$78*12+'Model Inputs & Calcs'!$F6<K$95,J$78*12+'Model Inputs & Calcs'!$F6>K$96),0,K$98/$D$23) -> #DIV/0! | L82: =IF(OR(K$78*12+'Model Inputs & Calcs'!$F6<L$95,K$78*12+'Model Inputs & Calcs'!$F6>L$96),0,L$98/$D$23) -> #DIV/0! | ... O82: =IF(OR(N$78*12+'Model Inputs & Calcs'!$F6<O$95,N$78*12+'Model Inputs & Calcs'!$F6>O$96),0,O$98/$D$23) -> #DIV/0!
C83: =EOMONTH(C82,1) -> 46265 | E83: =IF(OR(D$78*12+'Model Inputs & Calcs'!$F7<E$95,D$78*12+'Model Inputs & Calcs'!$F7>E$96),0,E$98/$D$23) -> #DIV/0! | F83: =IF(OR(E$78*12+'Model Inputs & Calcs'!$F7<F$95,E$78*12+'Model Inputs & Calcs'!$F7>F$96),0,F$98/$D$23) -> #DIV/0! | G83: =IF(OR(F$78*12+'Model Inputs & Calcs'!$F7<G$95,F$78*12+'Model Inputs & Calcs'!$F7>G$96),0,G$98/$D$23) -> #DIV/0! | H83: =IF(OR(G$78*12+'Model Inputs & Calcs'!$F7<H$95,G$78*12+'Model Inputs & Calcs'!$F7>H$96),0,H$98/$D$23) -> #DIV/0! | I83: =IF(OR(H$78*12+'Model Inputs & Calcs'!$F7<I$95,H$78*12+'Model Inputs & Calcs'!$F7>I$96),0,I$98/$D$23) -> #DIV/0! | J83: =IF(OR(I$78*12+'Model Inputs & Calcs'!$F7<J$95,I$78*12+'Model Inputs & Calcs'!$F7>J$96),0,J$98/$D$23) -> #DIV/0! | K83: =IF(OR(J$78*12+'Model Inputs & Calcs'!$F7<K$95,J$78*12+'Model Inputs & Calcs'!$F7>K$96),0,K$98/$D$23) -> #DIV/0! | L83: =IF(OR(K$78*12+'Model Inputs & Calcs'!$F7<L$95,K$78*12+'Model Inputs & Calcs'!$F7>L$96),0,L$98/$D$23) -> #DIV/0! | ... O83: =IF(OR(N$78*12+'Model Inputs & Calcs'!$F7<O$95,N$78*12+'Model Inputs & Calcs'!$F7>O$96),0,O$98/$D$23) -> #DIV/0!
C84: =EOMONTH(C83,1) -> 46295 | E84: =IF(OR(D$78*12+'Model Inputs & Calcs'!$F8<E$95,D$78*12+'Model Inputs & Calcs'!$F8>E$96),0,E$98/$D$23) -> #DIV/0! | F84: =IF(OR(E$78*12+'Model Inputs & Calcs'!$F8<F$95,E$78*12+'Model Inputs & Calcs'!$F8>F$96),0,F$98/$D$23) -> #DIV/0! | G84: =IF(OR(F$78*12+'Model Inputs & Calcs'!$F8<G$95,F$78*12+'Model Inputs & Calcs'!$F8>G$96),0,G$98/$D$23) -> #DIV/0! | H84: =IF(OR(G$78*12+'Model Inputs & Calcs'!$F8<H$95,G$78*12+'Model Inputs & Calcs'!$F8>H$96),0,H$98/$D$23) -> #DIV/0! | I84: =IF(OR(H$78*12+'Model Inputs & Calcs'!$F8<I$95,H$78*12+'Model Inputs & Calcs'!$F8>I$96),0,I$98/$D$23) -> #DIV/0! | J84: =IF(OR(I$78*12+'Model Inputs & Calcs'!$F8<J$95,I$78*12+'Model Inputs & Calcs'!$F8>J$96),0,J$98/$D$23) -> #DIV/0! | K84: =IF(OR(J$78*12+'Model Inputs & Calcs'!$F8<K$95,J$78*12+'Model Inputs & Calcs'!$F8>K$96),0,K$98/$D$23) -> #DIV/0! | L84: =IF(OR(K$78*12+'Model Inputs & Calcs'!$F8<L$95,K$78*12+'Model Inputs & Calcs'!$F8>L$96),0,L$98/$D$23) -> #DIV/0! | ... O84: =IF(OR(N$78*12+'Model Inputs & Calcs'!$F8<O$95,N$78*12+'Model Inputs & Calcs'!$F8>O$96),0,O$98/$D$23) -> #DIV/0!
C85: =EOMONTH(C84,1) -> 46326 | E85: =IF(OR(D$78*12+'Model Inputs & Calcs'!$F9<E$95,D$78*12+'Model Inputs & Calcs'!$F9>E$96),0,E$98/$D$23) -> #DIV/0! | F85: =IF(OR(E$78*12+'Model Inputs & Calcs'!$F9<F$95,E$78*12+'Model Inputs & Calcs'!$F9>F$96),0,F$98/$D$23) -> #DIV/0! | G85: =IF(OR(F$78*12+'Model Inputs & Calcs'!$F9<G$95,F$78*12+'Model Inputs & Calcs'!$F9>G$96),0,G$98/$D$23) -> #DIV/0! | H85: =IF(OR(G$78*12+'Model Inputs & Calcs'!$F9<H$95,G$78*12+'Model Inputs & Calcs'!$F9>H$96),0,H$98/$D$23) -> #DIV/0! | I85: =IF(OR(H$78*12+'Model Inputs & Calcs'!$F9<I$95,H$78*12+'Model Inputs & Calcs'!$F9>I$96),0,I$98/$D$23) -> #DIV/0! | J85: =IF(OR(I$78*12+'Model Inputs & Calcs'!$F9<J$95,I$78*12+'Model Inputs & Calcs'!$F9>J$96),0,J$98/$D$23) -> #DIV/0! | K85: =IF(OR(J$78*12+'Model Inputs & Calcs'!$F9<K$95,J$78*12+'Model Inputs & Calcs'!$F9>K$96),0,K$98/$D$23) -> #DIV/0! | L85: =IF(OR(K$78*12+'Model Inputs & Calcs'!$F9<L$95,K$78*12+'Model Inputs & Calcs'!$F9>L$96),0,L$98/$D$23) -> #DIV/0! | ... O85: =IF(OR(N$78*12+'Model Inputs & Calcs'!$F9<O$95,N$78*12+'Model Inputs & Calcs'!$F9>O$96),0,O$98/$D$23) -> #DIV/0!
C86: =EOMONTH(C85,1) -> 46356 | E86: =IF(OR(D$78*12+'Model Inputs & Calcs'!$F10<E$95,D$78*12+'Model Inputs & Calcs'!$F10>E$96),0,E$98/$D$23) -> #DIV/0! | F86: =IF(OR(E$78*12+'Model Inputs & Calcs'!$F10<F$95,E$78*12+'Model Inputs & Calcs'!$F10>F$96),0,F$98/$D$23) -> #DIV/0! | G86: =IF(OR(F$78*12+'Model Inputs & Calcs'!$F10<G$95,F$78*12+'Model Inputs & Calcs'!$F10>G$96),0,G$98/$D$23) -> #DIV/0! | H86: =IF(OR(G$78*12+'Model Inputs & Calcs'!$F10<H$95,G$78*12+'Model Inputs & Calcs'!$F10>H$96),0,H$98/$D$23) -> #DIV/0! | I86: =IF(OR(H$78*12+'Model Inputs & Calcs'!$F10<I$95,H$78*12+'Model Inputs & Calcs'!$F10>I$96),0,I$98/$D$23) -> #DIV/0! | J86: =IF(OR(I$78*12+'Model Inputs & Calcs'!$F10<J$95,I$78*12+'Model Inputs & Calcs'!$F10>J$96),0,J$98/$D$23) -> #DIV/0! | K86: =IF(OR(J$78*12+'Model Inputs & Calcs'!$F10<K$95,J$78*12+'Model Inputs & Calcs'!$F10>K$96),0,K$98/$D$23) -> #DIV/0! | L86: =IF(OR(K$78*12+'Model Inputs & Calcs'!$F10<L$95,K$78*12+'Model Inputs & Calcs'!$F10>L$96),0,L$98/$D$23) -> #DIV/0! | ... O86: =IF(OR(N$78*12+'Model Inputs & Calcs'!$F10<O$95,N$78*12+'Model Inputs & Calcs'!$F10>O$96),0,O$98/$D$23) -> #DIV/0!
C87: =EOMONTH(C86,1) -> 46387 | E87: =IF(OR(D$78*12+'Model Inputs & Calcs'!$F11<E$95,D$78*12+'Model Inputs & Calcs'!$F11>E$96),0,E$98/$D$23) -> #DIV/0! | F87: =IF(OR(E$78*12+'Model Inputs & Calcs'!$F11<F$95,E$78*12+'Model Inputs & Calcs'!$F11>F$96),0,F$98/$D$23) -> #DIV/0! | G87: =IF(OR(F$78*12+'Model Inputs & Calcs'!$F11<G$95,F$78*12+'Model Inputs & Calcs'!$F11>G$96),0,G$98/$D$23) -> #DIV/0! | H87: =IF(OR(G$78*12+'Model Inputs & Calcs'!$F11<H$95,G$78*12+'Model Inputs & Calcs'!$F11>H$96),0,H$98/$D$23) -> #DIV/0! | I87: =IF(OR(H$78*12+'Model Inputs & Calcs'!$F11<I$95,H$78*12+'Model Inputs & Calcs'!$F11>I$96),0,I$98/$D$23) -> #DIV/0! | J87: =IF(OR(I$78*12+'Model Inputs & Calcs'!$F11<J$95,I$78*12+'Model Inputs & Calcs'!$F11>J$96),0,J$98/$D$23) -> #DIV/0! | K87: =IF(OR(J$78*12+'Model Inputs & Calcs'!$F11<K$95,J$78*12+'Model Inputs & Calcs'!$F11>K$96),0,K$98/$D$23) -> #DIV/0! | L87: =IF(OR(K$78*12+'Model Inputs & Calcs'!$F11<L$95,K$78*12+'Model Inputs & Calcs'!$F11>L$96),0,L$98/$D$23) -> #DIV/0! | ... O87: =IF(OR(N$78*12+'Model Inputs & Calcs'!$F11<O$95,N$78*12+'Model Inputs & Calcs'!$F11>O$96),0,O$98/$D$23) -> #DIV/0!
C88: =EOMONTH(C87,1) -> 46418 | E88: =IF(OR(D$78*12+'Model Inputs & Calcs'!$F12<E$95,D$78*12+'Model Inputs & Calcs'!$F12>E$96),0,E$98/$D$23) -> #DIV/0! | F88: =IF(OR(E$78*12+'Model Inputs & Calcs'!$F12<F$95,E$78*12+'Model Inputs & Calcs'!$F12>F$96),0,F$98/$D$23) -> #DIV/0! | G88: =IF(OR(F$78*12+'Model Inputs & Calcs'!$F12<G$95,F$78*12+'Model Inputs & Calcs'!$F12>G$96),0,G$98/$D$23) -> #DIV/0! | H88: =IF(OR(G$78*12+'Model Inputs & Calcs'!$F12<H$95,G$78*12+'Model Inputs & Calcs'!$F12>H$96),0,H$98/$D$23) -> #DIV/0! | I88: =IF(OR(H$78*12+'Model Inputs & Calcs'!$F12<I$95,H$78*12+'Model Inputs & Calcs'!$F12>I$96),0,I$98/$D$23) -> #DIV/0! | J88: =IF(OR(I$78*12+'Model Inputs & Calcs'!$F12<J$95,I$78*12+'Model Inputs & Calcs'!$F12>J$96),0,J$98/$D$23) -> #DIV/0! | K88: =IF(OR(J$78*12+'Model Inputs & Calcs'!$F12<K$95,J$78*12+'Model Inputs & Calcs'!$F12>K$96),0,K$98/$D$23) -> #DIV/0! | L88: =IF(OR(K$78*12+'Model Inputs & Calcs'!$F12<L$95,K$78*12+'Model Inputs & Calcs'!$F12>L$96),0,L$98/$D$23) -> #DIV/0! | ... O88: =IF(OR(N$78*12+'Model Inputs & Calcs'!$F12<O$95,N$78*12+'Model Inputs & Calcs'!$F12>O$96),0,O$98/$D$23) -> #DIV/0!
C89: =EOMONTH(C88,1) -> 46446 | E89: =IF(OR(D$78*12+'Model Inputs & Calcs'!$F13<E$95,D$78*12+'Model Inputs & Calcs'!$F13>E$96),0,E$98/$D$23) -> #DIV/0! | F89: =IF(OR(E$78*12+'Model Inputs & Calcs'!$F13<F$95,E$78*12+'Model Inputs & Calcs'!$F13>F$96),0,F$98/$D$23) -> #DIV/0! | G89: =IF(OR(F$78*12+'Model Inputs & Calcs'!$F13<G$95,F$78*12+'Model Inputs & Calcs'!$F13>G$96),0,G$98/$D$23) -> #DIV/0! | H89: =IF(OR(G$78*12+'Model Inputs & Calcs'!$F13<H$95,G$78*12+'Model Inputs & Calcs'!$F13>H$96),0,H$98/$D$23) -> #DIV/0! | I89: =IF(OR(H$78*12+'Model Inputs & Calcs'!$F13<I$95,H$78*12+'Model Inputs & Calcs'!$F13>I$96),0,I$98/$D$23) -> #DIV/0! | J89: =IF(OR(I$78*12+'Model Inputs & Calcs'!$F13<J$95,I$78*12+'Model Inputs & Calcs'!$F13>J$96),0,J$98/$D$23) -> #DIV/0! | K89: =IF(OR(J$78*12+'Model Inputs & Calcs'!$F13<K$95,J$78*12+'Model Inputs & Calcs'!$F13>K$96),0,K$98/$D$23) -> #DIV/0! | L89: =IF(OR(K$78*12+'Model Inputs & Calcs'!$F13<L$95,K$78*12+'Model Inputs & Calcs'!$F13>L$96),0,L$98/$D$23) -> #DIV/0! | ... O89: =IF(OR(N$78*12+'Model Inputs & Calcs'!$F13<O$95,N$78*12+'Model Inputs & Calcs'!$F13>O$96),0,O$98/$D$23) -> #DIV/0!
C90: =EOMONTH(C89,1) -> 46477 | E90: =IF(OR(D$78*12+'Model Inputs & Calcs'!$F14<E$95,D$78*12+'Model Inputs & Calcs'!$F14>E$96),0,E$98/$D$23) -> #DIV/0! | F90: =IF(OR(E$78*12+'Model Inputs & Calcs'!$F14<F$95,E$78*12+'Model Inputs & Calcs'!$F14>F$96),0,F$98/$D$23) -> #DIV/0! | G90: =IF(OR(F$78*12+'Model Inputs & Calcs'!$F14<G$95,F$78*12+'Model Inputs & Calcs'!$F14>G$96),0,G$98/$D$23) -> #DIV/0! | H90: =IF(OR(G$78*12+'Model Inputs & Calcs'!$F14<H$95,G$78*12+'Model Inputs & Calcs'!$F14>H$96),0,H$98/$D$23) -> #DIV/0! | I90: =IF(OR(H$78*12+'Model Inputs & Calcs'!$F14<I$95,H$78*12+'Model Inputs & Calcs'!$F14>I$96),0,I$98/$D$23) -> #DIV/0! | J90: =IF(OR(I$78*12+'Model Inputs & Calcs'!$F14<J$95,I$78*12+'Model Inputs & Calcs'!$F14>J$96),0,J$98/$D$23) -> #DIV/0! | K90: =IF(OR(J$78*12+'Model Inputs & Calcs'!$F14<K$95,J$78*12+'Model Inputs & Calcs'!$F14>K$96),0,K$98/$D$23) -> #DIV/0! | L90: =IF(OR(K$78*12+'Model Inputs & Calcs'!$F14<L$95,K$78*12+'Model Inputs & Calcs'!$F14>L$96),0,L$98/$D$23) -> #DIV/0! | ... O90: =IF(OR(N$78*12+'Model Inputs & Calcs'!$F14<O$95,N$78*12+'Model Inputs & Calcs'!$F14>O$96),0,O$98/$D$23) -> #DIV/0!
C91: Year End Physical Occupancy | E91: =(SUM(E79:E90)*$D$23+($D$25*$D$21))/$D$21 -> #DIV/0! | F91: =(SUM(F79:F90)*$D$23+E91*$D$21)/$D$21 -> #DIV/0! | G91: =(SUM(G79:G90)*$D$23+F91*$D$21)/$D$21 -> #DIV/0! | H91: =(SUM(H79:H90)*$D$23+G91*$D$21)/$D$21 -> #DIV/0! | I91: =(SUM(I79:I90)*$D$23+H91*$D$21)/$D$21 -> #DIV/0! | J91: =(SUM(J79:J90)*$D$23+I91*$D$21)/$D$21 -> #DIV/0! | K91: =(SUM(K79:K90)*$D$23+J91*$D$21)/$D$21 -> #DIV/0! | L91: =(SUM(L79:L90)*$D$23+K91*$D$21)/$D$21 -> #DIV/0! | M91: =(SUM(M79:M90)*$D$23+L91*$D$21)/$D$21 -> #DIV/0! | ... O91: =(SUM(O79:O90)*$D$23+N91*$D$21)/$D$21 -> #DIV/0!
C92: Average SM Lease-Up from Open to Stabilized | E92: =IFERROR(SUM(E79:E90)*$D$23,"-") -> - | F92: =IFERROR(SUM(F79:F90)*$D$23,"-") -> - | G92: =IFERROR(SUM(G79:G90)*$D$23,"-") -> - | H92: =IFERROR(SUM(H79:H90)*$D$23,"-") -> - | I92: =IFERROR(SUM(I79:I90)*$D$23,"-") -> - | J92: =IFERROR(SUM(J79:J90)*$D$23,"-") -> - | K92: =IFERROR(SUM(K79:K90)*$D$23,"-") -> - | L92: =IFERROR(SUM(L79:L90)*$D$23,"-") -> - | ... O92: =IFERROR(SUM(O79:O90)*$D$23,"-") -> -
C94: Lease-Up Timeline 1
C95: Start Month | D95: =IF(E98>=0,IF(E98>0,E95,IF(F98>0,F95,IF(G98>0,G95,IF(H98>0,H95,IF(I98>0,I95)))))) -> FALSE | E95: 1 | F95: =E96+1 -> 13 | G95: =F96+1 -> 25 | H95: =G96+1 -> 37 | I95: =H96+1 -> 49 | J95: =I96+1 -> 61 | K95: =J96+1 -> 73 | L95: =K96+1 -> 85 | M95: =L96+1 -> 97 | ... O95: =N96+1 -> 121
C96: End Month | E96: 12 | F96: =F95+11 -> 24 | G96: =G95+11 -> 36 | H96: =H95+11 -> 48 | I96: =I95+11 -> 60 | J96: =J95+11 -> 72 | K96: =K95+11 -> 84 | L96: =L95+11 -> 96 | M96: =M95+11 -> 108 | ... O96: =O95+11 -> 132
C97: Year End Occupancy | E97: 0 | F97: 0 | G97: 0 | H97: =G97 -> 0 | I97: =H97 -> 0 | J97: =I97 -> 0 | K97: =J97 -> 0 | L97: =K97 -> 0 | M97: =L97 -> 0 | N97: =M97 -> 0 | O97: =N97 -> 0
C98: Average Monthly Lease-Up | E98: =(E97-D25)/(E96-E95+1)*$D$21 -> 0 | F98: =(F97-E97)/(F96-F95+1)*$D$21 -> 0 | G98: =(G97-F97)/(G96-G95+1)*$D$21 -> 0 | H98: =(H97-G97)/(H96-H95+1)*$D$21 -> 0 | I98: =(I97-H97)/(I96-I95+1)*$D$21 -> 0 | J98: =(J97-I97)/(J96-J95+1)*$D$21 -> 0 | K98: =(K97-J97)/(K96-K95+1)*$D$21 -> 0 | L98: =(L97-K97)/(L96-L95+1)*$D$21 -> 0 | M98: =(M97-L97)/(M96-M95+1)*$D$21 -> 0 | ... O98: =(O97-N97)/(O96-O95+1)*$D$21 -> 0
A100: RV | C100: Monthly Net Lease-Up | E100: 1 | F100: =E100+1 -> 2 | G100: =F100+1 -> 3 | H100: =G100+1 -> 4 | I100: =H100+1 -> 5 | J100: =I100+1 -> 6 | K100: =J100+1 -> 7 | L100: =K100+1 -> 8 | M100: =L100+1 -> 9 | ... O100: =N100+1 -> 11
C101: =EOMONTH(I12,1) -> 46142 | E101: =IFERROR(IF(OR(D$100*12+'Model Inputs & Calcs'!$F3<E$117,D$100*12+'Model Inputs & Calcs'!$F3>E$118),0,E$120/$D$30),0) -> 0 | F101: =IFERROR(IF(OR(E$100*12+'Model Inputs & Calcs'!$F3<F$117,E$100*12+'Model Inputs & Calcs'!$F3>F$118),0,F$120/$D$30),0) -> 0 | G101: =IFERROR(IF(OR(F$100*12+'Model Inputs & Calcs'!$F3<G$117,F$100*12+'Model Inputs & Calcs'!$F3>G$118),0,G$120/$D$30),0) -> 0 | H101: =IFERROR(IF(OR(G$100*12+'Model Inputs & Calcs'!$F3<H$117,G$100*12+'Model Inputs & Calcs'!$F3>H$118),0,H$120/$D$30),0) -> 0 | I101: =IFERROR(IF(OR(H$100*12+'Model Inputs & Calcs'!$F3<I$117,H$100*12+'Model Inputs & Calcs'!$F3>I$118),0,I$120/$D$30),0) -> 0 | J101: =IFERROR(IF(OR(I$100*12+'Model Inputs & Calcs'!$F3<J$117,I$100*12+'Model Inputs & Calcs'!$F3>J$118),0,J$120/$D$30),0) -> 0 | K101: =IFERROR(IF(OR(J$100*12+'Model Inputs & Calcs'!$F3<K$117,J$100*12+'Model Inputs & Calcs'!$F3>K$118),0,K$120/$D$30),0) -> 0 | L101: =IFERROR(IF(OR(K$100*12+'Model Inputs & Calcs'!$F3<L$117,K$100*12+'Model Inputs & Calcs'!$F3>L$118),0,L$120/$D$30),0) -> 0 | ... O101: =IFERROR(IF(OR(N$100*12+'Model Inputs & Calcs'!$F3<O$117,N$100*12+'Model Inputs & Calcs'!$F3>O$118),0,O$120/$D$30),0) -> 0
C102: =EOMONTH(C101,1) -> 46173 | E102: =IFERROR(IF(OR(D$100*12+'Model Inputs & Calcs'!$F4<E$117,D$100*12+'Model Inputs & Calcs'!$F4>E$118),0,E$120/$D$30),0) -> 0 | F102: =IFERROR(IF(OR(E$100*12+'Model Inputs & Calcs'!$F4<F$117,E$100*12+'Model Inputs & Calcs'!$F4>F$118),0,F$120/$D$30),0) -> 0 | G102: =IFERROR(IF(OR(F$100*12+'Model Inputs & Calcs'!$F4<G$117,F$100*12+'Model Inputs & Calcs'!$F4>G$118),0,G$120/$D$30),0) -> 0 | H102: =IFERROR(IF(OR(G$100*12+'Model Inputs & Calcs'!$F4<H$117,G$100*12+'Model Inputs & Calcs'!$F4>H$118),0,H$120/$D$30),0) -> 0 | I102: =IFERROR(IF(OR(H$100*12+'Model Inputs & Calcs'!$F4<I$117,H$100*12+'Model Inputs & Calcs'!$F4>I$118),0,I$120/$D$30),0) -> 0 | J102: =IFERROR(IF(OR(I$100*12+'Model Inputs & Calcs'!$F4<J$117,I$100*12+'Model Inputs & Calcs'!$F4>J$118),0,J$120/$D$30),0) -> 0 | K102: =IFERROR(IF(OR(J$100*12+'Model Inputs & Calcs'!$F4<K$117,J$100*12+'Model Inputs & Calcs'!$F4>K$118),0,K$120/$D$30),0) -> 0 | L102: =IFERROR(IF(OR(K$100*12+'Model Inputs & Calcs'!$F4<L$117,K$100*12+'Model Inputs & Calcs'!$F4>L$118),0,L$120/$D$30),0) -> 0 | ... O102: =IFERROR(IF(OR(N$100*12+'Model Inputs & Calcs'!$F4<O$117,N$100*12+'Model Inputs & Calcs'!$F4>O$118),0,O$120/$D$30),0) -> 0
C103: =EOMONTH(C102,1) -> 46203 | E103: =IFERROR(IF(OR(D$100*12+'Model Inputs & Calcs'!$F5<E$117,D$100*12+'Model Inputs & Calcs'!$F5>E$118),0,E$120/$D$30),0) -> 0 | F103: =IFERROR(IF(OR(E$100*12+'Model Inputs & Calcs'!$F5<F$117,E$100*12+'Model Inputs & Calcs'!$F5>F$118),0,F$120/$D$30),0) -> 0 | G103: =IFERROR(IF(OR(F$100*12+'Model Inputs & Calcs'!$F5<G$117,F$100*12+'Model Inputs & Calcs'!$F5>G$118),0,G$120/$D$30),0) -> 0 | H103: =IFERROR(IF(OR(G$100*12+'Model Inputs & Calcs'!$F5<H$117,G$100*12+'Model Inputs & Calcs'!$F5>H$118),0,H$120/$D$30),0) -> 0 | I103: =IFERROR(IF(OR(H$100*12+'Model Inputs & Calcs'!$F5<I$117,H$100*12+'Model Inputs & Calcs'!$F5>I$118),0,I$120/$D$30),0) -> 0 | J103: =IFERROR(IF(OR(I$100*12+'Model Inputs & Calcs'!$F5<J$117,I$100*12+'Model Inputs & Calcs'!$F5>J$118),0,J$120/$D$30),0) -> 0 | K103: =IFERROR(IF(OR(J$100*12+'Model Inputs & Calcs'!$F5<K$117,J$100*12+'Model Inputs & Calcs'!$F5>K$118),0,K$120/$D$30),0) -> 0 | L103: =IFERROR(IF(OR(K$100*12+'Model Inputs & Calcs'!$F5<L$117,K$100*12+'Model Inputs & Calcs'!$F5>L$118),0,L$120/$D$30),0) -> 0 | ... O103: =IFERROR(IF(OR(N$100*12+'Model Inputs & Calcs'!$F5<O$117,N$100*12+'Model Inputs & Calcs'!$F5>O$118),0,O$120/$D$30),0) -> 0
C104: =EOMONTH(C103,1) -> 46234 | E104: =IFERROR(IF(OR(D$100*12+'Model Inputs & Calcs'!$F6<E$117,D$100*12+'Model Inputs & Calcs'!$F6>E$118),0,E$120/$D$30),0) -> 0 | F104: =IFERROR(IF(OR(E$100*12+'Model Inputs & Calcs'!$F6<F$117,E$100*12+'Model Inputs & Calcs'!$F6>F$118),0,F$120/$D$30),0) -> 0 | G104: =IFERROR(IF(OR(F$100*12+'Model Inputs & Calcs'!$F6<G$117,F$100*12+'Model Inputs & Calcs'!$F6>G$118),0,G$120/$D$30),0) -> 0 | H104: =IFERROR(IF(OR(G$100*12+'Model Inputs & Calcs'!$F6<H$117,G$100*12+'Model Inputs & Calcs'!$F6>H$118),0,H$120/$D$30),0) -> 0 | I104: =IFERROR(IF(OR(H$100*12+'Model Inputs & Calcs'!$F6<I$117,H$100*12+'Model Inputs & Calcs'!$F6>I$118),0,I$120/$D$30),0) -> 0 | J104: =IFERROR(IF(OR(I$100*12+'Model Inputs & Calcs'!$F6<J$117,I$100*12+'Model Inputs & Calcs'!$F6>J$118),0,J$120/$D$30),0) -> 0 | K104: =IFERROR(IF(OR(J$100*12+'Model Inputs & Calcs'!$F6<K$117,J$100*12+'Model Inputs & Calcs'!$F6>K$118),0,K$120/$D$30),0) -> 0 | L104: =IFERROR(IF(OR(K$100*12+'Model Inputs & Calcs'!$F6<L$117,K$100*12+'Model Inputs & Calcs'!$F6>L$118),0,L$120/$D$30),0) -> 0 | ... O104: =IFERROR(IF(OR(N$100*12+'Model Inputs & Calcs'!$F6<O$117,N$100*12+'Model Inputs & Calcs'!$F6>O$118),0,O$120/$D$30),0) -> 0
C105: =EOMONTH(C104,1) -> 46265 | E105: =IFERROR(IF(OR(D$100*12+'Model Inputs & Calcs'!$F7<E$117,D$100*12+'Model Inputs & Calcs'!$F7>E$118),0,E$120/$D$30),0) -> 0 | F105: =IFERROR(IF(OR(E$100*12+'Model Inputs & Calcs'!$F7<F$117,E$100*12+'Model Inputs & Calcs'!$F7>F$118),0,F$120/$D$30),0) -> 0 | G105: =IFERROR(IF(OR(F$100*12+'Model Inputs & Calcs'!$F7<G$117,F$100*12+'Model Inputs & Calcs'!$F7>G$118),0,G$120/$D$30),0) -> 0 | H105: =IFERROR(IF(OR(G$100*12+'Model Inputs & Calcs'!$F7<H$117,G$100*12+'Model Inputs & Calcs'!$F7>H$118),0,H$120/$D$30),0) -> 0 | I105: =IFERROR(IF(OR(H$100*12+'Model Inputs & Calcs'!$F7<I$117,H$100*12+'Model Inputs & Calcs'!$F7>I$118),0,I$120/$D$30),0) -> 0 | J105: =IFERROR(IF(OR(I$100*12+'Model Inputs & Calcs'!$F7<J$117,I$100*12+'Model Inputs & Calcs'!$F7>J$118),0,J$120/$D$30),0) -> 0 | K105: =IFERROR(IF(OR(J$100*12+'Model Inputs & Calcs'!$F7<K$117,J$100*12+'Model Inputs & Calcs'!$F7>K$118),0,K$120/$D$30),0) -> 0 | L105: =IFERROR(IF(OR(K$100*12+'Model Inputs & Calcs'!$F7<L$117,K$100*12+'Model Inputs & Calcs'!$F7>L$118),0,L$120/$D$30),0) -> 0 | ... O105: =IFERROR(IF(OR(N$100*12+'Model Inputs & Calcs'!$F7<O$117,N$100*12+'Model Inputs & Calcs'!$F7>O$118),0,O$120/$D$30),0) -> 0
C106: =EOMONTH(C105,1) -> 46295 | E106: =IFERROR(IF(OR(D$100*12+'Model Inputs & Calcs'!$F8<E$117,D$100*12+'Model Inputs & Calcs'!$F8>E$118),0,E$120/$D$30),0) -> 0 | F106: =IFERROR(IF(OR(E$100*12+'Model Inputs & Calcs'!$F8<F$117,E$100*12+'Model Inputs & Calcs'!$F8>F$118),0,F$120/$D$30),0) -> 0 | G106: =IFERROR(IF(OR(F$100*12+'Model Inputs & Calcs'!$F8<G$117,F$100*12+'Model Inputs & Calcs'!$F8>G$118),0,G$120/$D$30),0) -> 0 | H106: =IFERROR(IF(OR(G$100*12+'Model Inputs & Calcs'!$F8<H$117,G$100*12+'Model Inputs & Calcs'!$F8>H$118),0,H$120/$D$30),0) -> 0 | I106: =IFERROR(IF(OR(H$100*12+'Model Inputs & Calcs'!$F8<I$117,H$100*12+'Model Inputs & Calcs'!$F8>I$118),0,I$120/$D$30),0) -> 0 | J106: =IFERROR(IF(OR(I$100*12+'Model Inputs & Calcs'!$F8<J$117,I$100*12+'Model Inputs & Calcs'!$F8>J$118),0,J$120/$D$30),0) -> 0 | K106: =IFERROR(IF(OR(J$100*12+'Model Inputs & Calcs'!$F8<K$117,J$100*12+'Model Inputs & Calcs'!$F8>K$118),0,K$120/$D$30),0) -> 0 | L106: =IFERROR(IF(OR(K$100*12+'Model Inputs & Calcs'!$F8<L$117,K$100*12+'Model Inputs & Calcs'!$F8>L$118),0,L$120/$D$30),0) -> 0 | ... O106: =IFERROR(IF(OR(N$100*12+'Model Inputs & Calcs'!$F8<O$117,N$100*12+'Model Inputs & Calcs'!$F8>O$118),0,O$120/$D$30),0) -> 0
C107: =EOMONTH(C106,1) -> 46326 | E107: =IFERROR(IF(OR(D$100*12+'Model Inputs & Calcs'!$F9<E$117,D$100*12+'Model Inputs & Calcs'!$F9>E$118),0,E$120/$D$30),0) -> 0 | F107: =IFERROR(IF(OR(E$100*12+'Model Inputs & Calcs'!$F9<F$117,E$100*12+'Model Inputs & Calcs'!$F9>F$118),0,F$120/$D$30),0) -> 0 | G107: =IFERROR(IF(OR(F$100*12+'Model Inputs & Calcs'!$F9<G$117,F$100*12+'Model Inputs & Calcs'!$F9>G$118),0,G$120/$D$30),0) -> 0 | H107: =IFERROR(IF(OR(G$100*12+'Model Inputs & Calcs'!$F9<H$117,G$100*12+'Model Inputs & Calcs'!$F9>H$118),0,H$120/$D$30),0) -> 0 | I107: =IFERROR(IF(OR(H$100*12+'Model Inputs & Calcs'!$F9<I$117,H$100*12+'Model Inputs & Calcs'!$F9>I$118),0,I$120/$D$30),0) -> 0 | J107: =IFERROR(IF(OR(I$100*12+'Model Inputs & Calcs'!$F9<J$117,I$100*12+'Model Inputs & Calcs'!$F9>J$118),0,J$120/$D$30),0) -> 0 | K107: =IFERROR(IF(OR(J$100*12+'Model Inputs & Calcs'!$F9<K$117,J$100*12+'Model Inputs & Calcs'!$F9>K$118),0,K$120/$D$30),0) -> 0 | L107: =IFERROR(IF(OR(K$100*12+'Model Inputs & Calcs'!$F9<L$117,K$100*12+'Model Inputs & Calcs'!$F9>L$118),0,L$120/$D$30),0) -> 0 | ... O107: =IFERROR(IF(OR(N$100*12+'Model Inputs & Calcs'!$F9<O$117,N$100*12+'Model Inputs & Calcs'!$F9>O$118),0,O$120/$D$30),0) -> 0
C108: =EOMONTH(C107,1) -> 46356 | E108: =IFERROR(IF(OR(D$100*12+'Model Inputs & Calcs'!$F10<E$117,D$100*12+'Model Inputs & Calcs'!$F10>E$118),0,E$120/$D$30),0) -> 0 | F108: =IFERROR(IF(OR(E$100*12+'Model Inputs & Calcs'!$F10<F$117,E$100*12+'Model Inputs & Calcs'!$F10>F$118),0,F$120/$D$30),0) -> 0 | G108: =IFERROR(IF(OR(F$100*12+'Model Inputs & Calcs'!$F10<G$117,F$100*12+'Model Inputs & Calcs'!$F10>G$118),0,G$120/$D$30),0) -> 0 | H108: =IFERROR(IF(OR(G$100*12+'Model Inputs & Calcs'!$F10<H$117,G$100*12+'Model Inputs & Calcs'!$F10>H$118),0,H$120/$D$30),0) -> 0 | I108: =IFERROR(IF(OR(H$100*12+'Model Inputs & Calcs'!$F10<I$117,H$100*12+'Model Inputs & Calcs'!$F10>I$118),0,I$120/$D$30),0) -> 0 | J108: =IFERROR(IF(OR(I$100*12+'Model Inputs & Calcs'!$F10<J$117,I$100*12+'Model Inputs & Calcs'!$F10>J$118),0,J$120/$D$30),0) -> 0 | K108: =IFERROR(IF(OR(J$100*12+'Model Inputs & Calcs'!$F10<K$117,J$100*12+'Model Inputs & Calcs'!$F10>K$118),0,K$120/$D$30),0) -> 0 | L108: =IFERROR(IF(OR(K$100*12+'Model Inputs & Calcs'!$F10<L$117,K$100*12+'Model Inputs & Calcs'!$F10>L$118),0,L$120/$D$30),0) -> 0 | ... O108: =IFERROR(IF(OR(N$100*12+'Model Inputs & Calcs'!$F10<O$117,N$100*12+'Model Inputs & Calcs'!$F10>O$118),0,O$120/$D$30),0) -> 0
C109: =EOMONTH(C108,1) -> 46387 | E109: =IFERROR(IF(OR(D$100*12+'Model Inputs & Calcs'!$F11<E$117,D$100*12+'Model Inputs & Calcs'!$F11>E$118),0,E$120/$D$30),0) -> 0 | F109: =IFERROR(IF(OR(E$100*12+'Model Inputs & Calcs'!$F11<F$117,E$100*12+'Model Inputs & Calcs'!$F11>F$118),0,F$120/$D$30),0) -> 0 | G109: =IFERROR(IF(OR(F$100*12+'Model Inputs & Calcs'!$F11<G$117,F$100*12+'Model Inputs & Calcs'!$F11>G$118),0,G$120/$D$30),0) -> 0 | H109: =IFERROR(IF(OR(G$100*12+'Model Inputs & Calcs'!$F11<H$117,G$100*12+'Model Inputs & Calcs'!$F11>H$118),0,H$120/$D$30),0) -> 0 | I109: =IFERROR(IF(OR(H$100*12+'Model Inputs & Calcs'!$F11<I$117,H$100*12+'Model Inputs & Calcs'!$F11>I$118),0,I$120/$D$30),0) -> 0 | J109: =IFERROR(IF(OR(I$100*12+'Model Inputs & Calcs'!$F11<J$117,I$100*12+'Model Inputs & Calcs'!$F11>J$118),0,J$120/$D$30),0) -> 0 | K109: =IFERROR(IF(OR(J$100*12+'Model Inputs & Calcs'!$F11<K$117,J$100*12+'Model Inputs & Calcs'!$F11>K$118),0,K$120/$D$30),0) -> 0 | L109: =IFERROR(IF(OR(K$100*12+'Model Inputs & Calcs'!$F11<L$117,K$100*12+'Model Inputs & Calcs'!$F11>L$118),0,L$120/$D$30),0) -> 0 | ... O109: =IFERROR(IF(OR(N$100*12+'Model Inputs & Calcs'!$F11<O$117,N$100*12+'Model Inputs & Calcs'!$F11>O$118),0,O$120/$D$30),0) -> 0
...

Sheet Sheet1
B2: Stabilised Yield on Cost - Untrended
B3: NLA | C3: =UW!D21 -> 0
B4: Day 1 Operating Rent | C4: =OFFSET(UW!D613,,IF(UW!$E$97>0,UW!$E$95,IF(UW!$F$97>0,UW!$F$95,IF(UW!$G$97>0,UW!$G$95))))/UW!$D$21*12 -> #DIV/0!
B5: Stabilised Occupancy | C5: =UW!$J$24 -> 0
B6: Stabilised Discount Rate | C6: 0.04
B7: Income | C7: =C3*C4*C5*(1-C6) -> #DIV/0!
B8: Other Income | C8: =C7*0.004 -> #DIV/0!
B9: Total Expenses | C9: =UW!D391 -> 375238.2
B10: NOI | C10: =C7+C8-C9 -> #DIV/0!
B12: Normalised Costs | C12: =UW!D388+UW!D389 -> 149700
B13: NOI | C13: =C10+C12 -> #DIV/0!

Sheet Sensitivity Analysis
B2: Sensitivty Analysis
C5: Land Rate | D5: 700 | E5: 750 | F5: 800 | G5: 850 | H5: 900
C6: Asking rate | D6: $341/m2 | E6: $345/m2 | F6: $349/m2 | G6: $353/m2 | H6: $357/m2
C7: IRR | D7: 0.1503 | E7: 0.1502 | F7: 0.1502 | G7: 0.1502 | H7: 0.15

Sheet Submarket Analysis
B2: Deal Name | C2: =UW!D7 -> 0
B3: Address | C3: =UW!D8 -> 0
B4: State | C4: =UW!D10 -> 0
B5: Land Area | C5: =UW!E12 -> 0
B6: GFA | C6: =UW!D20 -> 0
B7: NLA | C7: =UW!D21 -> 0
B9: Geographic Market Area | D9: 8
B11: Stores | D11: Address | G11: NLA | H11: Distance (km) | I11: Direction | J11: Drive Time (Mins) | L11: Development Pipeline | P11: Address | T11: NLA | U11: Distance (km) | V11: Direction | W11: Drive Time (Mins)
L16: Total | T16: =SUM(T12:T15) -> 0
B30: Total | G30: =SUM(G12:G29) -> 0
B34: Supply Summary
D35: Radius (km) | G35: Drive Time (mins)
D36: 3 | E36: 5 | F36: =D9 -> 8 | G36: 3 | H36: 5 | I36: 10
B37: Existing Supply | D37: =SUMIF($H$12:$H$29,"<="&D$36,$G$12:$G$29) -> 0 | E37: =SUMIF($H$12:$H$29,"<="&E$36,$G$12:$G$29) -> 0 | F37: =SUMIF($H$12:$H$29,"<="&F$36,$G$12:$G$29) -> 0 | G37: =SUMIF($J$12:$J$29,"<="&G$36,$G$12:$G$29) -> 0 | H37: =SUMIF($J$12:$J$29,"<="&H$36,$G$12:$G$29) -> 0 | I37: =SUMIF($J$12:$J$29,"<="&I$36,$G$12:$G$29) -> 0
B38: Population
B39: Supply/capita | D39: =IFERROR(D37/D38,0) -> 0 | E39: =IFERROR(E37/E38,0) -> 0 | F39: =IFERROR(F37/F38,0) -> 0 | G39: =IFERROR(G37/G38,0) -> 0 | H39: =IFERROR(H37/H38,0) -> 0 | I39: =IFERROR(I37/I38,0) -> 0
B40: Add: Subject Supply | D40: =D37+$C$7 -> 0 | E40: =E37+$C$7 -> 0 | F40: =F37+$C$7 -> 0 | G40: =G37+$C$7 -> 0 | H40: =H37+$C$7 -> 0 | I40: =I37+$C$7 -> 0
B41: Supply/capita | D41: =IFERROR(D40/D38,0) -> 0 | E41: =IFERROR(E40/E38,0) -> 0 | F41: =IFERROR(F40/F38,0) -> 0 | G41: =IFERROR(G40/G38,0) -> 0 | H41: =IFERROR(H40/H38,0) -> 0 | I41: =IFERROR(I40/I38,0) -> 0
B42: Add: Pipeline Supply | D42: =SUMIF($U$12:$U$15,"<="&D$36,$T$12:$T$15)+D40 -> 0 | E42: =SUMIF($U$12:$U$15,"<="&E$36,$T$12:$T$15)+E40 -> 0 | F42: =SUMIF($U$12:$U$15,"<="&F$36,$T$12:$T$15)+F40 -> 0 | G42: =SUMIF($W$12:$W$15,"<="&G$36,$T$12:$T$15)+G40 -> 0 | H42: =SUMIF($W$12:$W$15,"<="&H$36,$T$12:$T$15)+H40 -> 0 | I42: =SUMIF($W$12:$W$15,"<="&I$36,$T$12:$T$15)+I40 -> 0
B43: Supply/capita | D43: =IFERROR(D42/D38,0) -> 0 | E43: =IFERROR(E42/E38,0) -> 0 | F43: =IFERROR(F42/F38,0) -> 0 | G43: =IFERROR(G42/G38,0) -> 0 | H43: =IFERROR(H42/H38,0) -> 0 | I43: =IFERROR(I42/I38,0) -> 0
B44: StoreLocal Pacific Pines | D44: 0.13 | E44: 0.47 | F44: 0.51 | G44: 16.29 | H44: 0.73 | I44: 0.59
B45: StoreLocal Pimpama | D45: 0.41 | E45: 0.73 | F45: 0.45 | G45: 4.01 | H45: 1.81 | I45: 1.42
B46: StoreLocal Berrinba | D46: 0.4 | E46: 0.44 | F46: 0.33 | G46: 1.64 | H46: 0.7 | I46: 0.45
B47: StoreLocal Port Kennedy | D47: 1.61 | E47: 0.7 | F47: 0.3 | G47: 9.76 | H47: 1.49 | I47: 0.44
B49: Demand Table | K49: Over/(Under) Supply
D50: Radius (km) | G50: Drive Time (mins) | M50: Radius (km) | P50: Drive Time (mins)
B51: sqm/Demand/Person | D51: =D$36 -> 3 | E51: =E$36 -> 5 | F51: =F$36 -> 8 | G51: =G$36 -> 3 | H51: =H$36 -> 5 | I51: =I$36 -> 10 | K51: sqm/Demand/Person | M51: =D$36 -> 3 | N51: =E$36 -> 5 | O51: =F$36 -> 8 | P51: =G$36 -> 3 | Q51: =H$36 -> 5 | R51: =I$36 -> 10
B52: 0.1 | D52: =$B52*D$38 -> 0 | E52: =$B52*E$38 -> 0 | F52: =$B52*F$38 -> 0 | G52: =$B52*G$38 -> 0 | H52: =$B52*H$38 -> 0 | I52: =$B52*I$38 -> 0 | K52: 0.1 | M52: =D$42-D52 -> 0 | N52: =E$42-E52 -> 0 | O52: =F$42-F52 -> 0 | P52: =G$42-G52 -> 0 | Q52: =H$42-H52 -> 0 | R52: =I$42-I52 -> 0
B53: 0.2 | D53: =$B53*D$38 -> 0 | E53: =$B53*E$38 -> 0 | F53: =$B53*F$38 -> 0 | G53: =$B53*G$38 -> 0 | H53: =$B53*H$38 -> 0 | I53: =$B53*I$38 -> 0 | K53: 0.2 | M53: =D$42-D53 -> 0 | N53: =E$42-E53 -> 0 | O53: =F$42-F53 -> 0 | P53: =G$42-G53 -> 0 | Q53: =H$42-H53 -> 0 | R53: =I$42-I53 -> 0
B54: 0.3 | D54: =$B54*D$38 -> 0 | E54: =$B54*E$38 -> 0 | F54: =$B54*F$38 -> 0 | G54: =$B54*G$38 -> 0 | H54: =$B54*H$38 -> 0 | I54: =$B54*I$38 -> 0 | K54: 0.3 | M54: =D$42-D54 -> 0 | N54: =E$42-E54 -> 0 | O54: =F$42-F54 -> 0 | P54: =G$42-G54 -> 0 | Q54: =H$42-H54 -> 0 | R54: =I$42-I54 -> 0
B55: 0.4 | D55: =$B55*D$38 -> 0 | E55: =$B55*E$38 -> 0 | F55: =$B55*F$38 -> 0 | G55: =$B55*G$38 -> 0 | H55: =$B55*H$38 -> 0 | I55: =$B55*I$38 -> 0 | K55: 0.4 | M55: =D$42-D55 -> 0 | N55: =E$42-E55 -> 0 | O55: =F$42-F55 -> 0 | P55: =G$42-G55 -> 0 | Q55: =H$42-H55 -> 0 | R55: =I$42-I55 -> 0
B56: 0.5 | D56: =$B56*D$38 -> 0 | E56: =$B56*E$38 -> 0 | F56: =$B56*F$38 -> 0 | G56: =$B56*G$38 -> 0 | H56: =$B56*H$38 -> 0 | I56: =$B56*I$38 -> 0 | K56: 0.5 | M56: =D$42-D56 -> 0 | N56: =E$42-E56 -> 0 | O56: =F$42-F56 -> 0 | P56: =G$42-G56 -> 0 | Q56: =H$42-H56 -> 0 | R56: =I$42-I56 -> 0
B57: 0.6 | D57: =$B57*D$38 -> 0 | E57: =$B57*E$38 -> 0 | F57: =$B57*F$38 -> 0 | G57: =$B57*G$38 -> 0 | H57: =$B57*H$38 -> 0 | I57: =$B57*I$38 -> 0 | K57: 0.6 | M57: =D$42-D57 -> 0 | N57: =E$42-E57 -> 0 | O57: =F$42-F57 -> 0 | P57: =G$42-G57 -> 0 | Q57: =H$42-H57 -> 0 | R57: =I$42-I57 -> 0
B58: 0.7 | D58: =$B58*D$38 -> 0 | E58: =$B58*E$38 -> 0 | F58: =$B58*F$38 -> 0 | G58: =$B58*G$38 -> 0 | H58: =$B58*H$38 -> 0 | I58: =$B58*I$38 -> 0 | K58: 0.7 | M58: =D$42-D58 -> 0 | N58: =E$42-E58 -> 0 | O58: =F$42-F58 -> 0 | P58: =G$42-G58 -> 0 | Q58: =H$42-H58 -> 0 | R58: =I$42-I58 -> 0
C61: Deomgraphics | D61: =C2 -> 0 | E61: =C4 -> 0 | F61: Variance to State | G61: Australia | H61: Variance to AUS
C62: Avg. No. of People per Household | F62: =D62/E62-1 -> #DIV/0! | G62: 2.5 | H62: =D62/G62-1 -> -1
C63: Median Weekly Household Income | F63: =D63/E63-1 -> #DIV/0! | G63: 1746 | H63: =D63/G63-1 -> -1
C64: Less than $650 (Weekly) | F64: =D64/E64-1 -> #DIV/0! | G64: 0.165 | H64: =D64/G64-1 -> -1
C65: More than $3,000 (Weekly) | F65: =D65/E65-1 -> #DIV/0! | G65: 0.243 | H65: =D65/G65-1 -> -1
C66: Median Monthly Mortgage Repayments | F66: =D66/E66-1 -> #DIV/0! | G66: 1863 | H66: =D66/G66-1 -> -1
C67: Owned Outright | F67: =D67/E67-1 -> #DIV/0! | G67: 0.31 | H67: =D67/G67-1 -> -1
C68: Owned with a Mortgage | F68: =D68/E68-1 -> #DIV/0! | G68: 0.35 | H68: =D68/G68-1 -> -1
C69: Rented | F69: =D69/E69-1 -> #DIV/0! | G69: 0.306 | H69: =D69/G69-1 -> -1
C70: Median Weekly Rent | F70: =D70/E70-1 -> #DIV/0! | G70: 375 | H70: =D70/G70-1 -> -1
C71: Rent Payments less than 30% of Income | F71: =D71/E71-1 -> #DIV/0! | G71: 0.587 | H71: =D71/G71-1 -> -1
C72: Rent Payments more than 30% of Income | F72: =D72/E72-1 -> #DIV/0! | G72: 0.322 | H72: =D72/G72-1 -> -1
C73: Mortgage Payments less than 30% of Income | F73: =D73/E73-1 -> #DIV/0! | G73: 0.74 | H73: =D73/G73-1 -> -1
... C77: Flat or Apartment | F77: =D77/E77-1 -> #DIV/0! | G77: 0.142 | H77: =D77/G77-1 -> -1

Sheet Comps & Unit Mix
B1: STORELOCAL xxx MARKET RENT ANALYSIS
B3: 10 | C3: 1 | D3: 3 | E3: 5 | F3: =B3 -> 10 | J3: Competitor:
B4: Total SF: | C4: =SUMIF($N$9:$AS$9,"<="&C3,$N$6:$AS$6)+$G$6 -> 0 | D4: =SUMIF($N$9:$AS$9,"<="&D3,$N$6:$AS$6)+$G$6 -> 0 | E4: =SUMIF($N$9:$AS$9,"<="&E3,$N$6:$AS$6)+G6 -> 0 | F4: =SUMIF($N$9:$AS$9,"<="&F3,$N$6:$AS$6)+$G$6 -> 0 | J4: Address:
B5: Pop: | J5: Occupancy:
B6: SM / Person: | C6: =C4/C5 -> #DIV/0! | D6: =D4/D5 -> #DIV/0! | E6: =E4/E5 -> #DIV/0! | F6: =F4/F5 -> #DIV/0! | G6: =AW268 -> 0 | J6: Size: | N6: =N199 -> 0 | P6: =P199 -> 0 | R6: =R199 -> 0 | T6: =T199 -> 0 | V6: =V199 -> 0 | X6: =X199 -> 0 | Z6: =Z199 -> 0 | AB6: =AB199 -> 0 | AD6: =AD199 -> 0 | AF6: =AF199 -> 0 | AH6: =AH199 -> 0 | AJ6: 0 | AL6: 0 | AN6: 0 | AP6: 0 | AR6: =AR199 -> 0
B7: higher | J7: RV / Boat? : | N7: No | P7: No | R7: No | T7: No | V7: No | X7: Yes | Z7: Yes | AB7: No | AD7: No | AF7: No | AH7: No | AJ7: No | AL7: No | AN7: No | AP7: No | AR7: No
B8: lower | E8: Date created: | F8: <Insert Date> | J8: Direction:
B9: new | E9: Date last updated: | F9: <Insert Date> | J9: Distance:
G10: SELECTED COMPS | I10: RENT COMPS | K10: RENT DISCOUNT | N10: Yes | O10: =N10 -> Yes | P10: Yes | Q10: =P10 -> Yes | R10: Yes | S10: =R10 -> Yes | T10: Yes | U10: =T10 -> Yes | V10: Yes | W10: =V10 -> Yes | X10: No | Y10: =X10 -> No | Z10: No | AB10: No | AC10: =AB10 -> No | AD10: No | AE10: =AD10 -> No | AF10: No | AG10: =AF10 -> No | AH10: No | AI10: =AH10 -> No | AJ10: No | AK10: No | AL10: No | AM10: No | AN10: No | AO10: No | AP10: No | AR10: No | AS10: =AR10 -> No
B11: Size | C11: SM | D11: Floor | E11: Type | F11: CC? | G11: Per SM | H11: Per Unit | I11: Per SM | J11: Per Unit | K11: Per SM | L11: Per Unit | N11: Asking Rate | O11: Discount | P11: Asking Rate | Q11: Discount | R11: Asking Rate | S11: Discount | T11: Asking Rate | U11: Discount | V11: Asking Rate | W11: Discount | X11: Asking Rate | Y11: Discount | Z11: Asking Rate | AA11: Discount | AB11: Asking Rate | AC11: Discount | AD11: Asking Rate | AE11: Discount | AF11: Asking Rate | AG11: Discount | AH11: Asking Rate | AI11: Discount | AJ11: Asking Rate | AK11: Discount | AL11: Asking Rate | AM11: Discount | AN11: Asking Rate | AO11: Discount | AP11: Asking Rate | AQ11: Discount | AR11: Asking Rate | AS11: Discount
B12: 1.5x1.5 | C12: 2.25 | D12: 1 | E12: Drive-up | F12: No | G12: =IFERROR((H12/$C12),"-") -> - | H12: =IFERROR(AVERAGEIFS(N12:AS12,$N$11:$AS$11,"Asking Rate",$N$10:$AS$10,$B$204),"-") -> - | I12: =IFERROR((J12/$C12),"-") -> - | J12: =IFERROR(AVERAGEIF($N$9:$AS$9,"<="&$B$3,N12:AS12),"-") -> - | K12: =IFERROR((L12/$C12),"-") -> - | L12: =IFERROR(AVERAGEIFS(N12:AS12,$N$11:$AS$11,"Discount",$N$10:$AS$10,$B$204),"-") -> -
B13: 1.5x2 | C13: 3 | D13: 1 | E13: Drive-up | F13: No | G13: =IFERROR((H13/$C13),"-") -> - | H13: =IFERROR(AVERAGEIFS(N13:AS13,$N$11:$AS$11,"Asking Rate",$N$10:$AS$10,$B$204),"-") -> - | I13: =IFERROR((J13/$C13),"-") -> - | J13: =IFERROR(AVERAGEIF($N$9:$AS$9,"<="&$B$3,N13:AS13),"-") -> - | K13: =IFERROR((L13/$C13),"-") -> - | L13: =IFERROR(AVERAGEIFS(N13:AS13,$N$11:$AS$11,"Discount",$N$10:$AS$10,$B$204),"-") -> -
B14: 1.2x3 | C14: 3.6 | D14: 1 | E14: Drive-up | F14: No | G14: =IFERROR((H14/$C14),"-") -> - | H14: =IFERROR(AVERAGEIFS(N14:AS14,$N$11:$AS$11,"Asking Rate",$N$10:$AS$10,$B$204),"-") -> - | I14: =IFERROR((J14/$C14),"-") -> - | J14: =IFERROR(AVERAGEIF($N$9:$AS$9,"<="&$B$3,N14:AS14),"-") -> - | K14: =IFERROR((L14/$C14),"-") -> - | L14: =IFERROR(AVERAGEIFS(N14:AS14,$N$11:$AS$11,"Discount",$N$10:$AS$10,$B$204),"-") -> -
B15: 1.4x3 | C15: 4.2 | D15: 1 | E15: Drive-up | F15: No | G15: =IFERROR((H15/$C15),"-") -> - | H15: =IFERROR(AVERAGEIFS(N15:AS15,$N$11:$AS$11,"Asking Rate",$N$10:$AS$10,$B$204),"-") -> - | I15: =IFERROR((J15/$C15),"-") -> - | J15: =IFERROR(AVERAGEIF($N$9:$AS$9,"<="&$B$3,N15:AS15),"-") -> - | K15: =IFERROR((L15/$C15),"-") -> - | L15: =IFERROR(AVERAGEIFS(N15:AS15,$N$11:$AS$11,"Discount",$N$10:$AS$10,$B$204),"-") -> -
B16: 1.5x3 | C16: 4.5 | D16: 1 | E16: Drive-up | F16: No | G16: =IFERROR((H16/$C16),"-") -> - | H16: =IFERROR(AVERAGEIFS(N16:AS16,$N$11:$AS$11,"Asking Rate",$N$10:$AS$10,$B$204),"-") -> - | I16: =IFERROR((J16/$C16),"-") -> - | J16: =IFERROR(AVERAGEIF($N$9:$AS$9,"<="&$B$3,N16:AS16),"-") -> - | K16: =IFERROR((L16/$C16),"-") -> - | L16: =IFERROR(AVERAGEIFS(N16:AS16,$N$11:$AS$11,"Discount",$N$10:$AS$10,$B$204),"-") -> -
B17: 2x3 | C17: 6 | D17: 1 | E17: Drive-up | F17: No | G17: =IFERROR((H17/$C17),"-") -> - | H17: =IFERROR(AVERAGEIFS(N17:AS17,$N$11:$AS$11,"Asking Rate",$N$10:$AS$10,$B$204),"-") -> - | I17: =IFERROR((J17/$C17),"-") -> - | J17: =IFERROR(AVERAGEIF($N$9:$AS$9,"<="&$B$3,N17:AS17),"-") -> - | K17: =IFERROR((L17/$C17),"-") -> - | L17: =IFERROR(AVERAGEIFS(N17:AS17,$N$11:$AS$11,"Discount",$N$10:$AS$10,$B$204),"-") -> -
B18: 1.4x4.5 | C18: 6.3 | D18: 1 | E18: Drive-up | F18: No | G18: =IFERROR((H18/$C18),"-") -> - | H18: =IFERROR(AVERAGEIFS(N18:AS18,$N$11:$AS$11,"Asking Rate",$N$10:$AS$10,$B$204),"-") -> - | I18: =IFERROR((J18/$C18),"-") -> - | J18: =IFERROR(AVERAGEIF($N$9:$AS$9,"<="&$B$3,N18:AS18),"-") -> - | K18: =IFERROR((L18/$C18),"-") -> - | L18: =IFERROR(AVERAGEIFS(N18:AS18,$N$11:$AS$11,"Discount",$N$10:$AS$10,$B$204),"-") -> -
B19: 2.3x3 | C19: 6.9 | D19: 1 | E19: Drive-up | F19: No | G19: =IFERROR((H19/$C19),"-") -> - | H19: =IFERROR(AVERAGEIFS(N19:AS19,$N$11:$AS$11,"Asking Rate",$N$10:$AS$10,$B$204),"-") -> - | I19: =IFERROR((J19/$C19),"-") -> - | J19: =IFERROR(AVERAGEIF($N$9:$AS$9,"<="&$B$3,N19:AS19),"-") -> - | K19: =IFERROR((L19/$C19),"-") -> - | L19: =IFERROR(AVERAGEIFS(N19:AS19,$N$11:$AS$11,"Discount",$N$10:$AS$10,$B$204),"-") -> -
B20: 2.5x3 | C20: 7.5 | D20: 1 | E20: Drive-up | F20: No | G20: =IFERROR((H20/$C20),"-") -> - | H20: =IFERROR(AVERAGEIFS(N20:AS20,$N$11:$AS$11,"Asking Rate",$N$10:$AS$10,$B$204),"-") -> - | I20: =IFERROR((J20/$C20),"-") -> - | J20: =IFERROR(AVERAGEIF($N$9:$AS$9,"<="&$B$3,N20:AS20),"-") -> - | K20: =IFERROR((L20/$C20),"-") -> - | L20: =IFERROR(AVERAGEIFS(N20:AS20,$N$11:$AS$11,"Discount",$N$10:$AS$10,$B$204),"-") -> -
B21: 2x4 | C21: 8 | D21: 1 | E21: Drive-up | F21: No | G21: =IFERROR((H21/$C21),"-") -> - | H21: =IFERROR(AVERAGEIFS(N21:AS21,$N$11:$AS$11,"Asking Rate",$N$10:$AS$10,$B$204),"-") -> - | I21: =IFERROR((J21/$C21),"-") -> - | J21: =IFERROR(AVERAGEIF($N$9:$AS$9,"<="&$B$3,N21:AS21),"-") -> - | K21: =IFERROR((L21/$C21),"-") -> - | L21: =IFERROR(AVERAGEIFS(N21:AS21,$N$11:$AS$11,"Discount",$N$10:$AS$10,$B$204),"-") -> -
B22: 6x1.4 | C22: 8.4 | D22: 1 | E22: Drive-up | F22: No | G22: =IFERROR((H22/$C22),"-") -> - | H22: =IFERROR(AVERAGEIFS(N22:AS22,$N$11:$AS$11,"Asking Rate",$N$10:$AS$10,$B$204),"-") -> - | I22: =IFERROR((J22/$C22),"-") -> - | J22: =IFERROR(AVERAGEIF($N$9:$AS$9,"<="&$B$3,N22:AS22),"-") -> - | K22: =IFERROR((L22/$C22),"-") -> - | L22: =IFERROR(AVERAGEIFS(N22:AS22,$N$11:$AS$11,"Discount",$N$10:$AS$10,$B$204),"-") -> -
B23: 3x3 | C23: 9 | D23: 1 | E23: Drive-up | F23: No | G23: =IFERROR((H23/$C23),"-") -> - | H23: =IFERROR(AVERAGEIFS(N23:AS23,$N$11:$AS$11,"Asking Rate",$N$10:$AS$10,$B$204),"-") -> - | I23: =IFERROR((J23/$C23),"-") -> - | J23: =IFERROR(AVERAGEIF($N$9:$AS$9,"<="&$B$3,N23:AS23),"-") -> - | K23: =IFERROR((L23/$C23),"-") -> - | L23: =IFERROR(AVERAGEIFS(N23:AS23,$N$11:$AS$11,"Discount",$N$10:$AS$10,$B$204),"-") -> -
B24: 3x3.5 | C24: 10.5 | D24: 1 | E24: Drive-up | F24: No | G24: =IFERROR((H24/$C24),"-") -> - | H24: =IFERROR(AVERAGEIFS(N24:AS24,$N$11:$AS$11,"Asking Rate",$N$10:$AS$10,$B$204),"-") -> - | I24: =IFERROR((J24/$C24),"-") -> - | J24: =IFERROR(AVERAGEIF($N$9:$AS$9,"<="&$B$3,N24:AS24),"-") -> - | K24: =IFERROR((L24/$C24),"-") -> - | L24: =IFERROR(AVERAGEIFS(N24:AS24,$N$11:$AS$11,"Discount",$N$10:$AS$10,$B$204),"-") -> -
C25: 11.2 | D25: 1 | E25: Drive-up | F25: No | G25: =IFERROR((H25/$C25),"-") -> - | H25: =IFERROR(AVERAGEIFS(N25:AS25,$N$11:$AS$11,"Asking Rate",$N$10:$AS$10,$B$204),"-") -> - | I25: =IFERROR((J25/$C25),"-") -> - | J25: =IFERROR(AVERAGEIF($N$9:$AS$9,"<="&$B$3,N25:AS25),"-") -> - | K25: =IFERROR((L25/$C25),"-") -> - | L25: =IFERROR(AVERAGEIFS(N25:AS25,$N$11:$AS$11,"Discount",$N$10:$AS$10,$B$204),"-") -> -
B26: 3x3.80 | C26: 11.4 | D26: 1 | E26: Drive-up | F26: No | G26: =IFERROR((H26/$C26),"-") -> - | H26: =IFERROR(AVERAGEIFS(N26:AS26,$N$11:$AS$11,"Asking Rate",$N$10:$AS$10,$B$204),"-") -> - | I26: =IFERROR((J26/$C26),"-") -> - | J26: =IFERROR(AVERAGEIF($N$9:$AS$9,"<="&$B$3,N26:AS26),"-") -> - | K26: =IFERROR((L26/$C26),"-") -> - | L26: =IFERROR(AVERAGEIFS(N26:AS26,$N$11:$AS$11,"Discount",$N$10:$AS$10,$B$204),"-") -> -
B27: 3x4 | C27: 12 | D27: 1 | E27: Drive-up | F27: No | G27: =IFERROR((H27/$C27),"-") -> - | H27: =IFERROR(AVERAGEIFS(N27:AS27,$N$11:$AS$11,"Asking Rate",$N$10:$AS$10,$B$204),"-") -> - | I27: =IFERROR((J27/$C27),"-") -> - | J27: =IFERROR(AVERAGEIF($N$9:$AS$9,"<="&$B$3,N27:AS27),"-") -> - | K27: =IFERROR((L27/$C27),"-") -> - | L27: =IFERROR(AVERAGEIFS(N27:AS27,$N$11:$AS$11,"Discount",$N$10:$AS$10,$B$204),"-") -> -
B28: 3.5x4 | C28: 12.25 | D28: 1 | E28: Drive-up | F28: No | G28: =IFERROR((H28/$C28),"-") -> - | H28: =IFERROR(AVERAGEIFS(N28:AS28,$N$11:$AS$11,"Asking Rate",$N$10:$AS$10,$B$204),"-") -> - | I28: =IFERROR((J28/$C28),"-") -> - | J28: =IFERROR(AVERAGEIF($N$9:$AS$9,"<="&$B$3,N28:AS28),"-") -> - | K28: =IFERROR((L28/$C28),"-") -> - | L28: =IFERROR(AVERAGEIFS(N28:AS28,$N$11:$AS$11,"Discount",$N$10:$AS$10,$B$204),"-") -> -
B29: 4.5x2.8 | C29: 12.6 | D29: 1 | E29: Drive-up | F29: No | G29: =IFERROR((H29/$C29),"-") -> - | H29: =IFERROR(AVERAGEIFS(N29:AS29,$N$11:$AS$11,"Asking Rate",$N$10:$AS$10,$B$204),"-") -> - | I29: =IFERROR((J29/$C29),"-") -> - | J29: =IFERROR(AVERAGEIF($N$9:$AS$9,"<="&$B$3,N29:AS29),"-") -> - | K29: =IFERROR((L29/$C29),"-") -> - | L29: =IFERROR(AVERAGEIFS(N29:AS29,$N$11:$AS$11,"Discount",$N$10:$AS$10,$B$204),"-") -> -
B30: 4.5x3 | C30: 13.5 | D30: 1 | E30: Drive-up | F30: No | G30: =IFERROR((H30/$C30),"-") -> - | H30: =IFERROR(AVERAGEIFS(N30:AS30,$N$11:$AS$11,"Asking Rate",$N$10:$AS$10,$B$204),"-") -> - | I30: =IFERROR((J30/$C30),"-") -> - | J30: =IFERROR(AVERAGEIF($N$9:$AS$9,"<="&$B$3,N30:AS30),"-") -> - | K30: =IFERROR((L30/$C30),"-") -> - | L30: =IFERROR(AVERAGEIFS(N30:AS30,$N$11:$AS$11,"Discount",$N$10:$AS$10,$B$204),"-") -> -
B31: 3x5 | C31: 15 | D31: 1 | E31: Drive-up | F31: No | G31: =IFERROR((H31/$C31),"-") -> - | H31: =IFERROR(AVERAGEIFS(N31:AS31,$N$11:$AS$11,"Asking Rate",$N$10:$AS$10,$B$204),"-") -> - | I31: =IFERROR((J31/$C31),"-") -> - | J31: =IFERROR(AVERAGEIF($N$9:$AS$9,"<="&$B$3,N31:AS31),"-") -> - | K31: =IFERROR((L31/$C31),"-") -> - | L31: =IFERROR(AVERAGEIFS(N31:AS31,$N$11:$AS$11,"Discount",$N$10:$AS$10,$B$204),"-") -> -
B32: 4x4 | C32: 16 | D32: 1 | E32: Drive-up | F32: No | G32: =IFERROR((H32/$C32),"-") -> - | H32: =IFERROR(AVERAGEIFS(N32:AS32,$N$11:$AS$11,"Asking Rate",$N$10:$AS$10,$B$204),"-") -> - | I32: =IFERROR((J32/$C32),"-") -> - | J32: =IFERROR(AVERAGEIF($N$9:$AS$9,"<="&$B$3,N32:AS32),"-") -> - | K32: =IFERROR((L32/$C32),"-") -> - | L32: =IFERROR(AVERAGEIFS(N32:AS32,$N$11:$AS$11,"Discount",$N$10:$AS$10,$B$204),"-") -> -
C33: 16.24 | D33: 1 | E33: Drive-up | F33: No | G33: =IFERROR((H33/$C33),"-") -> - | H33: =IFERROR(AVERAGEIFS(N33:AS33,$N$11:$AS$11,"Asking Rate",$N$10:$AS$10,$B$204),"-") -> - | I33: =IFERROR((J33/$C33),"-") -> - | J33: =IFERROR(AVERAGEIF($N$9:$AS$9,"<="&$B$3,N33:AS33),"-") -> - | K33: =IFERROR((L33/$C33),"-") -> - | L33: =IFERROR(AVERAGEIFS(N33:AS33,$N$11:$AS$11,"Discount",$N$10:$AS$10,$B$204),"-") -> -
B34: 3x5.5 | C34: 16.5 | D34: 1 | E34: Drive-up | F34: No | G34: =IFERROR((H34/$C34),"-") -> - | H34: =IFERROR(AVERAGEIFS(N34:AS34,$N$11:$AS$11,"Asking Rate",$N$10:$AS$10,$B$204),"-") -> - | I34: =IFERROR((J34/$C34),"-") -> - | J34: =IFERROR(AVERAGEIF($N$9:$AS$9,"<="&$B$3,N34:AS34),"-") -> - | K34: =IFERROR((L34/$C34),"-") -> - | L34: =IFERROR(AVERAGEIFS(N34:AS34,$N$11:$AS$11,"Discount",$N$10:$AS$10,$B$204),"-") -> -
B35: 6x2.8 | C35: 16.8 | D35: 1 | E35: Drive-up | F35: No | G35: =IFERROR((H35/$C35),"-") -> - | H35: =IFERROR(AVERAGEIFS(N35:AS35,$N$11:$AS$11,"Asking Rate",$N$10:$AS$10,$B$204),"-") -> - | I35: =IFERROR((J35/$C35),"-") -> - | J35: =IFERROR(AVERAGEIF($N$9:$AS$9,"<="&$B$3,N35:AS35),"-") -> - | K35: =IFERROR((L35/$C35),"-") -> - | L35: =IFERROR(AVERAGEIFS(N35:AS35,$N$11:$AS$11,"Discount",$N$10:$AS$10,$B$204),"-") -> -
B36: 2.5x7 | C36: 17.5 | D36: 1 | E36: Drive-up | F36: No | G36: =IFERROR((H36/$C36),"-") -> - | H36: =IFERROR(AVERAGEIFS(N36:AS36,$N$11:$AS$11,"Asking Rate",$N$10:$AS$10,$B$204),"-") -> - | I36: =IFERROR((J36/$C36),"-") -> - | J36: =IFERROR(AVERAGEIF($N$9:$AS$9,"<="&$B$3,N36:AS36),"-") -> - | K36: =IFERROR((L36/$C36),"-") -> - | L36: =IFERROR(AVERAGEIFS(N36:AS36,$N$11:$AS$11,"Discount",$N$10:$AS$10,$B$204),"-") -> -
B37: 6x3 | C37: 18 | D37: 1 | E37: Drive-up | F37: No | G37: =IFERROR((H37/$C37),"-") -> - | H37: =IFERROR(AVERAGEIFS(N37:AS37,$N$11:$AS$11,"Asking Rate",$N$10:$AS$10,$B$204),"-") -> - | I37: =IFERROR((J37/$C37),"-") -> - | J37: =IFERROR(AVERAGEIF($N$9:$AS$9,"<="&$B$3,N37:AS37),"-") -> - | K37: =IFERROR((L37/$C37),"-") -> - | L37: =IFERROR(AVERAGEIFS(N37:AS37,$N$11:$AS$11,"Discount",$N$10:$AS$10,$B$204),"-") -> -
C38: 19.5 | D38: 1 | E38: Drive-up | F38: No | G38: =IFERROR((H38/$C38),"-") -> - | H38: =IFERROR(AVERAGEIFS(N38:AS38,$N$11:$AS$11,"Asking Rate",$N$10:$AS$10,$B$204),"-") -> - | I38: =IFERROR((J38/$C38),"-") -> - | J38: =IFERROR(AVERAGEIF($N$9:$AS$9,"<="&$B$3,N38:AS38),"-") -> - | K38: =IFERROR((L38/$C38),"-") -> - | L38: =IFERROR(AVERAGEIFS(N38:AS38,$N$11:$AS$11,"Discount",$N$10:$AS$10,$B$204),"-") -> -
B39: 3x7 | C39: 21 | D39: 1 | E39: Drive-up | F39: No | G39: =IFERROR((H39/$C39),"-") -> - | H39: =IFERROR(AVERAGEIFS(N39:AS39,$N$11:$AS$11,"Asking Rate",$N$10:$AS$10,$B$204),"-") -> - | I39: =IFERROR((J39/$C39),"-") -> - | J39: =IFERROR(AVERAGEIF($N$9:$AS$9,"<="&$B$3,N39:AS39),"-") -> - | K39: =IFERROR((L39/$C39),"-") -> - | L39: =IFERROR(AVERAGEIFS(N39:AS39,$N$11:$AS$11,"Discount",$N$10:$AS$10,$B$204),"-") -> -
B40: 3x7.5 | C40: 22.5 | D40: 1 | E40: Drive-up | F40: No | G40: =IFERROR((H40/$C40),"-") -> - | H40: =IFERROR(AVERAGEIFS(N40:AS40,$N$11:$AS$11,"Asking Rate",$N$10:$AS$10,$B$204),"-") -> - | I40: =IFERROR((J40/$C40),"-") -> - | J40: =IFERROR(AVERAGEIF($N$9:$AS$9,"<="&$B$3,N40:AS40),"-") -> - | K40: =IFERROR((L40/$C40),"-") -> - | L40: =IFERROR(AVERAGEIFS(N40:AS40,$N$11:$AS$11,"Discount",$N$10:$AS$10,$B$204),"-") -> -
B41: 8x3 | C41: 24 | D41: 1 | E41: Drive-up | F41: No | G41: =IFERROR((H41/$C41),"-") -> - | H41: =IFERROR(AVERAGEIFS(N41:AS41,$N$11:$AS$11,"Asking Rate",$N$10:$AS$10,$B$204),"-") -> - | I41: =IFERROR((J41/$C41),"-") -> - | J41: =IFERROR(AVERAGEIF($N$9:$AS$9,"<="&$B$3,N41:AS41),"-") -> - | K41: =IFERROR((L41/$C41),"-") -> - | L41: =IFERROR(AVERAGEIFS(N41:AS41,$N$11:$AS$11,"Discount",$N$10:$AS$10,$B$204),"-") -> -
B42: 8.5x3 | C42: 25.5 | D42: 1 | E42: Drive-up | F42: No | G42: =IFERROR((H42/$C42),"-") -> - | H42: =IFERROR(AVERAGEIFS(N42:AS42,$N$11:$AS$11,"Asking Rate",$N$10:$AS$10,$B$204),"-") -> - | I42: =IFERROR((J42/$C42),"-") -> - | J42: =IFERROR(AVERAGEIF($N$9:$AS$9,"<="&$B$3,N42:AS42),"-") -> - | K42: =IFERROR((L42/$C42),"-") -> - | L42: =IFERROR(AVERAGEIFS(N42:AS42,$N$11:$AS$11,"Discount",$N$10:$AS$10,$B$204),"-") -> -
B43: 3x9 | C43: 27 | D43: 1 | E43: Drive-up | F43: No | G43: =IFERROR((H43/$C43),"-") -> - | H43: =IFERROR(AVERAGEIFS(N43:AS43,$N$11:$AS$11,"Asking Rate",$N$10:$AS$10,$B$204),"-") -> - | I43: =IFERROR((J43/$C43),"-") -> - | J43: =IFERROR(AVERAGEIF($N$9:$AS$9,"<="&$B$3,N43:AS43),"-") -> - | K43: =IFERROR((L43/$C43),"-") -> - | L43: =IFERROR(AVERAGEIFS(N43:AS43,$N$11:$AS$11,"Discount",$N$10:$AS$10,$B$204),"-") -> -
B44: 3x12 | C44: 36 | D44: 1 | E44: Drive-up | F44: No | G44: =IFERROR((H44/$C44),"-") -> - | H44: =IFERROR(AVERAGEIFS(N44:AS44,$N$11:$AS$11,"Asking Rate",$N$10:$AS$10,$B$204),"-") -> - | I44: =IFERROR((J44/$C44),"-") -> - | J44: =IFERROR(AVERAGEIF($N$9:$AS$9,"<="&$B$3,N44:AS44),"-") -> - | K44: =IFERROR((L44/$C44),"-") -> - | L44: =IFERROR(AVERAGEIFS(N44:AS44,$N$11:$AS$11,"Discount",$N$10:$AS$10,$B$204),"-") -> -
A45: x | B45: Size | C45: SM | D45: Floor | E45: Type | F45: CC? | G45: Per SM | H45: Per Unit | I45: Per SM | J45: Per Unit | K45: Per SM | L45: Per Unit
B46: 1x1 | C46: 1 | D46: 1 | E46: Ground | F46: No | G46: =IFERROR((H46/$C46),"-") -> - | H46: =IFERROR(AVERAGEIFS(N46:AS46,$N$11:$AS$11,"Asking Rate",$N$10:$AS$10,$B$204),"-") -> - | I46: =IFERROR((J46/$C46),"-") -> - | J46: =IFERROR(AVERAGEIF($N$9:$AS$9,"<="&$B$3,N46:AS46),"-") -> - | K46: =IFERROR((L46/$C46),"-") -> - | L46: =IFERROR(AVERAGEIFS(N46:AS46,$N$11:$AS$11,"Discount",$N$10:$AS$10,$B$204),"-") -> -
C47: 1.5 | D47: 1 | E47: Ground | F47: No | G47: =IFERROR((H47/$C47),"-") -> - | H47: =IFERROR(AVERAGEIFS(N47:AS47,$N$11:$AS$11,"Asking Rate",$N$10:$AS$10,$B$204),"-") -> - | I47: =IFERROR((J47/$C47),"-") -> - | J47: =IFERROR(AVERAGEIF($N$9:$AS$9,"<="&$B$3,N47:AS47),"-") -> - | K47: =IFERROR((L47/$C47),"-") -> - | L47: =IFERROR(AVERAGEIFS(N47:AS47,$N$11:$AS$11,"Discount",$N$10:$AS$10,$B$204),"-") -> -
C48: 1.8 | D48: 1 | E48: Ground | F48: No | G48: =IFERROR((H48/$C48),"-") -> - | H48: =IFERROR(AVERAGEIFS(N48:AS48,$N$11:$AS$11,"Asking Rate",$N$10:$AS$10,$B$204),"-") -> - | I48: =IFERROR((J48/$C48),"-") -> - | J48: =IFERROR(AVERAGEIF($N$9:$AS$9,"<="&$B$3,N48:AS48),"-") -> - | K48: =IFERROR((L48/$C48),"-") -> - | L48: =IFERROR(AVERAGEIFS(N48:AS48,$N$11:$AS$11,"Discount",$N$10:$AS$10,$B$204),"-") -> -
C49: 1.95 | D49: 1 | E49: Ground | F49: No | G49: =IFERROR((H49/$C49),"-") -> - | H49: =IFERROR(AVERAGEIFS(N49:AS49,$N$11:$AS$11,"Asking Rate",$N$10:$AS$10,$B$204),"-") -> - | I49: =IFERROR((J49/$C49),"-") -> - | J49: =IFERROR(AVERAGEIF($N$9:$AS$9,"<="&$B$3,N49:AS49),"-") -> - | K49: =IFERROR((L49/$C49),"-") -> - | L49: =IFERROR(AVERAGEIFS(N49:AS49,$N$11:$AS$11,"Discount",$N$10:$AS$10,$B$204),"-") -> -
B50: 1.5x1.4 | C50: 2.1 | D50: 1 | E50: Ground | F50: No | G50: =IFERROR((H50/$C50),"-") -> - | H50: =IFERROR(AVERAGEIFS(N50:AS50,$N$11:$AS$11,"Asking Rate",$N$10:$AS$10,$B$204),"-") -> - | I50: =IFERROR((J50/$C50),"-") -> - | J50: =IFERROR(AVERAGEIF($N$9:$AS$9,"<="&$B$3,N50:AS50),"-") -> - | K50: =IFERROR((L50/$C50),"-") -> - | L50: =IFERROR(AVERAGEIFS(N50:AS50,$N$11:$AS$11,"Discount",$N$10:$AS$10,$B$204),"-") -> -
B51: 1.5x1.5 | C51: 2.25 | D51: 1 | E51: Ground | F51: No | G51: =IFERROR((H51/$C51),"-") -> - | H51: =IFERROR(AVERAGEIFS(N51:AS51,$N$11:$AS$11,"Asking Rate",$N$10:$AS$10,$B$204),"-") -> - | I51: =IFERROR((J51/$C51),"-") -> - | J51: =IFERROR(AVERAGEIF($N$9:$AS$9,"<="&$B$3,N51:AS51),"-") -> - | K51: =IFERROR((L51/$C51),"-") -> - | L51: =IFERROR(AVERAGEIFS(N51:AS51,$N$11:$AS$11,"Discount",$N$10:$AS$10,$B$204),"-") -> -
C52: 2.41 | D52: 1 | E52: Ground | F52: No | G52: =IFERROR((H52/$C52),"-") -> - | H52: =IFERROR(AVERAGEIFS(N52:AS52,$N$11:$AS$11,"Asking Rate",$N$10:$AS$10,$B$204),"-") -> - | I52: =IFERROR((J52/$C52),"-") -> - | J52: =IFERROR(AVERAGEIF($N$9:$AS$9,"<="&$B$3,N52:AS52),"-") -> - | K52: =IFERROR((L52/$C52),"-") -> - | L52: =IFERROR(AVERAGEIFS(N52:AS52,$N$11:$AS$11,"Discount",$N$10:$AS$10,$B$204),"-") -> -
B53: 1.8x1.5 | C53: 2.7 | D53: 1 | E53: Ground | F53: No | G53: =IFERROR((H53/$C53),"-") -> - | H53: =IFERROR(AVERAGEIFS(N53:AS53,$N$11:$AS$11,"Asking Rate",$N$10:$AS$10,$B$204),"-") -> - | I53: =IFERROR((J53/$C53),"-") -> - | J53: =IFERROR(AVERAGEIF($N$9:$AS$9,"<="&$B$3,N53:AS53),"-") -> - | K53: =IFERROR((L53/$C53),"-") -> - | L53: =IFERROR(AVERAGEIFS(N53:AS53,$N$11:$AS$11,"Discount",$N$10:$AS$10,$B$204),"-") -> -
B54: 1.5x2 | C54: 3 | D54: 1 | E54: Ground | F54: No | G54: =IFERROR((H54/$C54),"-") -> - | H54: =IFERROR(AVERAGEIFS(N54:AS54,$N$11:$AS$11,"Asking Rate",$N$10:$AS$10,$B$204),"-") -> - | I54: =IFERROR((J54/$C54),"-") -> - | J54: =IFERROR(AVERAGEIF($N$9:$AS$9,"<="&$B$3,N54:AS54),"-") -> - | K54: =IFERROR((L54/$C54),"-") -> - | L54: =IFERROR(AVERAGEIFS(N54:AS54,$N$11:$AS$11,"Discount",$N$10:$AS$10,$B$204),"-") -> -
B55: 2.1x1.5 | C55: 3.15 | D55: 1 | E55: Ground | F55: No | G55: =IFERROR((H55/$C55),"-") -> - | H55: =IFERROR(AVERAGEIFS(N55:AS55,$N$11:$AS$11,"Asking Rate",$N$10:$AS$10,$B$204),"-") -> - | I55: =IFERROR((J55/$C55),"-") -> - | J55: =IFERROR(AVERAGEIF($N$9:$AS$9,"<="&$B$3,N55:AS55),"-") -> - | K55: =IFERROR((L55/$C55),"-") -> - | L55: =IFERROR(AVERAGEIFS(N55:AS55,$N$11:$AS$11,"Discount",$N$10:$AS$10,$B$204),"-") -> -
C56: 3.6 | D56: 1 | E56: Ground | F56: No | G56: =IFERROR((H56/$C56),"-") -> - | H56: =IFERROR(AVERAGEIFS(N56:AS56,$N$11:$AS$11,"Asking Rate",$N$10:$AS$10,$B$204),"-") -> - | I56: =IFERROR((J56/$C56),"-") -> - | J56: =IFERROR(AVERAGEIF($N$9:$AS$9,"<="&$B$3,N56:AS56),"-") -> - | K56: =IFERROR((L56/$C56),"-") -> - | L56: =IFERROR(AVERAGEIFS(N56:AS56,$N$11:$AS$11,"Discount",$N$10:$AS$10,$B$204),"-") -> -
B57: 1.5x2.5 | C57: 3.75 | D57: 1 | E57: Ground | F57: No | G57: =IFERROR((H57/$C57),"-") -> - | H57: =IFERROR(AVERAGEIFS(N57:AS57,$N$11:$AS$11,"Asking Rate",$N$10:$AS$10,$B$204),"-") -> - | I57: =IFERROR((J57/$C57),"-") -> - | J57: =IFERROR(AVERAGEIF($N$9:$AS$9,"<="&$B$3,N57:AS57),"-") -> - | K57: =IFERROR((L57/$C57),"-") -> - | L57: =IFERROR(AVERAGEIFS(N57:AS57,$N$11:$AS$11,"Discount",$N$10:$AS$10,$B$204),"-") -> -
B58: 2x2 | C58: 4 | D58: 1 | E58: Ground | F58: No | G58: =IFERROR((H58/$C58),"-") -> - | H58: =IFERROR(AVERAGEIFS(N58:AS58,$N$11:$AS$11,"Asking Rate",$N$10:$AS$10,$B$204),"-") -> - | I58: =IFERROR((J58/$C58),"-") -> - | J58: =IFERROR(AVERAGEIF($N$9:$AS$9,"<="&$B$3,N58:AS58),"-") -> - | K58: =IFERROR((L58/$C58),"-") -> - | L58: =IFERROR(AVERAGEIFS(N58:AS58,$N$11:$AS$11,"Discount",$N$10:$AS$10,$B$204),"-") -> -
C59: 4.2 | D59: 1 | E59: Ground | F59: No | G59: =IFERROR((H59/$C59),"-") -> - | H59: =IFERROR(AVERAGEIFS(N59:AS59,$N$11:$AS$11,"Asking Rate",$N$10:$AS$10,$B$204),"-") -> - | I59: =IFERROR((J59/$C59),"-") -> - | J59: =IFERROR(AVERAGEIF($N$9:$AS$9,"<="&$B$3,N59:AS59),"-") -> - | K59: =IFERROR((L59/$C59),"-") -> - | L59: =IFERROR(AVERAGEIFS(N59:AS59,$N$11:$AS$11,"Discount",$N$10:$AS$10,$B$204),"-") -> -
B60: 2.1x2.1 | C60: 4.41 | D60: 1 | E60: Ground | F60: No | G60: =IFERROR((H60/$C60),"-") -> - | H60: =IFERROR(AVERAGEIFS(N60:AS60,$N$11:$AS$11,"Asking Rate",$N$10:$AS$10,$B$204),"-") -> - | I60: =IFERROR((J60/$C60),"-") -> - | J60: =IFERROR(AVERAGEIF($N$9:$AS$9,"<="&$B$3,N60:AS60),"-") -> - | K60: =IFERROR((L60/$C60),"-") -> - | L60: =IFERROR(AVERAGEIFS(N60:AS60,$N$11:$AS$11,"Discount",$N$10:$AS$10,$B$204),"-") -> -
B61: 1.5x3 | C61: 4.5 | D61: 1 | E61: Ground | F61: No | G61: =IFERROR((H61/$C61),"-") -> - | H61: =IFERROR(AVERAGEIFS(N61:AS61,$N$11:$AS$11,"Asking Rate",$N$10:$AS$10,$B$204),"-") -> - | I61: =IFERROR((J61/$C61),"-") -> - | J61: =IFERROR(AVERAGEIF($N$9:$AS$9,"<="&$B$3,N61:AS61),"-") -> - | K61: =IFERROR((L61/$C61),"-") -> - | L61: =IFERROR(AVERAGEIFS(N61:AS61,$N$11:$AS$11,"Discount",$N$10:$AS$10,$B$204),"-") -> -
C62: 5 | D62: 1 | E62: Ground | F62: No | G62: =IFERROR((H62/$C62),"-") -> - | H62: =IFERROR(AVERAGEIFS(N62:AS62,$N$11:$AS$11,"Asking Rate",$N$10:$AS$10,$B$204),"-") -> - | I62: =IFERROR((J62/$C62),"-") -> - | J62: =IFERROR(AVERAGEIF($N$9:$AS$9,"<="&$B$3,N62:AS62),"-") -> - | K62: =IFERROR((L62/$C62),"-") -> - | L62: =IFERROR(AVERAGEIFS(N62:AS62,$N$11:$AS$11,"Discount",$N$10:$AS$10,$B$204),"-") -> -
B63: 1.5x3.5 | C63: 5.25 | D63: 1 | E63: Ground | F63: No | G63: =IFERROR((H63/$C63),"-") -> - | H63: =IFERROR(AVERAGEIFS(N63:AS63,$N$11:$AS$11,"Asking Rate",$N$10:$AS$10,$B$204),"-") -> - | I63: =IFERROR((J63/$C63),"-") -> - | J63: =IFERROR(AVERAGEIF($N$9:$AS$9,"<="&$B$3,N63:AS63),"-") -> - | K63: =IFERROR((L63/$C63),"-") -> - | L63: =IFERROR(AVERAGEIFS(N63:AS63,$N$11:$AS$11,"Discount",$N$10:$AS$10,$B$204),"-") -> -
B64: 1.5x4 | C64: 6 | D64: 1 | E64: Ground | F64: No | G64: =IFERROR((H64/$C64),"-") -> - | H64: =IFERROR(AVERAGEIFS(N64:AS64,$N$11:$AS$11,"Asking Rate",$N$10:$AS$10,$B$204),"-") -> - | I64: =IFERROR((J64/$C64),"-") -> - | J64: =IFERROR(AVERAGEIF($N$9:$AS$9,"<="&$B$3,N64:AS64),"-") -> - | K64: =IFERROR((L64/$C64),"-") -> - | L64: =IFERROR(AVERAGEIFS(N64:AS64,$N$11:$AS$11,"Discount",$N$10:$AS$10,$B$204),"-") -> -
B65: 4.5x1.4 | C65: 6.3 | D65: 1 | E65: Ground | F65: No | G65: =IFERROR((H65/$C65),"-") -> - | H65: =IFERROR(AVERAGEIFS(N65:AS65,$N$11:$AS$11,"Asking Rate",$N$10:$AS$10,$B$204),"-") -> - | I65: =IFERROR((J65/$C65),"-") -> - | J65: =IFERROR(AVERAGEIF($N$9:$AS$9,"<="&$B$3,N65:AS65),"-") -> - | K65: =IFERROR((L65/$C65),"-") -> - | L65: =IFERROR(AVERAGEIFS(N65:AS65,$N$11:$AS$11,"Discount",$N$10:$AS$10,$B$204),"-") -> -
B66: 1.5x4.5 | C66: 6.75 | D66: 1 | E66: Ground | F66: No | G66: =IFERROR((H66/$C66),"-") -> - | H66: =IFERROR(AVERAGEIFS(N66:AS66,$N$11:$AS$11,"Asking Rate",$N$10:$AS$10,$B$204),"-") -> - | I66: =IFERROR((J66/$C66),"-") -> - | J66: =IFERROR(AVERAGEIF($N$9:$AS$9,"<="&$B$3,N66:AS66),"-") -> - | K66: =IFERROR((L66/$C66),"-") -> - | L66: =IFERROR(AVERAGEIFS(N66:AS66,$N$11:$AS$11,"Discount",$N$10:$AS$10,$B$204),"-") -> -
C67: 6.8 | D67: 1 | E67: Ground | F67: No | G67: =IFERROR((H67/$C67),"-") -> - | H67: =IFERROR(AVERAGEIFS(N67:AS67,$N$11:$AS$11,"Asking Rate",$N$10:$AS$10,$B$204),"-") -> - | I67: =IFERROR((J67/$C67),"-") -> - | J67: =IFERROR(AVERAGEIF($N$9:$AS$9,"<="&$B$3,N67:AS67),"-") -> - | K67: =IFERROR((L67/$C67),"-") -> - | L67: =IFERROR(AVERAGEIFS(N67:AS67,$N$11:$AS$11,"Discount",$N$10:$AS$10,$B$204),"-") -> -
B68: 2.3x3 | C68: 6.9 | D68: 1 | E68: Ground | F68: No | G68: =IFERROR((H68/$C68),"-") -> - | H68: =IFERROR(AVERAGEIFS(N68:AS68,$N$11:$AS$11,"Asking Rate",$N$10:$AS$10,$B$204),"-") -> - | I68: =IFERROR((J68/$C68),"-") -> - | J68: =IFERROR(AVERAGEIF($N$9:$AS$9,"<="&$B$3,N68:AS68),"-") -> - | K68: =IFERROR((L68/$C68),"-") -> - | L68: =IFERROR(AVERAGEIFS(N68:AS68,$N$11:$AS$11,"Discount",$N$10:$AS$10,$B$204),"-") -> -
B69: 2.5x3 | C69: 7.5 | D69: 1 | E69: Ground | F69: No | G69: =IFERROR((H69/$C69),"-") -> - | H69: =IFERROR(AVERAGEIFS(N69:AS69,$N$11:$AS$11,"Asking Rate",$N$10:$AS$10,$B$204),"-") -> - | I69: =IFERROR((J69/$C69),"-") -> - | J69: =IFERROR(AVERAGEIF($N$9:$AS$9,"<="&$B$3,N69:AS69),"-") -> - | K69: =IFERROR((L69/$C69),"-") -> - | L69: =IFERROR(AVERAGEIFS(N69:AS69,$N$11:$AS$11,"Discount",$N$10:$AS$10,$B$204),"-") -> -
B70: 2x4 | C70: 8 | D70: 1 | E70: Ground | F70: No | G70: =IFERROR((H70/$C70),"-") -> - | H70: =IFERROR(AVERAGEIFS(N70:AS70,$N$11:$AS$11,"Asking Rate",$N$10:$AS$10,$B$204),"-") -> - | I70: =IFERROR((J70/$C70),"-") -> - | J70: =IFERROR(AVERAGEIF($N$9:$AS$9,"<="&$B$3,N70:AS70),"-") -> - | K70: =IFERROR((L70/$C70),"-") -> - | L70: =IFERROR(AVERAGEIFS(N70:AS70,$N$11:$AS$11,"Discount",$N$10:$AS$10,$B$204),"-") -> -
C71: 8.12 | D71: 1 | E71: Ground | F71: No | G71: =IFERROR((H71/$C71),"-") -> - | H71: =IFERROR(AVERAGEIFS(N71:AS71,$N$11:$AS$11,"Asking Rate",$N$10:$AS$10,$B$204),"-") -> - | I71: =IFERROR((J71/$C71),"-") -> - | J71: =IFERROR(AVERAGEIF($N$9:$AS$9,"<="&$B$3,N71:AS71),"-") -> - | K71: =IFERROR((L71/$C71),"-") -> - | L71: =IFERROR(AVERAGEIFS(N71:AS71,$N$11:$AS$11,"Discount",$N$10:$AS$10,$B$204),"-") -> -
B72: 3.6x2.3 | C72: 8.28 | D72: 1 | E72: Ground | F72: No | G72: =IFERROR((H72/$C72),"-") -> - | H72: =IFERROR(AVERAGEIFS(N72:AS72,$N$11:$AS$11,"Asking Rate",$N$10:$AS$10,$B$204),"-") -> - | I72: =IFERROR((J72/$C72),"-") -> - | J72: =IFERROR(AVERAGEIF($N$9:$AS$9,"<="&$B$3,N72:AS72),"-") -> - | K72: =IFERROR((L72/$C72),"-") -> - | L72: =IFERROR(AVERAGEIFS(N72:AS72,$N$11:$AS$11,"Discount",$N$10:$AS$10,$B$204),"-") -> -
B73: 6x1.4 | C73: 8.4 | D73: 1 | E73: Ground | F73: No | G73: =IFERROR((H73/$C73),"-") -> - | H73: =IFERROR(AVERAGEIFS(N73:AS73,$N$11:$AS$11,"Asking Rate",$N$10:$AS$10,$B$204),"-") -> - | I73: =IFERROR((J73/$C73),"-") -> - | J73: =IFERROR(AVERAGEIF($N$9:$AS$9,"<="&$B$3,N73:AS73),"-") -> - | K73: =IFERROR((L73/$C73),"-") -> - | L73: =IFERROR(AVERAGEIFS(N73:AS73,$N$11:$AS$11,"Discount",$N$10:$AS$10,$B$204),"-") -> -
C74: 8.5 | D74: 1 | E74: Ground | F74: No | G74: =IFERROR((H74/$C74),"-") -> - | H74: =IFERROR(AVERAGEIFS(N74:AS74,$N$11:$AS$11,"Asking Rate",$N$10:$AS$10,$B$204),"-") -> - | I74: =IFERROR((J74/$C74),"-") -> - | J74: =IFERROR(AVERAGEIF($N$9:$AS$9,"<="&$B$3,N74:AS74),"-") -> - | K74: =IFERROR((L74/$C74),"-") -> - | L74: =IFERROR(AVERAGEIFS(N74:AS74,$N$11:$AS$11,"Discount",$N$10:$AS$10,$B$204),"-") -> -
B75: 2.5x3.5 | C75: 8.75 | D75: 1 | E75: Ground | F75: No | G75: =IFERROR((H75/$C75),"-") -> - | H75: =IFERROR(AVERAGEIFS(N75:AS75,$N$11:$AS$11,"Asking Rate",$N$10:$AS$10,$B$204),"-") -> - | I75: =IFERROR((J75/$C75),"-") -> - | J75: =IFERROR(AVERAGEIF($N$9:$AS$9,"<="&$B$3,N75:AS75),"-") -> - | K75: =IFERROR((L75/$C75),"-") -> - | L75: =IFERROR(AVERAGEIFS(N75:AS75,$N$11:$AS$11,"Discount",$N$10:$AS$10,$B$204),"-") -> -
B76: 3x3 | C76: 9 | D76: 1 | E76: Ground | F76: No | G76: =IFERROR((H76/$C76),"-") -> - | H76: =IFERROR(AVERAGEIFS(N76:AS76,$N$11:$AS$11,"Asking Rate",$N$10:$AS$10,$B$204),"-") -> - | I76: =IFERROR((J76/$C76),"-") -> - | J76: =IFERROR(AVERAGEIF($N$9:$AS$9,"<="&$B$3,N76:AS76),"-") -> - | K76: =IFERROR((L76/$C76),"-") -> - | L76: =IFERROR(AVERAGEIFS(N76:AS76,$N$11:$AS$11,"Discount",$N$10:$AS$10,$B$204),"-") -> -
B77: 4.6x2.1 | C77: 9.66 | D77: 1 | E77: Ground | F77: No | G77: =IFERROR((H77/$C77),"-") -> - | H77: =IFERROR(AVERAGEIFS(N77:AS77,$N$11:$AS$11,"Asking Rate",$N$10:$AS$10,$B$204),"-") -> - | I77: =IFERROR((J77/$C77),"-") -> - | J77: =IFERROR(AVERAGEIF($N$9:$AS$9,"<="&$B$3,N77:AS77),"-") -> - | K77: =IFERROR((L77/$C77),"-") -> - | L77: =IFERROR(AVERAGEIFS(N77:AS77,$N$11:$AS$11,"Discount",$N$10:$AS$10,$B$204),"-") -> -
B78: 2.8x3.5 | C78: 9.8 | D78: 1 | E78: Ground | F78: No | G78: =IFERROR((H78/$C78),"-") -> - | H78: =IFERROR(AVERAGEIFS(N78:AS78,$N$11:$AS$11,"Asking Rate",$N$10:$AS$10,$B$204),"-") -> - | I78: =IFERROR((J78/$C78),"-") -> - | J78: =IFERROR(AVERAGEIF($N$9:$AS$9,"<="&$B$3,N78:AS78),"-") -> - | K78: =IFERROR((L78/$C78),"-") -> - | L78: =IFERROR(AVERAGEIFS(N78:AS78,$N$11:$AS$11,"Discount",$N$10:$AS$10,$B$204),"-") -> -
B79: 4x2.5 | C79: 10 | D79: 1 | E79: Ground | F79: No | G79: =IFERROR((H79/$C79),"-") -> - | H79: =IFERROR(AVERAGEIFS(N79:AS79,$N$11:$AS$11,"Asking Rate",$N$10:$AS$10,$B$204),"-") -> - | I79: =IFERROR((J79/$C79),"-") -> - | J79: =IFERROR(AVERAGEIF($N$9:$AS$9,"<="&$B$3,N79:AS79),"-") -> - | K79: =IFERROR((L79/$C79),"-") -> - | L79: =IFERROR(AVERAGEIFS(N79:AS79,$N$11:$AS$11,"Discount",$N$10:$AS$10,$B$204),"-") -> -
C80: 10.4 | D80: 1 | E80: Ground | F80: No | G80: =IFERROR((H80/$C80),"-") -> - | H80: =IFERROR(AVERAGEIFS(N80:AS80,$N$11:$AS$11,"Asking Rate",$N$10:$AS$10,$B$204),"-") -> - | I80: =IFERROR((J80/$C80),"-") -> - | J80: =IFERROR(AVERAGEIF($N$9:$AS$9,"<="&$B$3,N80:AS80),"-") -> - | K80: =IFERROR((L80/$C80),"-") -> - | L80: =IFERROR(AVERAGEIFS(N80:AS80,$N$11:$AS$11,"Discount",$N$10:$AS$10,$B$204),"-") -> -
B81: 3x3.5 | C81: 10.5 | D81: 1 | E81: Ground | F81: No | G81: =IFERROR((H81/$C81),"-") -> - | H81: =IFERROR(AVERAGEIFS(N81:AS81,$N$11:$AS$11,"Asking Rate",$N$10:$AS$10,$B$204),"-") -> - | I81: =IFERROR((J81/$C81),"-") -> - | J81: =IFERROR(AVERAGEIF($N$9:$AS$9,"<="&$B$3,N81:AS81),"-") -> - | K81: =IFERROR((L81/$C81),"-") -> - | L81: =IFERROR(AVERAGEIFS(N81:AS81,$N$11:$AS$11,"Discount",$N$10:$AS$10,$B$204),"-") -> -
B82: 2x5.5 | C82: 11 | D82: 1 | E82: Ground | F82: No | G82: =IFERROR((H82/$C82),"-") -> - | H82: =IFERROR(AVERAGEIFS(N82:AS82,$N$11:$AS$11,"Asking Rate",$N$10:$AS$10,$B$204),"-") -> - | I82: =IFERROR((J82/$C82),"-") -> - | J82: =IFERROR(AVERAGEIF($N$9:$AS$9,"<="&$B$3,N82:AS82),"-") -> - | K82: =IFERROR((L82/$C82),"-") -> - | L82: =IFERROR(AVERAGEIFS(N82:AS82,$N$11:$AS$11,"Discount",$N$10:$AS$10,$B$204),"-") -> -
B83: 4.6x2.4 | C83: 11.04 | D83: 1 | E83: Ground | F83: No | G83: =IFERROR((H83/$C83),"-") -> - | H83: =IFERROR(AVERAGEIFS(N83:AS83,$N$11:$AS$11,"Asking Rate",$N$10:$AS$10,$B$204),"-") -> - | I83: =IFERROR((J83/$C83),"-") -> - | J83: =IFERROR(AVERAGEIF($N$9:$AS$9,"<="&$B$3,N83:AS83),"-") -> - | K83: =IFERROR((L83/$C83),"-") -> - | L83: =IFERROR(AVERAGEIFS(N83:AS83,$N$11:$AS$11,"Discount",$N$10:$AS$10,$B$204),"-") -> -
C84: 11.2 | D84: 1 | E84: Ground | F84: No | G84: =IFERROR((H84/$C84),"-") -> - | H84: =IFERROR(AVERAGEIFS(N84:AS84,$N$11:$AS$11,"Asking Rate",$N$10:$AS$10,$B$204),"-") -> - | I84: =IFERROR((J84/$C84),"-") -> - | J84: =IFERROR(AVERAGEIF($N$9:$AS$9,"<="&$B$3,N84:AS84),"-") -> - | K84: =IFERROR((L84/$C84),"-") -> - | L84: =IFERROR(AVERAGEIFS(N84:AS84,$N$11:$AS$11,"Discount",$N$10:$AS$10,$B$204),"-") -> -
B85: 3x3.80 | C85: 11.4 | D85: 1 | E85: Ground | F85: No | G85: =IFERROR((H85/$C85),"-") -> - | H85: =IFERROR(AVERAGEIFS(N85:AS85,$N$11:$AS$11,"Asking Rate",$N$10:$AS$10,$B$204),"-") -> - | I85: =IFERROR((J85/$C85),"-") -> - | J85: =IFERROR(AVERAGEIF($N$9:$AS$9,"<="&$B$3,N85:AS85),"-") -> - | K85: =IFERROR((L85/$C85),"-") -> - | L85: =IFERROR(AVERAGEIFS(N85:AS85,$N$11:$AS$11,"Discount",$N$10:$AS$10,$B$204),"-") -> -
C86: 11.44 | D86: 1 | E86: Ground | F86: No | G86: =IFERROR((H86/$C86),"-") -> - | H86: =IFERROR(AVERAGEIFS(N86:AS86,$N$11:$AS$11,"Asking Rate",$N$10:$AS$10,$B$204),"-") -> - | I86: =IFERROR((J86/$C86),"-") -> - | J86: =IFERROR(AVERAGEIF($N$9:$AS$9,"<="&$B$3,N86:AS86),"-") -> - | K86: =IFERROR((L86/$C86),"-") -> - | L86: =IFERROR(AVERAGEIFS(N86:AS86,$N$11:$AS$11,"Discount",$N$10:$AS$10,$B$204),"-") -> -
C87: 11.52 | D87: 1 | E87: Ground | F87: No | G87: =IFERROR((H87/$C87),"-") -> - | H87: =IFERROR(AVERAGEIFS(N87:AS87,$N$11:$AS$11,"Asking Rate",$N$10:$AS$10,$B$204),"-") -> - | I87: =IFERROR((J87/$C87),"-") -> - | J87: =IFERROR(AVERAGEIF($N$9:$AS$9,"<="&$B$3,N87:AS87),"-") -> - | K87: =IFERROR((L87/$C87),"-") -> - | L87: =IFERROR(AVERAGEIFS(N87:AS87,$N$11:$AS$11,"Discount",$N$10:$AS$10,$B$204),"-") -> -
C88: 11.75 | D88: 1 | E88: Ground | F88: No | G88: =IFERROR((H88/$C88),"-") -> - | H88: =IFERROR(AVERAGEIFS(N88:AS88,$N$11:$AS$11,"Asking Rate",$N$10:$AS$10,$B$204),"-") -> - | I88: =IFERROR((J88/$C88),"-") -> - | J88: =IFERROR(AVERAGEIF($N$9:$AS$9,"<="&$B$3,N88:AS88),"-") -> - | K88: =IFERROR((L88/$C88),"-") -> - | L88: =IFERROR(AVERAGEIFS(N88:AS88,$N$11:$AS$11,"Discount",$N$10:$AS$10,$B$204),"-") -> -
B89: 3x4 | C89: 12 | D89: 1 | E89: Ground | F89: No | G89: =IFERROR((H89/$C89),"-") -> - | H89: =IFERROR(AVERAGEIFS(N89:AS89,$N$11:$AS$11,"Asking Rate",$N$10:$AS$10,$B$204),"-") -> - | I89: =IFERROR((J89/$C89),"-") -> - | J89: =IFERROR(AVERAGEIF($N$9:$AS$9,"<="&$B$3,N89:AS89),"-") -> - | K89: =IFERROR((L89/$C89),"-") -> - | L89: =IFERROR(AVERAGEIFS(N89:AS89,$N$11:$AS$11,"Discount",$N$10:$AS$10,$B$204),"-") -> -
B90: 3.5x3.5 | C90: 12.25 | D90: 1 | E90: Ground | F90: No | G90: =IFERROR((H90/$C90),"-") -> - | H90: =IFERROR(AVERAGEIFS(N90:AS90,$N$11:$AS$11,"Asking Rate",$N$10:$AS$10,$B$204),"-") -> - | I90: =IFERROR((J90/$C90),"-") -> - | J90: =IFERROR(AVERAGEIF($N$9:$AS$9,"<="&$B$3,N90:AS90),"-") -> - | K90: =IFERROR((L90/$C90),"-") -> - | L90: =IFERROR(AVERAGEIFS(N90:AS90,$N$11:$AS$11,"Discount",$N$10:$AS$10,$B$204),"-") -> -
B91: 4.5x2.8 | C91: 12.6 | D91: 1 | E91: Ground | F91: No | G91: =IFERROR((H91/$C91),"-") -> - | H91: =IFERROR(AVERAGEIFS(N91:AS91,$N$11:$AS$11,"Asking Rate",$N$10:$AS$10,$B$204),"-") -> - | I91: =IFERROR((J91/$C91),"-") -> - | J91: =IFERROR(AVERAGEIF($N$9:$AS$9,"<="&$B$3,N91:AS91),"-") -> - | K91: =IFERROR((L91/$C91),"-") -> - | L91: =IFERROR(AVERAGEIFS(N91:AS91,$N$11:$AS$11,"Discount",$N$10:$AS$10,$B$204),"-") -> -
B92: 2.65x5 | C92: 13.25 | D92: 1 | E92: Ground | F92: No | G92: =IFERROR((H92/$C92),"-") -> - | H92: =IFERROR(AVERAGEIFS(N92:AS92,$N$11:$AS$11,"Asking Rate",$N$10:$AS$10,$B$209),"-") -> - | I92: =IFERROR((J92/$C92),"-") -> - | J92: =IFERROR(AVERAGEIF($N$9:$AS$9,"<="&$B$3,N92:AS92),"-") -> - | K92: =IFERROR((L92/$C92),"-") -> - | L92: =IFERROR(AVERAGEIFS(N92:AS92,$N$11:$AS$11,"Discount",$N$10:$AS$10,$B$209),"-") -> -
B93: 3x4.5 | C93: 13.5 | D93: 1 | E93: Ground | F93: No | G93: =IFERROR((H93/$C93),"-") -> - | H93: =IFERROR(AVERAGEIFS(N93:AS93,$N$11:$AS$11,"Asking Rate",$N$10:$AS$10,$B$204),"-") -> - | I93: =IFERROR((J93/$C93),"-") -> - | J93: =IFERROR(AVERAGEIF($N$9:$AS$9,"<="&$B$3,N93:AS93),"-") -> - | K93: =IFERROR((L93/$C93),"-") -> - | L93: =IFERROR(AVERAGEIFS(N93:AS93,$N$11:$AS$11,"Discount",$N$10:$AS$10,$B$204),"-") -> -
B94: 2.5x5.5 | C94: 13.75 | D94: 1 | E94: Ground | F94: No | G94: =IFERROR((H94/$C94),"-") -> - | H94: =IFERROR(AVERAGEIFS(N94:AS94,$N$11:$AS$11,"Asking Rate",$N$10:$AS$10,$B$204),"-") -> - | I94: =IFERROR((J94/$C94),"-") -> - | J94: =IFERROR(AVERAGEIF($N$9:$AS$9,"<="&$B$3,N94:AS94),"-") -> - | K94: =IFERROR((L94/$C94),"-") -> - | L94: =IFERROR(AVERAGEIFS(N94:AS94,$N$11:$AS$11,"Discount",$N$10:$AS$10,$B$204),"-") -> -
B95: 6x2.5 | C95: 15 | D95: 1 | E95: Ground | F95: No | G95: =IFERROR((H95/$C95),"-") -> - | H95: =IFERROR(AVERAGEIFS(N95:AS95,$N$11:$AS$11,"Asking Rate",$N$10:$AS$10,$B$204),"-") -> - | I95: =IFERROR((J95/$C95),"-") -> - | J95: =IFERROR(AVERAGEIF($N$9:$AS$9,"<="&$B$3,N95:AS95),"-") -> - | K95: =IFERROR((L95/$C95),"-") -> - | L95: =IFERROR(AVERAGEIFS(N95:AS95,$N$11:$AS$11,"Discount",$N$10:$AS$10,$B$204),"-") -> -
B96: 3.5x4.5 | C96: 15.75 | D96: 1 | E96: Ground | F96: No | G96: =IFERROR((H96/$C96),"-") -> - | H96: =IFERROR(AVERAGEIFS(N96:AS96,$N$11:$AS$11,"Asking Rate",$N$10:$AS$10,$B$204),"-") -> - | I96: =IFERROR((J96/$C96),"-") -> - | J96: =IFERROR(AVERAGEIF($N$9:$AS$9,"<="&$B$3,N96:AS96),"-") -> - | K96: =IFERROR((L96/$C96),"-") -> - | L96: =IFERROR(AVERAGEIFS(N96:AS96,$N$11:$AS$11,"Discount",$N$10:$AS$10,$B$204),"-") -> -
B97: 4x4 | C97: 16 | D97: 1 | E97: Ground | F97: No | G97: =IFERROR((H97/$C97),"-") -> - | H97: =IFERROR(AVERAGEIFS(N97:AS97,$N$11:$AS$11,"Asking Rate",$N$10:$AS$10,$B$204),"-") -> - | I97: =IFERROR((J97/$C97),"-") -> - | J97: =IFERROR(AVERAGEIF($N$9:$AS$9,"<="&$B$3,N97:AS97),"-") -> - | K97: =IFERROR((L97/$C97),"-") -> - | L97: =IFERROR(AVERAGEIFS(N97:AS97,$N$11:$AS$11,"Discount",$N$10:$AS$10,$B$204),"-") -> -
C98: 16.5 | D98: 1 | E98: Ground | F98: No | G98: =IFERROR((H98/$C98),"-") -> - | H98: =IFERROR(AVERAGEIFS(N98:AS98,$N$11:$AS$11,"Asking Rate",$N$10:$AS$10,$B$204),"-") -> - | I98: =IFERROR((J98/$C98),"-") -> - | J98: =IFERROR(AVERAGEIF($N$9:$AS$9,"<="&$B$3,N98:AS98),"-") -> - | K98: =IFERROR((L98/$C98),"-") -> - | L98: =IFERROR(AVERAGEIFS(N98:AS98,$N$11:$AS$11,"Discount",$N$10:$AS$10,$B$204),"-") -> -
B99: 3.35x5 | C99: 16.75 | D99: 1 | E99: Ground | F99: No | G99: =IFERROR((H99/$C99),"-") -> - | H99: =IFERROR(AVERAGEIFS(N99:AS99,$N$11:$AS$11,"Asking Rate",$N$10:$AS$10,$B$209),"-") -> - | I99: =IFERROR((J99/$C99),"-") -> - | J99: =IFERROR(AVERAGEIF($N$9:$AS$9,"<="&$B$3,N99:AS99),"-") -> - | K99: =IFERROR((L99/$C99),"-") -> - | L99: =IFERROR(AVERAGEIFS(N99:AS99,$N$11:$AS$11,"Discount",$N$10:$AS$10,$B$209),"-") -> -
C100: 16.8 | D100: 1 | E100: Ground | F100: No | G100: =IFERROR((H100/$C100),"-") -> - | H100: =IFERROR(AVERAGEIFS(N100:AS100,$N$11:$AS$11,"Asking Rate",$N$10:$AS$10,$B$204),"-") -> - | I100: =IFERROR((J100/$C100),"-") -> - | J100: =IFERROR(AVERAGEIF($N$9:$AS$9,"<="&$B$3,N100:AS100),"-") -> - | K100: =IFERROR((L100/$C100),"-") -> - | L100: =IFERROR(AVERAGEIFS(N100:AS100,$N$11:$AS$11,"Discount",$N$10:$AS$10,$B$204),"-") -> -
B101: 3x6 | C101: 18 | D101: 1 | E101: Ground | F101: No | G101: =IFERROR((H101/$C101),"-") -> - | H101: =IFERROR(AVERAGEIFS(N101:AS101,$N$11:$AS$11,"Asking Rate",$N$10:$AS$10,$B$204),"-") -> - | I101: =IFERROR((J101/$C101),"-") -> - | J101: =IFERROR(AVERAGEIF($N$9:$AS$9,"<="&$B$3,N101:AS101),"-") -> - | K101: =IFERROR((L101/$C101),"-") -> - | L101: =IFERROR(AVERAGEIFS(N101:AS101,$N$11:$AS$11,"Discount",$N$10:$AS$10,$B$204),"-") -> -
...

Sheet Workstore Sales
B2: Number of units | C2: =$B$33 -> 15
B3: Rate/m2 | C3: 5300
B4: Commission | C4: 0.03
B5: Average Unit Size | C5: =AVERAGE(C11:C32) -> 0
B6: Floor Area | C6: =$E$33 -> 0
B8: Workstores Unit Mix | G8: Workstore Sales
M9: Notes
B10: Unit No. | C10: Ground Floor (m2) | D10: Mezzanine (m2) | E10: Total (m2) | G10: Unit No. | H10: Sale Month | I10: Sale Price (GF) | J10: Commission | K10: Total
B11: 1 | C11: 0 | E11: =C11+D11 -> 0 | G11: =B11 -> 1 | H11: 15 | I11: =E11*$C$3 -> 0 | J11: =I11*$C$4 -> 0 | K11: =I11-J11 -> 0
B12: 2 | C12: 0 | E12: =C12+D12 -> 0 | G12: =B12 -> 2 | H12: 15 | I12: =E12*$C$3 -> 0 | J12: =I12*$C$4 -> 0 | K12: =I12-J12 -> 0
B13: 3 | C13: 0 | E13: =C13+D13 -> 0 | G13: =B13 -> 3 | H13: 15 | I13: =E13*$C$3 -> 0 | J13: =I13*$C$4 -> 0 | K13: =I13-J13 -> 0
B14: 4 | C14: 0 | E14: =C14+D14 -> 0 | G14: =B14 -> 4 | H14: 15 | I14: =E14*$C$3 -> 0 | J14: =I14*$C$4 -> 0 | K14: =I14-J14 -> 0
B15: 5 | C15: 0 | E15: =C15+D15 -> 0 | G15: =B15 -> 5 | H15: 15 | I15: =E15*$C$3 -> 0 | J15: =I15*$C$4 -> 0 | K15: =I15-J15 -> 0
B16: 6 | C16: 0 | E16: =C16+D16 -> 0 | G16: =B16 -> 6 | H16: 15 | I16: =E16*$C$3 -> 0 | J16: =I16*$C$4 -> 0 | K16: =I16-J16 -> 0
B17: 7 | C17: 0 | E17: =C17+D17 -> 0 | G17: =B17 -> 7 | H17: 15 | I17: =E17*$C$3 -> 0 | J17: =I17*$C$4 -> 0 | K17: =I17-J17 -> 0
B18: 8 | C18: 0 | E18: =C18+D18 -> 0 | G18: =B18 -> 8 | H18: 16 | I18: =E18*$C$3 -> 0 | J18: =I18*$C$4 -> 0 | K18: =I18-J18 -> 0
B19: 9 | C19: 0 | E19: =C19+D19 -> 0 | G19: =B19 -> 9 | H19: 16 | I19: =E19*$C$3 -> 0 | J19: =I19*$C$4 -> 0 | K19: =I19-J19 -> 0
B20: 10 | C20: 0 | E20: =C20+D20 -> 0 | G20: =B20 -> 10 | H20: 17 | I20: =E20*$C$3 -> 0 | J20: =I20*$C$4 -> 0 | K20: =I20-J20 -> 0
B21: 11 | C21: 0 | E21: =C21+D21 -> 0 | G21: =B21 -> 11 | H21: 17 | I21: =E21*$C$3 -> 0 | J21: =I21*$C$4 -> 0 | K21: =I21-J21 -> 0
B22: 12 | C22: 0 | E22: =C22+D22 -> 0 | G22: =B22 -> 12 | H22: 18 | I22: =E22*$C$3 -> 0 | J22: =I22*$C$4 -> 0 | K22: =I22-J22 -> 0
... B25: 15 | C25: 0 | E25: =C25+D25 -> 0 | G25: =B25 -> 15 | H25: 19 | I25: =E25*$C$3 -> 0 | J25: =I25*$C$4 -> 0 | K25: =I25-J25 -> 0
E26: =C26+D26 -> 0 | G26: =B26 -> 0 | H26: 20 | I26: =E26*$C$3 -> 0 | J26: =I26*$C$4 -> 0 | K26: =I26-J26 -> 0
E27: =C27+D27 -> 0 | G27: =B27 -> 0 | H27: 20 | I27: =E27*$C$3 -> 0 | J27: =I27*$C$4 -> 0 | K27: =I27-J27 -> 0
E28: =C28+D28 -> 0 | G28: =B28 -> 0 | H28: 21 | I28: =E28*$C$3 -> 0 | J28: =I28*$C$4 -> 0 | K28: =I28-J28 -> 0
E29: =C29+D29 -> 0 | G29: =B29 -> 0 | I29: =E29*$C$3 -> 0 | J29: =I29*$C$4 -> 0 | K29: =I29-J29 -> 0
E30: =C30+D30 -> 0 | G30: =B30 -> 0 | I30: =E30*$C$3 -> 0 | J30: =I30*$C$4 -> 0 | K30: =I30-J30 -> 0
E31: =C31+D31 -> 0 | G31: =B31 -> 0 | I31: =E31*$C$3 -> 0 | J31: =I31*$C$4 -> 0 | K31: =I31-J31 -> 0
E32: =C32+D32 -> 0 | G32: =B32 -> 0 | I32: =E32*$C$3 -> 0 | J32: =I32*$C$4 -> 0 | K32: =I32-J32 -> 0
B33: =COUNT(B11:B32) -> 15 | C33: =SUM(C11:C32) -> 0 | D33: =SUM(D11:D32) -> 0 | E33: =SUM(E11:E32) -> 0 | G33: =B33 -> 15 | I33: =SUM(I11:I32) -> 0 | J33: =SUM(J11:J32) -> 0 | K33: =I33-J33 -> 0
B36: Month | C36: 1 | D36: =C36+1 -> 2 | E36: =D36+1 -> 3 | F36: =E36+1 -> 4 | G36: =F36+1 -> 5 | H36: =G36+1 -> 6 | I36: =H36+1 -> 7 | J36: =I36+1 -> 8 | K36: =J36+1 -> 9 | ... EG36: =EF36+1 -> 135
B37: Workstore Sales | C37: =SUMIF($H$11:$H$32,C36,$K$11:$K$32) -> 0 | D37: =SUMIF($H$11:$H$32,D36,$K$11:$K$32) -> 0 | E37: =SUMIF($H$11:$H$32,E36,$K$11:$K$32) -> 0 | F37: =SUMIF($H$11:$H$32,F36,$K$11:$K$32) -> 0 | G37: =SUMIF($H$11:$H$32,G36,$K$11:$K$32) -> 0 | H37: =SUMIF($H$11:$H$32,H36,$K$11:$K$32) -> 0 | I37: =SUMIF($H$11:$H$32,I36,$K$11:$K$32) -> 0 | J37: =SUMIF($H$11:$H$32,J36,$K$11:$K$32) -> 0 | ... EG37: =SUMIF($H$11:$H$32,EG36,$K$11:$K$32) -> 0

Sheet Sale Comps
B2: Sale Comps

Sheet LT&Rates
C2: Industrial Rate Category Cost: | F2: 0.015452
C3: Ratebale Value Ratio: | F3: 0.9 | H3: Original Land Size: | J3: 34800
C4: Year | D4: Rateable Value | F4: Rates Payble | H4: Total Rateable Value
C5: 2019 | D5: =D6*(1-0.03) -> 0 | H5: 6133333
C6: 2020 | D6: =D7*(1-0.03) -> 0 | H6: 6466666
C7: 2021 | D7: =UW!J9*(3800/6071) -> 0 | F7: =AVERAGE(D5:D7)*$F$2 -> 0
C8: 2022 | D8: =D7*1.03 -> 0 | F8: =AVERAGE(D6:D8)*$F$2 -> 0
C9: 2023 | D9: =D8*1.03 -> 0 | F9: =AVERAGE(D7:D9)*$F$2 -> 0

Sheet Dev Bdgt
B2: Development Budget
C5: Land Costs | E5: =UW!J9 -> 0
H6: Construction Cost
C7: Closing Date | E7: =UW!$I$12 -> 46112 | F7: =UW!$I$12 -> 46112 | H7: =SUM(E14:E19)/E8 -> #DIV/0! | I7: <-- Today's assumed cost
C8: Building Size (GSM) | E8: =UW!D20 -> 0 | F8: ='Workstore Sales'!E33 -> 0 | H8: =SUM(E14:E20)/E8 -> #DIV/0! | I8: <-- Future assumed cost
C9: Building Size (NRSM) | E9: ='Comps & Unit Mix'!AW328 -> 0 | F9: 0
C10: Average Unit Size | E10: =E9/E11 -> #DIV/0! | F10: ='Comps & Unit Mix'!AU439 -> 0
C11: Number of Units | E11: ='Comps & Unit Mix'!AV328 -> 0 | F11: ='Comps & Unit Mix'!AV439 -> 0
M12: =E7 -> 46112 | N12: =EOMONTH(M12,1) -> 46142 | O12: =EOMONTH(N12,1) -> 46173 | P12: =EOMONTH(O12,1) -> 46203 | Q12: =EOMONTH(P12,1) -> 46234 | R12: =EOMONTH(Q12,1) -> 46265 | S12: =EOMONTH(R12,1) -> 46295 | T12: =EOMONTH(S12,1) -> 46326 | U12: =EOMONTH(T12,1) -> 46356 | ... EC12: =EOMONTH(EB12,1) -> 49765
C13: Hard Costs | F13: Month | G13: Duration | H13: Start Date | I13: End Date | J13: Notes | M13: 0 | N13: =M13+1 -> 1 | O13: =N13+1 -> 2 | P13: =O13+1 -> 3 | Q13: =P13+1 -> 4 | R13: =Q13+1 -> 5 | S13: =R13+1 -> 6 | T13: =S13+1 -> 7 | U13: =T13+1 -> 8 | ... EC13: =EB13+1 -> 120
C14: Construction Cost (SS) | D14: 0 | E14: =D14*E8 -> 0 | F14: 7 | G14: 14 | H14: =IF($E14=0,"-",EOMONTH($E$7,F14)) -> - | I14: =IF($E14=0,"-",EOMONTH(H14,G14-1)) -> - | M14: =IF(AND(M$13>=$F14,M$13<SUM($F14:$G14)),$E14/$G14,0) -> 0 | N14: =IF(AND(N$13>=$F14,N$13<SUM($F14:$G14)),$E14/$G14,0) -> 0 | O14: =IF(AND(O$13>=$F14,O$13<SUM($F14:$G14)),$E14/$G14,0) -> 0 | P14: =IF(AND(P$13>=$F14,P$13<SUM($F14:$G14)),$E14/$G14,0) -> 0 | Q14: =IF(AND(Q$13>=$F14,Q$13<SUM($F14:$G14)),$E14/$G14,0) -> 0 | R14: =IF(AND(R$13>=$F14,R$13<SUM($F14:$G14)),$E14/$G14,0) -> 0 | S14: =IF(AND(S$13>=$F14,S$13<SUM($F14:$G14)),$E14/$G14,0) -> 0 | T14: =IF(AND(T$13>=$F14,T$13<SUM($F14:$G14)),$E14/$G14,0) -> 0 | ... EC14: =IF(AND(EC$13>=$F14,EC$13<SUM($F14:$G14)),$E14/$G14,0) -> 0
C15: Contamination Allowance | D15: 0 | E15: 0 | F15: =F14 -> 7 | G15: 2 | H15: =IF($E15=0,"-",EOMONTH($E$7,F15)) -> - | I15: =IF($E15=0,"-",EOMONTH(H15,G15-1)) -> - | M15: =IF(AND(M$13>=$F15,M$13<SUM($F15:$G15)),$E15/$G15,0) -> 0 | N15: =IF(AND(N$13>=$F15,N$13<SUM($F15:$G15)),$E15/$G15,0) -> 0 | O15: =IF(AND(O$13>=$F15,O$13<SUM($F15:$G15)),$E15/$G15,0) -> 0 | P15: =IF(AND(P$13>=$F15,P$13<SUM($F15:$G15)),$E15/$G15,0) -> 0 | Q15: =IF(AND(Q$13>=$F15,Q$13<SUM($F15:$G15)),$E15/$G15,0) -> 0 | R15: =IF(AND(R$13>=$F15,R$13<SUM($F15:$G15)),$E15/$G15,0) -> 0 | S15: =IF(AND(S$13>=$F15,S$13<SUM($F15:$G15)),$E15/$G15,0) -> 0 | T15: =IF(AND(T$13>=$F15,T$13<SUM($F15:$G15)),$E15/$G15,0) -> 0 | ... EC15: =IF(AND(EC$13>=$F15,EC$13<SUM($F15:$G15)),$E15/$G15,0) -> 0
C16: Fitout | D16: 0 | E16: =D16*E9 -> 0 | F16: 9 | G16: 4 | H16: =IF($E16=0,"-",EOMONTH($E$7,F16)) -> - | I16: =IF($E16=0,"-",EOMONTH(H16,G16-1)) -> - | M16: =IF(AND(M$13>=$F16,M$13<SUM($F16:$G16)),$E16/$G16,0) -> 0 | N16: =IF(AND(N$13>=$F16,N$13<SUM($F16:$G16)),$E16/$G16,0) -> 0 | O16: =IF(AND(O$13>=$F16,O$13<SUM($F16:$G16)),$E16/$G16,0) -> 0 | P16: =IF(AND(P$13>=$F16,P$13<SUM($F16:$G16)),$E16/$G16,0) -> 0 | Q16: =IF(AND(Q$13>=$F16,Q$13<SUM($F16:$G16)),$E16/$G16,0) -> 0 | R16: =IF(AND(R$13>=$F16,R$13<SUM($F16:$G16)),$E16/$G16,0) -> 0 | S16: =IF(AND(S$13>=$F16,S$13<SUM($F16:$G16)),$E16/$G16,0) -> 0 | T16: =IF(AND(T$13>=$F16,T$13<SUM($F16:$G16)),$E16/$G16,0) -> 0 | ... EC16: =IF(AND(EC$13>=$F16,EC$13<SUM($F16:$G16)),$E16/$G16,0) -> 0
C17: Signage | E17: 0 | F17: 11 | G17: 2 | H17: =IF($E17=0,"-",EOMONTH($E$7,F17)) -> - | I17: =IF($E17=0,"-",EOMONTH(H17,G17-1)) -> - | M17: =IF(AND(M$13>=$F17,M$13<SUM($F17:$G17)),$E17/$G17,0) -> 0 | N17: =IF(AND(N$13>=$F17,N$13<SUM($F17:$G17)),$E17/$G17,0) -> 0 | O17: =IF(AND(O$13>=$F17,O$13<SUM($F17:$G17)),$E17/$G17,0) -> 0 | P17: =IF(AND(P$13>=$F17,P$13<SUM($F17:$G17)),$E17/$G17,0) -> 0 | Q17: =IF(AND(Q$13>=$F17,Q$13<SUM($F17:$G17)),$E17/$G17,0) -> 0 | R17: =IF(AND(R$13>=$F17,R$13<SUM($F17:$G17)),$E17/$G17,0) -> 0 | S17: =IF(AND(S$13>=$F17,S$13<SUM($F17:$G17)),$E17/$G17,0) -> 0 | T17: =IF(AND(T$13>=$F17,T$13<SUM($F17:$G17)),$E17/$G17,0) -> 0 | ... EC17: =IF(AND(EC$13>=$F17,EC$13<SUM($F17:$G17)),$E17/$G17,0) -> 0
C18: Lifts | E18: 0 | F18: 9 | G18: 4 | H18: =IF($E18=0,"-",EOMONTH($E$7,F18)) -> - | I18: =IF($E18=0,"-",EOMONTH(H18,G18-1)) -> - | M18: =IF(AND(M$13>=$F18,M$13<SUM($F18:$G18)),$E18/$G18,0) -> 0 | N18: =IF(AND(N$13>=$F18,N$13<SUM($F18:$G18)),$E18/$G18,0) -> 0 | O18: =IF(AND(O$13>=$F18,O$13<SUM($F18:$G18)),$E18/$G18,0) -> 0 | P18: =IF(AND(P$13>=$F18,P$13<SUM($F18:$G18)),$E18/$G18,0) -> 0 | Q18: =IF(AND(Q$13>=$F18,Q$13<SUM($F18:$G18)),$E18/$G18,0) -> 0 | R18: =IF(AND(R$13>=$F18,R$13<SUM($F18:$G18)),$E18/$G18,0) -> 0 | S18: =IF(AND(S$13>=$F18,S$13<SUM($F18:$G18)),$E18/$G18,0) -> 0 | T18: =IF(AND(T$13>=$F18,T$13<SUM($F18:$G18)),$E18/$G18,0) -> 0 | ... EC18: =IF(AND(EC$13>=$F18,EC$13<SUM($F18:$G18)),$E18/$G18,0) -> 0
C19: Security | E19: 0 | F19: 10 | G19: 3 | H19: =IF($E19=0,"-",EOMONTH($E$7,F19)) -> - | I19: =IF($E19=0,"-",EOMONTH(H19,G19-1)) -> - | M19: =IF(AND(M$13>=$F19,M$13<SUM($F19:$G19)),$E19/$G19,0) -> 0 | N19: =IF(AND(N$13>=$F19,N$13<SUM($F19:$G19)),$E19/$G19,0) -> 0 | O19: =IF(AND(O$13>=$F19,O$13<SUM($F19:$G19)),$E19/$G19,0) -> 0 | P19: =IF(AND(P$13>=$F19,P$13<SUM($F19:$G19)),$E19/$G19,0) -> 0 | Q19: =IF(AND(Q$13>=$F19,Q$13<SUM($F19:$G19)),$E19/$G19,0) -> 0 | R19: =IF(AND(R$13>=$F19,R$13<SUM($F19:$G19)),$E19/$G19,0) -> 0 | S19: =IF(AND(S$13>=$F19,S$13<SUM($F19:$G19)),$E19/$G19,0) -> 0 | T19: =IF(AND(T$13>=$F19,T$13<SUM($F19:$G19)),$E19/$G19,0) -> 0 | ... EC19: =IF(AND(EC$13>=$F19,EC$13<SUM($F19:$G19)),$E19/$G19,0) -> 0
C20: Cost Escalations | D20: 0.05 | E20: =SUM(E14:E19)*D20 -> 0 | H20: =IF($E20=0,"-",EOMONTH($E$7,F20)) -> - | I20: =IF($E20=0,"-",EOMONTH(H20,G20-1)) -> - | M20: =$D$20*SUM(M14:M19) -> 0 | N20: =$D$20*SUM(N14:N19) -> 0 | O20: =$D$20*SUM(O14:O19) -> 0 | P20: =$D$20*SUM(P14:P19) -> 0 | Q20: =$D$20*SUM(Q14:Q19) -> 0 | R20: =$D$20*SUM(R14:R19) -> 0 | S20: =$D$20*SUM(S14:S19) -> 0 | T20: =$D$20*SUM(T14:T19) -> 0 | ... EC20: =$D$20*SUM(EC14:EC19) -> 0
C21: Contingency | D21: 0.05 | E21: =SUM(M21:EC21) -> 0 | H21: =MIN(H14:H20) -> 0 | I21: =MAX(I14:I20) -> 0 | M21: =$D$21*SUM(M14:M20) -> 0 | N21: =$D$21*SUM(N14:N20) -> 0 | O21: =$D$21*SUM(O14:O20) -> 0 | P21: =$D$21*SUM(P14:P20) -> 0 | Q21: =$D$21*SUM(Q14:Q20) -> 0 | R21: =$D$21*SUM(R14:R20) -> 0 | S21: =$D$21*SUM(S14:S20) -> 0 | T21: =$D$21*SUM(T14:T20) -> 0 | ... EC21: =$D$21*SUM(EC14:EC20) -> 0
C22: GST | D22: 0.1 | E22: =SUM(M22:EC22) -> 0 | H22: =MIN(H15:H21) -> 0 | I22: =MAX(I15:I21) -> 0 | M22: =$D$22*SUM(M14:M21) -> 0 | N22: =$D$22*SUM(N14:N21) -> 0 | O22: =$D$22*SUM(O14:O21) -> 0 | P22: =$D$22*SUM(P14:P21) -> 0 | Q22: =$D$22*SUM(Q14:Q21) -> 0 | R22: =$D$22*SUM(R14:R21) -> 0 | S22: =$D$22*SUM(S14:S21) -> 0 | T22: =$D$22*SUM(T14:T21) -> 0 | ... EC22: =$D$22*SUM(EC14:EC21) -> 0
C23: GST Recapture | E23: =-E22 -> 0 | H23: =MIN(H16:H22) -> 0 | I23: =MAX(I16:I22) -> 0 | M23: =-M22 -> 0 | N23: =-N22 -> 0 | O23: =-O22 -> 0 | P23: =-P22 -> 0 | Q23: =-Q22 -> 0 | R23: =-R22 -> 0 | S23: =-S22 -> 0 | T23: =-T22 -> 0 | ... EC23: =-EC22 -> 0
C24: Total | D24: =E24/($E$8) -> #DIV/0! | E24: =SUM(E14:E23) -> 0 | L24: =SUM(M24:EC24) -> 0 | M24: =SUBTOTAL(9,M14:M23) -> 0 | N24: =SUBTOTAL(9,N14:N23) -> 0 | O24: =SUBTOTAL(9,O14:O23) -> 0 | P24: =SUBTOTAL(9,P14:P23) -> 0 | Q24: =SUBTOTAL(9,Q14:Q23) -> 0 | R24: =SUBTOTAL(9,R14:R23) -> 0 | S24: =SUBTOTAL(9,S14:S23) -> 0 | T24: =SUBTOTAL(9,T14:T23) -> 0 | ... EC24: =SUBTOTAL(9,EC14:EC23) -> 0
C26: Soft Costs | F26: Month | G26: Duration | H26: Start Date | I26: End Date
C27: Soft Cost Esitmate | D27: 0.01 | E27: =D27*E24 -> 0 | F27: 7 | G27: =F14+G14-F27 -> 14 | H27: =IF($E27=0,"-",EOMONTH($E$7,F27)) -> - | I27: =IF($E27=0,"-",EOMONTH(H27,G27-1)) -> - | M27: =IF(AND(M$13>=$F27,M$13<SUM($F27:$G27)),$E27/$G27,0) -> 0 | N27: =IF(AND(N$13>=$F27,N$13<SUM($F27:$G27)),$E27/$G27,0) -> 0 | O27: =IF(AND(O$13>=$F27,O$13<SUM($F27:$G27)),$E27/$G27,0) -> 0 | P27: =IF(AND(P$13>=$F27,P$13<SUM($F27:$G27)),$E27/$G27,0) -> 0 | Q27: =IF(AND(Q$13>=$F27,Q$13<SUM($F27:$G27)),$E27/$G27,0) -> 0 | R27: =IF(AND(R$13>=$F27,R$13<SUM($F27:$G27)),$E27/$G27,0) -> 0 | S27: =IF(AND(S$13>=$F27,S$13<SUM($F27:$G27)),$E27/$G27,0) -> 0 | T27: =IF(AND(T$13>=$F27,T$13<SUM($F27:$G27)),$E27/$G27,0) -> 0 | ... EC27: =IF(AND(EC$13>=$F27,EC$13<SUM($F27:$G27)),$E27/$G27,0) -> 0
C28: Contingency | D28: 0 | E28: =SUM(M28:EC28) -> 0 | H28: =MIN(H20:H27) -> 0 | I28: =MAX(I20:I27) -> 0 | M28: =$D$28*SUM(M26:M27) -> 0 | N28: =$D$28*SUM(N26:N27) -> 0 | O28: =$D$28*SUM(O26:O27) -> 0 | P28: =$D$28*SUM(P26:P27) -> 0 | Q28: =$D$28*SUM(Q26:Q27) -> 0 | R28: =$D$28*SUM(R26:R27) -> 0 | S28: =$D$28*SUM(S26:S27) -> 0 | T28: =$D$28*SUM(T26:T27) -> 0 | ... EC28: =$D$28*SUM(EC26:EC27) -> 0
C29: GST | D29: =D22 -> 0.1 | E29: =SUM(M29:EC29) -> 0 | H29: =MIN(H27:H28) -> 0 | I29: =MAX(I27:I28) -> 0 | M29: =$D$29*SUM(M27:M28) -> 0 | N29: =$D$29*SUM(N27:N28) -> 0 | O29: =$D$29*SUM(O27:O28) -> 0 | P29: =$D$29*SUM(P27:P28) -> 0 | Q29: =$D$29*SUM(Q27:Q28) -> 0 | R29: =$D$29*SUM(R27:R28) -> 0 | S29: =$D$29*SUM(S27:S28) -> 0 | T29: =$D$29*SUM(T27:T28) -> 0 | ... EC29: =$D$29*SUM(EC27:EC28) -> 0
C30: GST Recapture | E30: =-E29 -> 0 | H30: =MIN(H27:H29) -> 0 | I30: =MAX(I27:I29) -> 0 | M30: =-M29 -> 0 | N30: =-N29 -> 0 | O30: =-O29 -> 0 | P30: =-P29 -> 0 | Q30: =-Q29 -> 0 | R30: =-R29 -> 0 | S30: =-S29 -> 0 | T30: =-T29 -> 0 | ... EC30: =-EC29 -> 0
C31: Total | D31: =E31/($E$8+'Workstore Sales'!$E$33) -> #DIV/0! | E31: =SUM(E26:E30) -> 0 | M31: =SUBTOTAL(9,M27:M30) -> 0 | N31: =SUBTOTAL(9,N27:N30) -> 0 | O31: =SUBTOTAL(9,O27:O30) -> 0 | P31: =SUBTOTAL(9,P27:P30) -> 0 | Q31: =SUBTOTAL(9,Q27:Q30) -> 0 | R31: =SUBTOTAL(9,R27:R30) -> 0 | S31: =SUBTOTAL(9,S27:S30) -> 0 | T31: =SUBTOTAL(9,T27:T30) -> 0 | ... EC31: =SUBTOTAL(9,EC27:EC30) -> 0
C33: City Impact/Development Charges | F33: Month | G33: Duration | H33: Start Date | I33: End Date
C34: Development Application Fee | E34: =(E24/1000)*1.3 -> 0 | F34: 1 | G34: 1 | H34: =IF($E34=0,"-",EOMONTH($E$7,F34)) -> - | I34: =IF($E34=0,"-",EOMONTH(H34,G34-1)) -> - | M34: =IF(AND(M$13>=$F34,M$13<SUM($F34:$G34)),$E34/$G34,0) -> 0 | N34: =IF(AND(N$13>=$F34,N$13<SUM($F34:$G34)),$E34/$G34,0) -> 0 | O34: =IF(AND(O$13>=$F34,O$13<SUM($F34:$G34)),$E34/$G34,0) -> 0 | P34: =IF(AND(P$13>=$F34,P$13<SUM($F34:$G34)),$E34/$G34,0) -> 0 | Q34: =IF(AND(Q$13>=$F34,Q$13<SUM($F34:$G34)),$E34/$G34,0) -> 0 | R34: =IF(AND(R$13>=$F34,R$13<SUM($F34:$G34)),$E34/$G34,0) -> 0 | S34: =IF(AND(S$13>=$F34,S$13<SUM($F34:$G34)),$E34/$G34,0) -> 0 | T34: =IF(AND(T$13>=$F34,T$13<SUM($F34:$G34)),$E34/$G34,0) -> 0 | ... EC34: =IF(AND(EC$13>=$F34,EC$13<SUM($F34:$G34)),$E34/$G34,0) -> 0
C35: Assessment Fee | E35: 0 | F35: 0 | G35: 1 | H35: =IF($E35=0,"-",EOMONTH($E$7,F35)) -> - | I35: =IF($E35=0,"-",EOMONTH(H35,G35-1)) -> - | M35: =IF(AND(M$13>=$F35,M$13<SUM($F35:$G35)),$E35/$G35,0) -> 0 | N35: =IF(AND(N$13>=$F35,N$13<SUM($F35:$G35)),$E35/$G35,0) -> 0 | O35: =IF(AND(O$13>=$F35,O$13<SUM($F35:$G35)),$E35/$G35,0) -> 0 | P35: =IF(AND(P$13>=$F35,P$13<SUM($F35:$G35)),$E35/$G35,0) -> 0 | Q35: =IF(AND(Q$13>=$F35,Q$13<SUM($F35:$G35)),$E35/$G35,0) -> 0 | R35: =IF(AND(R$13>=$F35,R$13<SUM($F35:$G35)),$E35/$G35,0) -> 0 | S35: =IF(AND(S$13>=$F35,S$13<SUM($F35:$G35)),$E35/$G35,0) -> 0 | T35: =IF(AND(T$13>=$F35,T$13<SUM($F35:$G35)),$E35/$G35,0) -> 0 | ... EC35: =IF(AND(EC$13>=$F35,EC$13<SUM($F35:$G35)),$E35/$G35,0) -> 0
C36: Local Fire Services Fee | E36: 0 | F36: 4 | G36: 1 | H36: =IF($E36=0,"-",EOMONTH($E$7,F36)) -> - | I36: =IF($E36=0,"-",EOMONTH(H36,G36-1)) -> - | M36: =IF(AND(M$13>=$F36,M$13<SUM($F36:$G36)),$E36/$G36,0) -> 0 | N36: =IF(AND(N$13>=$F36,N$13<SUM($F36:$G36)),$E36/$G36,0) -> 0 | O36: =IF(AND(O$13>=$F36,O$13<SUM($F36:$G36)),$E36/$G36,0) -> 0 | P36: =IF(AND(P$13>=$F36,P$13<SUM($F36:$G36)),$E36/$G36,0) -> 0 | Q36: =IF(AND(Q$13>=$F36,Q$13<SUM($F36:$G36)),$E36/$G36,0) -> 0 | R36: =IF(AND(R$13>=$F36,R$13<SUM($F36:$G36)),$E36/$G36,0) -> 0 | S36: =IF(AND(S$13>=$F36,S$13<SUM($F36:$G36)),$E36/$G36,0) -> 0 | T36: =IF(AND(T$13>=$F36,T$13<SUM($F36:$G36)),$E36/$G36,0) -> 0 | ... EC36: =IF(AND(EC$13>=$F36,EC$13<SUM($F36:$G36)),$E36/$G36,0) -> 0
C37: Infrastructure Charges | D37: 55 | E37: =D37*(E8+F8) -> 0 | F37: 20 | G37: 1 | H37: =IF($E37=0,"-",EOMONTH($E$7,F37)) -> - | I37: =IF($E37=0,"-",EOMONTH(H37,G37-1)) -> - | M37: =IF(AND(M$13>=$F37,M$13<SUM($F37:$G37)),$E37/$G37,0) -> 0 | N37: =IF(AND(N$13>=$F37,N$13<SUM($F37:$G37)),$E37/$G37,0) -> 0 | O37: =IF(AND(O$13>=$F37,O$13<SUM($F37:$G37)),$E37/$G37,0) -> 0 | P37: =IF(AND(P$13>=$F37,P$13<SUM($F37:$G37)),$E37/$G37,0) -> 0 | Q37: =IF(AND(Q$13>=$F37,Q$13<SUM($F37:$G37)),$E37/$G37,0) -> 0 | R37: =IF(AND(R$13>=$F37,R$13<SUM($F37:$G37)),$E37/$G37,0) -> 0 | S37: =IF(AND(S$13>=$F37,S$13<SUM($F37:$G37)),$E37/$G37,0) -> 0 | T37: =IF(AND(T$13>=$F37,T$13<SUM($F37:$G37)),$E37/$G37,0) -> 0 | ... EC37: =IF(AND(EC$13>=$F37,EC$13<SUM($F37:$G37)),$E37/$G37,0) -> 0
C38: Area Impervious to Stormwater | D38: 11 | E38: =D38*UW!E12/2 -> 0 | F38: 20 | G38: 1 | H38: =IF($E38=0,"-",EOMONTH($E$7,F38)) -> - | I38: =IF($E38=0,"-",EOMONTH(H38,G38-1)) -> - | M38: =IF(AND(M$13>=$F38,M$13<SUM($F38:$G38)),$E38/$G38,0) -> 0 | N38: =IF(AND(N$13>=$F38,N$13<SUM($F38:$G38)),$E38/$G38,0) -> 0 | O38: =IF(AND(O$13>=$F38,O$13<SUM($F38:$G38)),$E38/$G38,0) -> 0 | P38: =IF(AND(P$13>=$F38,P$13<SUM($F38:$G38)),$E38/$G38,0) -> 0 | Q38: =IF(AND(Q$13>=$F38,Q$13<SUM($F38:$G38)),$E38/$G38,0) -> 0 | R38: =IF(AND(R$13>=$F38,R$13<SUM($F38:$G38)),$E38/$G38,0) -> 0 | S38: =IF(AND(S$13>=$F38,S$13<SUM($F38:$G38)),$E38/$G38,0) -> 0 | T38: =IF(AND(T$13>=$F38,T$13<SUM($F38:$G38)),$E38/$G38,0) -> 0 | ... EC38: =IF(AND(EC$13>=$F38,EC$13<SUM($F38:$G38)),$E38/$G38,0) -> 0
C39: Qleave levy | D39: 0.00525 | E39: =D39*E24 -> 0 | F39: 6 | G39: 1 | H39: =IF($E39=0,"-",EOMONTH($E$7,F39)) -> - | I39: =IF($E39=0,"-",EOMONTH(H39,G39-1)) -> - | M39: =IF(AND(M$13>=$F39,M$13<SUM($F39:$G39)),$E39/$G39,0) -> 0 | N39: =IF(AND(N$13>=$F39,N$13<SUM($F39:$G39)),$E39/$G39,0) -> 0 | O39: =IF(AND(O$13>=$F39,O$13<SUM($F39:$G39)),$E39/$G39,0) -> 0 | P39: =IF(AND(P$13>=$F39,P$13<SUM($F39:$G39)),$E39/$G39,0) -> 0 | Q39: =IF(AND(Q$13>=$F39,Q$13<SUM($F39:$G39)),$E39/$G39,0) -> 0 | R39: =IF(AND(R$13>=$F39,R$13<SUM($F39:$G39)),$E39/$G39,0) -> 0 | S39: =IF(AND(S$13>=$F39,S$13<SUM($F39:$G39)),$E39/$G39,0) -> 0 | T39: =IF(AND(T$13>=$F39,T$13<SUM($F39:$G39)),$E39/$G39,0) -> 0 | ... EC39: =IF(AND(EC$13>=$F39,EC$13<SUM($F39:$G39)),$E39/$G39,0) -> 0
C40: Water Connection Fee | E40: 0 | F40: 1 | G40: 1 | H40: =IF($E40=0,"-",EOMONTH($E$7,F40)) -> - | I40: =IF($E40=0,"-",EOMONTH(H40,G40-1)) -> - | M40: =IF(AND(M$13>=$F40,M$13<SUM($F40:$G40)),$E40/$G40,0) -> 0 | N40: =IF(AND(N$13>=$F40,N$13<SUM($F40:$G40)),$E40/$G40,0) -> 0 | O40: =IF(AND(O$13>=$F40,O$13<SUM($F40:$G40)),$E40/$G40,0) -> 0 | P40: =IF(AND(P$13>=$F40,P$13<SUM($F40:$G40)),$E40/$G40,0) -> 0 | Q40: =IF(AND(Q$13>=$F40,Q$13<SUM($F40:$G40)),$E40/$G40,0) -> 0 | R40: =IF(AND(R$13>=$F40,R$13<SUM($F40:$G40)),$E40/$G40,0) -> 0 | S40: =IF(AND(S$13>=$F40,S$13<SUM($F40:$G40)),$E40/$G40,0) -> 0 | T40: =IF(AND(T$13>=$F40,T$13<SUM($F40:$G40)),$E40/$G40,0) -> 0 | ... EC40: =IF(AND(EC$13>=$F40,EC$13<SUM($F40:$G40)),$E40/$G40,0) -> 0
C41: Electrical and Comms Connection Fee | E41: 0 | F41: 1 | G41: 1 | H41: =IF($E41=0,"-",EOMONTH($E$7,F41)) -> - | I41: =IF($E41=0,"-",EOMONTH(H41,G41-1)) -> - | M41: =IF(AND(M$13>=$F41,M$13<SUM($F41:$G41)),$E41/$G41,0) -> 0 | N41: =IF(AND(N$13>=$F41,N$13<SUM($F41:$G41)),$E41/$G41,0) -> 0 | O41: =IF(AND(O$13>=$F41,O$13<SUM($F41:$G41)),$E41/$G41,0) -> 0 | P41: =IF(AND(P$13>=$F41,P$13<SUM($F41:$G41)),$E41/$G41,0) -> 0 | Q41: =IF(AND(Q$13>=$F41,Q$13<SUM($F41:$G41)),$E41/$G41,0) -> 0 | R41: =IF(AND(R$13>=$F41,R$13<SUM($F41:$G41)),$E41/$G41,0) -> 0 | S41: =IF(AND(S$13>=$F41,S$13<SUM($F41:$G41)),$E41/$G41,0) -> 0 | T41: =IF(AND(T$13>=$F41,T$13<SUM($F41:$G41)),$E41/$G41,0) -> 0 | ... EC41: =IF(AND(EC$13>=$F41,EC$13<SUM($F41:$G41)),$E41/$G41,0) -> 0
C42: Parkland Dedication Fee (% of Land Value) | D42: 0 | E42: =D42*E5 -> 0 | F42: 0 | G42: 0 | H42: =IF($E42=0,"-",EOMONTH($E$7,F42)) -> - | I42: =IF($E42=0,"-",EOMONTH(H42,G42-1)) -> - | M42: =IF(AND(M$13>=$F42,M$13<SUM($F42:$G42)),$E42/$G42,0) -> 0 | N42: =IF(AND(N$13>=$F42,N$13<SUM($F42:$G42)),$E42/$G42,0) -> 0 | O42: =IF(AND(O$13>=$F42,O$13<SUM($F42:$G42)),$E42/$G42,0) -> 0 | P42: =IF(AND(P$13>=$F42,P$13<SUM($F42:$G42)),$E42/$G42,0) -> 0 | Q42: =IF(AND(Q$13>=$F42,Q$13<SUM($F42:$G42)),$E42/$G42,0) -> 0 | R42: =IF(AND(R$13>=$F42,R$13<SUM($F42:$G42)),$E42/$G42,0) -> 0 | S42: =IF(AND(S$13>=$F42,S$13<SUM($F42:$G42)),$E42/$G42,0) -> 0 | T42: =IF(AND(T$13>=$F42,T$13<SUM($F42:$G42)),$E42/$G42,0) -> 0 | ... EC42: =IF(AND(EC$13>=$F42,EC$13<SUM($F42:$G42)),$E42/$G42,0) -> 0
C43: Contingency | D43: 0.1 | E43: =SUM(M43:EC43) -> 0 | H43: =MIN(H34:H42) -> 0 | I43: =MAX(I34:I42) -> 0 | M43: =$D$43*SUM(M34:M42) -> 0 | N43: =$D$43*SUM(N34:N42) -> 0 | O43: =$D$43*SUM(O34:O42) -> 0 | P43: =$D$43*SUM(P34:P42) -> 0 | Q43: =$D$43*SUM(Q34:Q42) -> 0 | R43: =$D$43*SUM(R34:R42) -> 0 | S43: =$D$43*SUM(S34:S42) -> 0 | T43: =$D$43*SUM(T34:T42) -> 0 | ... EC43: =$D$43*SUM(EC34:EC42) -> 0
C44: Total | D44: =E44/($E$8+'Workstore Sales'!$E$33) -> #DIV/0! | E44: =SUM(E34:E43) -> 0 | M44: =SUBTOTAL(9,M34:M43) -> 0 | N44: =SUBTOTAL(9,N34:N43) -> 0 | O44: =SUBTOTAL(9,O34:O43) -> 0 | P44: =SUBTOTAL(9,P34:P43) -> 0 | Q44: =SUBTOTAL(9,Q34:Q43) -> 0 | R44: =SUBTOTAL(9,R34:R43) -> 0 | S44: =SUBTOTAL(9,S34:S43) -> 0 | T44: =SUBTOTAL(9,T34:T43) -> 0 | ... EC44: =SUBTOTAL(9,EC34:EC43) -> 0
C46: Financing Cost and Operating Reserves and Msc. Capex
C47: Operating Reserves | F47: 0 | G47: 0 | H47: =IF($E47=0,"-",EOMONTH($E$7,F47)) -> - | I47: =IF($E47=0,"-",EOMONTH(H47,G47-1)) -> - | M47: =IF(AND(M$13>=$F47,M$13<SUM($F47:$G47)),$E47/$G47,0) -> 0 | N47: =IF(AND(N$13>=$F47,N$13<SUM($F47:$G47)),$E47/$G47,0) -> 0 | O47: =IF(AND(O$13>=$F47,O$13<SUM($F47:$G47)),$E47/$G47,0) -> 0 | P47: =IF(AND(P$13>=$F47,P$13<SUM($F47:$G47)),$E47/$G47,0) -> 0 | Q47: =IF(AND(Q$13>=$F47,Q$13<SUM($F47:$G47)),$E47/$G47,0) -> 0 | R47: =IF(AND(R$13>=$F47,R$13<SUM($F47:$G47)),$E47/$G47,0) -> 0 | S47: =IF(AND(S$13>=$F47,S$13<SUM($F47:$G47)),$E47/$G47,0) -> 0 | T47: =IF(AND(T$13>=$F47,T$13<SUM($F47:$G47)),$E47/$G47,0) -> 0 | ... EC47: =IF(AND(EC$13>=$F47,EC$13<SUM($F47:$G47)),$E47/$G47,0) -> 0
C48: Development Management Fee | D48: =UW!J52 -> 0.05 | E48: =D48*($E$31+$E$24) -> 0 | F48: =F14 -> 7 | G48: =G14 -> 14 | H48: =IF($E48=0,"-",EOMONTH($E$7,F48)) -> - | I48: =IF($E48=0,"-",EOMONTH(H48,G48-1)) -> - | M48: =IF(AND(M$13>=$F48,M$13<SUM($F48:$G48)),$E48/$G48,0) -> 0 | N48: =IF(AND(N$13>=$F48,N$13<SUM($F48:$G48)),$E48/$G48,0) -> 0 | O48: =IF(AND(O$13>=$F48,O$13<SUM($F48:$G48)),$E48/$G48,0) -> 0 | P48: =IF(AND(P$13>=$F48,P$13<SUM($F48:$G48)),$E48/$G48,0) -> 0 | Q48: =IF(AND(Q$13>=$F48,Q$13<SUM($F48:$G48)),$E48/$G48,0) -> 0 | R48: =IF(AND(R$13>=$F48,R$13<SUM($F48:$G48)),$E48/$G48,0) -> 0 | S48: =IF(AND(S$13>=$F48,S$13<SUM($F48:$G48)),$E48/$G48,0) -> 0 | T48: =IF(AND(T$13>=$F48,T$13<SUM($F48:$G48)),$E48/$G48,0) -> 0 | ... EC48: =IF(AND(EC$13>=$F48,EC$13<SUM($F48:$G48)),$E48/$G48,0) -> 0
C49: Project Management Fee | D49: 0.009 | E49: =D49*($E$31+$E$24) -> 0 | F49: =F48-2 -> 5 | G49: =G48+2 -> 16 | H49: =IF($E49=0,"-",EOMONTH($E$7,F49)) -> - | I49: =IF($E49=0,"-",EOMONTH(H49,G49-1)) -> - | M49: =IF(AND(M$13>=$F49,M$13<SUM($F49:$G49)),$E49/$G49,0) -> 0 | N49: =IF(AND(N$13>=$F49,N$13<SUM($F49:$G49)),$E49/$G49,0) -> 0 | O49: =IF(AND(O$13>=$F49,O$13<SUM($F49:$G49)),$E49/$G49,0) -> 0 | P49: =IF(AND(P$13>=$F49,P$13<SUM($F49:$G49)),$E49/$G49,0) -> 0 | Q49: =IF(AND(Q$13>=$F49,Q$13<SUM($F49:$G49)),$E49/$G49,0) -> 0 | R49: =IF(AND(R$13>=$F49,R$13<SUM($F49:$G49)),$E49/$G49,0) -> 0 | S49: =IF(AND(S$13>=$F49,S$13<SUM($F49:$G49)),$E49/$G49,0) -> 0 | T49: =IF(AND(T$13>=$F49,T$13<SUM($F49:$G49)),$E49/$G49,0) -> 0 | ... EC49: =IF(AND(EC$13>=$F49,EC$13<SUM($F49:$G49)),$E49/$G49,0) -> 0
C50: Travel | E50: 0 | F50: 1 | G50: 14 | H50: =IF($E50=0,"-",EOMONTH($E$7,F50)) -> - | I50: =IF($E50=0,"-",EOMONTH(H50,G50-1)) -> - | M50: =IF(AND(M$13>=$F50,M$13<SUM($F50:$G50)),$E50/$G50,0) -> 0 | N50: =IF(AND(N$13>=$F50,N$13<SUM($F50:$G50)),$E50/$G50,0) -> 0 | O50: =IF(AND(O$13>=$F50,O$13<SUM($F50:$G50)),$E50/$G50,0) -> 0 | P50: =IF(AND(P$13>=$F50,P$13<SUM($F50:$G50)),$E50/$G50,0) -> 0 | Q50: =IF(AND(Q$13>=$F50,Q$13<SUM($F50:$G50)),$E50/$G50,0) -> 0 | R50: =IF(AND(R$13>=$F50,R$13<SUM($F50:$G50)),$E50/$G50,0) -> 0 | S50: =IF(AND(S$13>=$F50,S$13<SUM($F50:$G50)),$E50/$G50,0) -> 0 | T50: =IF(AND(T$13>=$F50,T$13<SUM($F50:$G50)),$E50/$G50,0) -> 0 | ... EC50: =IF(AND(EC$13>=$F50,EC$13<SUM($F50:$G50)),$E50/$G50,0) -> 0
C51: SLM Start Up Costs | E51: 60000 | F51: 20 | G51: 1 | H51: =IF($E51=0,"-",EOMONTH($E$7,F51)) -> 46721 | I51: =IF($E51=0,"-",EOMONTH(H51,G51-1)) -> 46721 | M51: =IF(AND(M$13>=$F51,M$13<SUM($F51:$G51)),$E51/$G51,0) -> 0 | N51: =IF(AND(N$13>=$F51,N$13<SUM($F51:$G51)),$E51/$G51,0) -> 0 | O51: =IF(AND(O$13>=$F51,O$13<SUM($F51:$G51)),$E51/$G51,0) -> 0 | P51: =IF(AND(P$13>=$F51,P$13<SUM($F51:$G51)),$E51/$G51,0) -> 0 | Q51: =IF(AND(Q$13>=$F51,Q$13<SUM($F51:$G51)),$E51/$G51,0) -> 0 | R51: =IF(AND(R$13>=$F51,R$13<SUM($F51:$G51)),$E51/$G51,0) -> 0 | S51: =IF(AND(S$13>=$F51,S$13<SUM($F51:$G51)),$E51/$G51,0) -> 0 | T51: =IF(AND(T$13>=$F51,T$13<SUM($F51:$G51)),$E51/$G51,0) -> 0 | ... EC51: =IF(AND(EC$13>=$F51,EC$13<SUM($F51:$G51)),$E51/$G51,0) -> 0
C52: Cart/Golf Carts | E52: 0 | F52: 12 | G52: 1 | H52: =IF($E52=0,"-",EOMONTH($E$7,F52)) -> - | I52: =IF($E52=0,"-",EOMONTH(H52,G52-1)) -> - | M52: =IF(AND(M$13>=$F52,M$13<SUM($F52:$G52)),$E52/$G52,0) -> 0 | N52: =IF(AND(N$13>=$F52,N$13<SUM($F52:$G52)),$E52/$G52,0) -> 0 | O52: =IF(AND(O$13>=$F52,O$13<SUM($F52:$G52)),$E52/$G52,0) -> 0 | P52: =IF(AND(P$13>=$F52,P$13<SUM($F52:$G52)),$E52/$G52,0) -> 0 | Q52: =IF(AND(Q$13>=$F52,Q$13<SUM($F52:$G52)),$E52/$G52,0) -> 0 | R52: =IF(AND(R$13>=$F52,R$13<SUM($F52:$G52)),$E52/$G52,0) -> 0 | S52: =IF(AND(S$13>=$F52,S$13<SUM($F52:$G52)),$E52/$G52,0) -> 0 | T52: =IF(AND(T$13>=$F52,T$13<SUM($F52:$G52)),$E52/$G52,0) -> 0 | ... EC52: =IF(AND(EC$13>=$F52,EC$13<SUM($F52:$G52)),$E52/$G52,0) -> 0
C53: Computers/Tech/Phone | F53: 12 | G53: 1 | H53: =IF($E53=0,"-",EOMONTH($E$7,F53)) -> - | I53: =IF($E53=0,"-",EOMONTH(H53,G53-1)) -> - | M53: =IF(AND(M$13>=$F53,M$13<SUM($F53:$G53)),$E53/$G53,0) -> 0 | N53: =IF(AND(N$13>=$F53,N$13<SUM($F53:$G53)),$E53/$G53,0) -> 0 | O53: =IF(AND(O$13>=$F53,O$13<SUM($F53:$G53)),$E53/$G53,0) -> 0 | P53: =IF(AND(P$13>=$F53,P$13<SUM($F53:$G53)),$E53/$G53,0) -> 0 | Q53: =IF(AND(Q$13>=$F53,Q$13<SUM($F53:$G53)),$E53/$G53,0) -> 0 | R53: =IF(AND(R$13>=$F53,R$13<SUM($F53:$G53)),$E53/$G53,0) -> 0 | S53: =IF(AND(S$13>=$F53,S$13<SUM($F53:$G53)),$E53/$G53,0) -> 0 | T53: =IF(AND(T$13>=$F53,T$13<SUM($F53:$G53)),$E53/$G53,0) -> 0 | ... EC53: =IF(AND(EC$13>=$F53,EC$13<SUM($F53:$G53)),$E53/$G53,0) -> 0
C54: Contingency | D54: 0 | E54: =SUM(M54:EC54) -> 0 | H54: =MIN(H47:H53) -> 46721 | I54: =MAX(I47:I53) -> 46721 | M54: =$D$54*SUM(M47:M53) -> 0 | N54: =$D$54*SUM(N47:N53) -> 0 | O54: =$D$54*SUM(O47:O53) -> 0 | P54: =$D$54*SUM(P47:P53) -> 0 | Q54: =$D$54*SUM(Q47:Q53) -> 0 | R54: =$D$54*SUM(R47:R53) -> 0 | S54: =$D$54*SUM(S47:S53) -> 0 | T54: =$D$54*SUM(T47:T53) -> 0 | ... EC54: =$D$54*SUM(EC47:EC53) -> 0
C55: Total | D55: =E55/($E$8+'Workstore Sales'!$E$33) -> #DIV/0! | E55: =SUM(E47:E54) -> 60000 | M55: =SUBTOTAL(9,M47:M54) -> 0 | N55: =SUBTOTAL(9,N47:N54) -> 0 | O55: =SUBTOTAL(9,O47:O54) -> 0 | P55: =SUBTOTAL(9,P47:P54) -> 0 | Q55: =SUBTOTAL(9,Q47:Q54) -> 0 | R55: =SUBTOTAL(9,R47:R54) -> 0 | S55: =SUBTOTAL(9,S47:S54) -> 0 | T55: =SUBTOTAL(9,T47:T54) -> 0 | ... EC55: =SUBTOTAL(9,EC47:EC54) -> 0
C57: Total Development Cost (Excluding Land) | D57: =E57/($E$8+'Workstore Sales'!$E$33) -> #DIV/0! | E57: =E55+E44+E31+E24 -> 60000 | F57: Check: | G57: =E57-SUM(L57:EC57) -> 0 | K57: =SUM(M57:EC57) -> 60000 | M57: =SUBTOTAL(9,M14:M55) -> 0 | N57: =SUBTOTAL(9,N14:N55) -> 0 | O57: =SUBTOTAL(9,O14:O55) -> 0 | P57: =SUBTOTAL(9,P14:P55) -> 0 | Q57: =SUBTOTAL(9,Q14:Q55) -> 0 | R57: =SUBTOTAL(9,R14:R55) -> 0 | S57: =SUBTOTAL(9,S14:S55) -> 0 | T57: =SUBTOTAL(9,T14:T55) -> 0 | ... EC57: =SUBTOTAL(9,EC14:EC55) -> 0
C58: Total Project Cost | D58: =E58/$E$8 -> #DIV/0! | E58: =E57+E5 -> 60000
E59: 25646877 | M59: =M57/$K$57*$E$57 -> 0 | N59: =N57/$K$57*$E$57 -> 0 | O59: =O57/$K$57*$E$57 -> 0 | P59: =P57/$K$57*$E$57 -> 0 | Q59: =Q57/$K$57*$E$57 -> 0 | R59: =R57/$K$57*$E$57 -> 0 | S59: =S57/$K$57*$E$57 -> 0 | T59: =T57/$K$57*$E$57 -> 0 | ... EC59: =EC57/$K$57*$E$57 -> 0
C62: Sensitivity Analysis - Construction Cost
C63: Construction Cost | D63: =E59 -> 25646877 | E63: =D63+250000 -> 25896877 | F63: =E63+250000 -> 26146877 | G63: =F63+250000 -> 26396877 | H63: =G63+250000 -> 26646877 | I63: =H63+250000 -> 26896877 | J63: =I63+250000 -> 27146877
C64: IRR - Levered (Deal Level) | D64: =INDEX($D$73:$D$79,MATCH(D$63,$C$73:$C$79,0),) -> 0 | E64: =INDEX($D$73:$D$79,MATCH(E$63,$C$73:$C$79,0),) -> 0 | F64: =INDEX($D$73:$D$79,MATCH(F$63,$C$73:$C$79,0),) -> 0 | G64: =INDEX($D$73:$D$79,MATCH(G$63,$C$73:$C$79,0),) -> 0 | H64: =INDEX($D$73:$D$79,MATCH(H$63,$C$73:$C$79,0),) -> 0 | I64: =INDEX($D$73:$D$79,MATCH(I$63,$C$73:$C$79,0),) -> 0 | J64: =INDEX($D$73:$D$79,MATCH(J$63,$C$73:$C$79,0),) -> 0
C65: IRR - Levered (Project Level) | D65: =INDEX($F$73:$F$79,MATCH(D$63,$C$73:$C$79,0),) -> 0 | E65: =INDEX($F$73:$F$79,MATCH(E$63,$C$73:$C$79,0),) -> 0 | F65: =INDEX($F$73:$F$79,MATCH(F$63,$C$73:$C$79,0),) -> 0 | G65: =INDEX($F$73:$F$79,MATCH(G$63,$C$73:$C$79,0),) -> 0 | H65: =INDEX($F$73:$F$79,MATCH(H$63,$C$73:$C$79,0),) -> 0 | I65: =INDEX($F$73:$F$79,MATCH(I$63,$C$73:$C$79,0),) -> 0 | J65: =INDEX($F$73:$F$79,MATCH(J$63,$C$73:$C$79,0),) -> 0
C66: IRR - Unlevered | D66: =INDEX($H$73:$H$79,MATCH(D$63,$C$73:$C$79,0),) -> 0 | E66: =INDEX($H$73:$H$79,MATCH(E$63,$C$73:$C$79,0),) -> 0 | F66: =INDEX($H$73:$H$79,MATCH(F$63,$C$73:$C$79,0),) -> 0 | G66: =INDEX($H$73:$H$79,MATCH(G$63,$C$73:$C$79,0),) -> 0 | H66: =INDEX($H$73:$H$79,MATCH(H$63,$C$73:$C$79,0),) -> 0 | I66: =INDEX($H$73:$H$79,MATCH(I$63,$C$73:$C$79,0),) -> 0 | J66: =INDEX($H$73:$H$79,MATCH(J$63,$C$73:$C$79,0),) -> 0
C67: Equity Multiple: | D67: =INDEX($J$73:$J$79,MATCH(D$63,$C$73:$C$79,0),) -> 0 | E67: =INDEX($J$73:$J$79,MATCH(E$63,$C$73:$C$79,0),) -> 0 | F67: =INDEX($J$73:$J$79,MATCH(F$63,$C$73:$C$79,0),) -> 0 | G67: =INDEX($J$73:$J$79,MATCH(G$63,$C$73:$C$79,0),) -> 0 | H67: =INDEX($J$73:$J$79,MATCH(H$63,$C$73:$C$79,0),) -> 0 | I67: =INDEX($J$73:$J$79,MATCH(I$63,$C$73:$C$79,0),) -> 0 | J67: =INDEX($J$73:$J$79,MATCH(J$63,$C$73:$C$79,0),) -> 0
C68: Yield on Cost | D68: =INDEX($L$73:$L$79,MATCH(D$63,$C$73:$C$79,0),) -> 0 | E68: =INDEX($L$73:$L$79,MATCH(E$63,$C$73:$C$79,0),) -> 0 | F68: =INDEX($L$73:$L$79,MATCH(F$63,$C$73:$C$79,0),) -> 0 | G68: =INDEX($L$73:$L$79,MATCH(G$63,$C$73:$C$79,0),) -> 0 | H68: =INDEX($L$73:$L$79,MATCH(H$63,$C$73:$C$79,0),) -> 0 | I68: =INDEX($L$73:$L$79,MATCH(I$63,$C$73:$C$79,0),) -> 0 | J68: =INDEX($L$73:$L$79,MATCH(J$63,$C$73:$C$79,0),) -> 0
C69: Construction Price Sensitivity | D69: 250000
D71: IRR Levered | F71: IRR Project | H71: IRR Unlevered | J71: Equity Multiple | L71: Yield on Cost
D72: =UW!#REF! -> #REF! | F72: =UW!#REF! -> #REF! | H72: =UW!#REF! -> #REF! | J72: =UW!J16 -> #DIV/0! | L72: =UW!J18 -> #DIV/0!
C73: 25646877 | E73: =$C73 -> 25646877 | G73: =C73 -> 25646877 | I73: =$C73 -> 25646877 | K73: =C73 -> 25646877
C74: =E63 -> 25896877 | E74: =$C74 -> 25896877 | G74: =C74 -> 25896877 | I74: =$C74 -> 25896877 | K74: =C74 -> 25896877
C75: =F63 -> 26146877 | E75: =$C75 -> 26146877 | G75: =C75 -> 26146877 | I75: =$C75 -> 26146877 | K75: =C75 -> 26146877
C76: =G63 -> 26396877 | E76: =$C76 -> 26396877 | G76: =C76 -> 26396877 | I76: =$C76 -> 26396877 | K76: =C76 -> 26396877
C77: =H63 -> 26646877 | E77: =$C77 -> 26646877 | G77: =C77 -> 26646877 | I77: =$C77 -> 26646877 | K77: =C77 -> 26646877
C78: =I63 -> 26896877 | E78: =$C78 -> 26896877 | G78: =C78 -> 26896877 | I78: =$C78 -> 26896877 | K78: =C78 -> 26896877
C79: =J63 -> 27146877 | E79: =$C79 -> 27146877 | G79: =C79 -> 27146877 | I79: =$C79 -> 27146877 | K79: =C79 -> 27146877
C81: Sensitivity Analysis - Construction Cost
C82: Construction Cost | D82: 25133939 | E82: 25133939 | F82: 25133939 | G82: =E59 -> 25646877 | H82: =G82*(1+$D$88) -> 26159815 | I82: =H82*(1+$D$88) -> 26683011 | J82: =I82*(1+$D$88) -> 27216671
C83: IRR - Levered (Deal Level) | D83: =INDEX($D$73:$D$79,MATCH(D$63,$C$73:$C$79,0),) -> 0 | E83: =INDEX($D$73:$D$79,MATCH(E$63,$C$73:$C$79,0),) -> 0 | F83: =INDEX($D$73:$D$79,MATCH(F$63,$C$73:$C$79,0),) -> 0 | G83: =INDEX($D$73:$D$79,MATCH(G$63,$C$73:$C$79,0),) -> 0 | H83: =INDEX($D$73:$D$79,MATCH(H$63,$C$73:$C$79,0),) -> 0 | I83: =INDEX($D$73:$D$79,MATCH(I$63,$C$73:$C$79,0),) -> 0 | J83: =INDEX($D$73:$D$79,MATCH(J$63,$C$73:$C$79,0),) -> 0
C84: IRR - Levered (Project Level) | D84: =INDEX($F$73:$F$79,MATCH(D$63,$C$73:$C$79,0),) -> 0 | E84: =INDEX($F$73:$F$79,MATCH(E$63,$C$73:$C$79,0),) -> 0 | F84: =INDEX($F$73:$F$79,MATCH(F$63,$C$73:$C$79,0),) -> 0 | G84: =INDEX($F$73:$F$79,MATCH(G$63,$C$73:$C$79,0),) -> 0 | H84: =INDEX($F$73:$F$79,MATCH(H$63,$C$73:$C$79,0),) -> 0 | I84: =INDEX($F$73:$F$79,MATCH(I$63,$C$73:$C$79,0),) -> 0 | J84: =INDEX($F$73:$F$79,MATCH(J$63,$C$73:$C$79,0),) -> 0
C85: IRR - Unlevered | D85: =INDEX($H$73:$H$79,MATCH(D$63,$C$73:$C$79,0),) -> 0 | E85: =INDEX($H$73:$H$79,MATCH(E$63,$C$73:$C$79,0),) -> 0 | F85: =INDEX($H$73:$H$79,MATCH(F$63,$C$73:$C$79,0),) -> 0 | G85: =INDEX($H$73:$H$79,MATCH(G$63,$C$73:$C$79,0),) -> 0 | H85: =INDEX($H$73:$H$79,MATCH(H$63,$C$73:$C$79,0),) -> 0 | I85: =INDEX($H$73:$H$79,MATCH(I$63,$C$73:$C$79,0),) -> 0 | J85: =INDEX($H$73:$H$79,MATCH(J$63,$C$73:$C$79,0),) -> 0
C86: Equity Multiple: | D86: =INDEX($J$73:$J$79,MATCH(D$63,$C$73:$C$79,0),) -> 0 | E86: =INDEX($J$73:$J$79,MATCH(E$63,$C$73:$C$79,0),) -> 0 | F86: =INDEX($J$73:$J$79,MATCH(F$63,$C$73:$C$79,0),) -> 0 | G86: =INDEX($J$73:$J$79,MATCH(G$63,$C$73:$C$79,0),) -> 0 | H86: =INDEX($J$73:$J$79,MATCH(H$63,$C$73:$C$79,0),) -> 0 | I86: =INDEX($J$73:$J$79,MATCH(I$63,$C$73:$C$79,0),) -> 0 | J86: =INDEX($J$73:$J$79,MATCH(J$63,$C$73:$C$79,0),) -> 0
C87: Yield on Cost | D87: =INDEX($L$73:$L$79,MATCH(D$63,$C$73:$C$79,0),) -> 0 | E87: =INDEX($L$73:$L$79,MATCH(E$63,$C$73:$C$79,0),) -> 0 | F87: =INDEX($L$73:$L$79,MATCH(F$63,$C$73:$C$79,0),) -> 0 | G87: =INDEX($L$73:$L$79,MATCH(G$63,$C$73:$C$79,0),) -> 0 | H87: =INDEX($L$73:$L$79,MATCH(H$63,$C$73:$C$79,0),) -> 0 | I87: =INDEX($L$73:$L$79,MATCH(I$63,$C$73:$C$79,0),) -> 0 | J87: =INDEX($L$73:$L$79,MATCH(J$63,$C$73:$C$79,0),) -> 0
C88: Construction Price Sensitivity | D88: 0.02
D90: IRR Levered | F90: IRR Project | H90: IRR Unlevered | J90: Equity Multiple | L90: Yield on Cost
D91: =UW!#REF! -> #REF! | F91: =UW!J36 -> 48 | H91: =UW!J37 -> 0.01 | J91: =UW!J38 -> 0.0025 | L91: =UW!J40 -> 0.1
C92: =D82 -> 25133939 | E92: =$C92 -> 25133939 | G92: =C92 -> 25133939 | I92: =$C92 -> 25133939 | K92: =C92 -> 25133939
C93: =E82 -> 25133939 | E93: =$C93 -> 25133939 | G93: =C93 -> 25133939 | I93: =$C93 -> 25133939 | K93: =C93 -> 25133939
C94: =F82 -> 25133939 | E94: =$C94 -> 25133939 | G94: =C94 -> 25133939 | I94: =$C94 -> 25133939 | K94: =C94 -> 25133939
C95: 25646877 | E95: =$C95 -> 25646877 | G95: =C95 -> 25646877 | I95: =$C95 -> 25646877 | K95: =C95 -> 25646877
C96: =H82 -> 26159815 | E96: =$C96 -> 26159815 | G96: =C96 -> 26159815 | I96: =$C96 -> 26159815 | K96: =C96 -> 26159815
C97: =I82 -> 26683011 | E97: =$C97 -> 26683011 | G97: =C97 -> 26683011 | I97: =$C97 -> 26683011 | K97: =C97 -> 26683011
C98: =J82 -> 27216671 | E98: =$C98 -> 27216671 | G98: =C98 -> 27216671 | I98: =$C98 -> 27216671 | K98: =C98 -> 27216671

Sheet Equity | Debt
F2: =UW!E607 -> 46142 | G2: =UW!F607 -> 46173 | H2: =UW!G607 -> 46203 | I2: =UW!H607 -> 46234 | J2: =UW!I607 -> 46265 | K2: =UW!J607 -> 46295 | L2: =UW!K607 -> 46326 | M2: =UW!L607 -> 46356 | ... CK2: =UW!CJ607 -> 48669
B3: Minimum | C3: Maximum | D3: Month 1-36 Maximum | F3: =UW!E612 -> 1 | G3: =UW!F612 -> 2 | H3: =UW!G612 -> 3 | I3: =UW!H612 -> 4 | J3: =UW!I612 -> 5 | K3: =UW!J612 -> 6 | L3: =UW!K612 -> 7 | M3: =UW!L612 -> 8 | ... CK3: =UW!CJ612 -> 84
B4: =MIN(F4:CK4) -> #DIV/0! | C4: =MAX(F4:CK4) -> #DIV/0! | D4: =MAX(F4:AO4) -> #DIV/0! | E4: Equity | F4: =UW!E760 -> #DIV/0! | G4: =UW!F760 -> #DIV/0! | H4: =UW!G760 -> #DIV/0! | I4: =UW!H760 -> #DIV/0! | J4: =UW!I760 -> #DIV/0! | K4: =UW!J760 -> #DIV/0! | L4: =UW!K760 -> #DIV/0! | M4: =UW!L760 -> #DIV/0! | ... CK4: =UW!CJ760 -> #DIV/0!
B5: =MIN(F5:CK5) -> #DIV/0! | C5: =MAX(F5:CK5) -> #DIV/0! | D5: =MAX(F5:AO5) -> #DIV/0! | E5: Debt | F5: =UW!E761 -> #DIV/0! | G5: =UW!F761 -> #DIV/0! | H5: =UW!G761 -> #DIV/0! | I5: =UW!H761 -> #DIV/0! | J5: =UW!I761 -> #DIV/0! | K5: =UW!J761 -> #DIV/0! | L5: =UW!K761 -> #DIV/0! | M5: =UW!L761 -> #DIV/0! | ... CK5: =UW!CJ761 -> 0
B6: =MIN(F6:CK6) -> #DIV/0! | C6: =MAX(F6:CK6) -> #DIV/0! | D6: =MAX(F6:AO6) -> #DIV/0! | E6: LVR | F6: =F5/MAX(Val!D98,Val!D99) -> #DIV/0! | G6: =G5/MAX(Val!E98,Val!E99) -> #DIV/0! | H6: =H5/MAX(Val!F98,Val!F99) -> #DIV/0! | I6: =I5/MAX(Val!G98,Val!G99) -> #DIV/0! | J6: =J5/MAX(Val!H98,Val!H99) -> #DIV/0! | K6: =K5/MAX(Val!I98,Val!I99) -> #DIV/0! | L6: =L5/MAX(Val!J98,Val!J99) -> #DIV/0! | M6: =M5/MAX(Val!K98,Val!K99) -> #DIV/0! | ... CK6: =CK5/MAX(Val!CI98,Val!CI99) -> #DIV/0!
B7: =MIN(F7:CK7) -> 3077.3891 | C7: =MAX(F7:CK7) -> 3230.654 | D7: =MAX(F7:AO7) -> 3077.3891 | E7: ICR | F7: =UW!E722 -> - | G7: =UW!F722 -> - | H7: =UW!G722 -> - | I7: =UW!H722 -> - | J7: =UW!I722 -> - | K7: =UW!J722 -> - | L7: =UW!K722 -> - | M7: =UW!L722 -> - | ... CK7: =UW!CJ722 -> -
B8: =MIN(F8:CK8) -> #DIV/0! | C8: =MAX(F8:CK8) -> #DIV/0! | D8: =MAX(F8:AO8) -> #DIV/0! | E8: Interest PMT | F8: =-UW!E719 -> 0 | G8: =-UW!F719 -> #DIV/0! | H8: =-UW!G719 -> #DIV/0! | I8: =-UW!H719 -> #DIV/0! | J8: =-UW!I719 -> #DIV/0! | K8: =-UW!J719 -> #DIV/0! | L8: =-UW!K719 -> #DIV/0! | M8: =-UW!L719 -> #DIV/0! | ... CK8: =-UW!CJ719 -> 0 | CL8: x
B9: =MIN(F9:CK9) -> 0.0605 | C9: =MAX(F9:CK9) -> 0.0605 | D9: =MAX(F9:AO9) -> 0.0605 | E9: Interst Rate | F9: =IF(F3<=UW!$D$863,UW!E864+UW!$D$792,UW!E863) -> 0.0605 | G9: =IF(G3<=UW!$D$863,UW!F864+UW!$D$792,UW!F863) -> 0.0605 | H9: =IF(H3<=UW!$D$863,UW!G864+UW!$D$792,UW!G863) -> 0.0605 | I9: =IF(I3<=UW!$D$863,UW!H864+UW!$D$792,UW!H863) -> 0.0605 | J9: =IF(J3<=UW!$D$863,UW!I864+UW!$D$792,UW!I863) -> 0.0605 | K9: =IF(K3<=UW!$D$863,UW!J864+UW!$D$792,UW!J863) -> 0.0605 | L9: =IF(L3<=UW!$D$863,UW!K864+UW!$D$792,UW!K863) -> 0.0605 | M9: =IF(M3<=UW!$D$863,UW!L864+UW!$D$792,UW!L863) -> 0.0605 | ... CK9: =IF(CK3<=UW!$D$863,UW!CJ864+UW!$D$792,UW!CJ863) -> 0.0605 | CL9: x
B10: =MIN(F10:CK10) -> -3307.0063 | C10: =MAX(F10:CK10) -> 0 | D10: =MAX(F10:AO10) -> -1061.0255 | E10: DCF Value | F10: =Val!D27 -> -3307.0063 | G10: =Val!E27 -> -3252.9647 | H10: =Val!F27 -> -3198.4727 | I10: =Val!G27 -> -3143.5266 | J10: =Val!H27 -> -3088.1227 | K10: =Val!I27 -> -3032.257 | L10: =Val!J27 -> -2975.9259 | M10: =Val!K27 -> -2919.1252 | ... CK10: =Val!CI27 -> 0 | CL10: x
B11: =MIN(F11:CK11) -> 0 | C11: =MAX(F11:CK11) -> 0 | D11: =MAX(F11:AO11) -> 0 | E11: Cap Value | F11: =Val!D28 -> 0 | G11: =Val!E28 -> 0 | H11: =Val!F28 -> 0 | I11: =Val!G28 -> 0 | J11: =Val!H28 -> 0 | K11: =Val!I28 -> 0 | L11: =Val!J28 -> 0 | M11: =Val!K28 -> 0 | ... CK11: =Val!CI28 -> 0 | CL11: x
CL12: x

Sheet Annual Bdgt
B2: Property Description
B3: =UW!C7 -> Property Name | C3: =UW!D7 -> 0
B4: =UW!C8 -> Street Address | C4: =UW!D8 -> 0
B5: =UW!C9 -> City | C5: =UW!D9 -> 0
B6: =UW!C10 -> State, Postal | C6: =UW!D10 -> 0
B7: =UW!C12 -> Parcel Size | C7: =UW!D12*10000 -> 0
B8: =UW!C13 -> Investment Type | C8: =UW!D13 -> Existing
B9: =UW!I9 -> Offer Price | C9: =UW!J9 -> 0
B10: =UW!C25 -> Occupancy | C10: =UW!D20 -> 0
B11: =UW!C26 -> Asking Rents | C11: =UW!D26 -> #DIV/0!
B12: =UW!I11 -> Projected Closing Date | C12: =UW!I12 -> 46112
B15: =IF(ISBLANK(UW!C217),"",UW!C217) -> Phys. Occ. As of Year End (Storage): | C15: =UW!D218 -> #DIV/0! | D15: =IF(ISBLANK(UW!E217),"",UW!E217) -> #DIV/0! | E15: =IF(ISBLANK(UW!F217),"",UW!F217) -> #DIV/0! | F15: =IF(ISBLANK(UW!G217),"",UW!G217) -> #DIV/0! | G15: =IF(ISBLANK(UW!H217),"",UW!H217) -> #DIV/0! | H15: =IF(ISBLANK(UW!I217),"",UW!I217) -> #DIV/0! | I15: =IF(ISBLANK(UW!J217),"",UW!J217) -> #DIV/0! | J15: =IF(ISBLANK(UW!K217),"",UW!K217) -> #DIV/0! | K15: =IF(ISBLANK(UW!L217),"",UW!L217) -> #DIV/0! | ... N15: =IF(ISBLANK(UW!O217),"",UW!O217) -> #DIV/0!
B16: =IF(ISBLANK(UW!C234),"",UW!C234) -> Phys. Occ. As of Year End (RV & Parking): | C16: =UW!D235 -> 0 | D16: =IF(ISBLANK(UW!E234),"",UW!E234) -> 0 | E16: =IF(ISBLANK(UW!F234),"",UW!F234) -> 0 | F16: =IF(ISBLANK(UW!G234),"",UW!G234) -> 0 | G16: =IF(ISBLANK(UW!H234),"",UW!H234) -> 0 | H16: =IF(ISBLANK(UW!I234),"",UW!I234) -> 0 | I16: =IF(ISBLANK(UW!J234),"",UW!J234) -> 0 | J16: =IF(ISBLANK(UW!K234),"",UW!K234) -> 0 | K16: =IF(ISBLANK(UW!L234),"",UW!L234) -> 0 | ... N16: =IF(ISBLANK(UW!O234),"",UW!O234) -> 0
B17: =IF(ISBLANK(UW!C251),"",UW!C251) -> Phys. Occ. As of Year End (Warehouse): | C17: =UW!D252 -> 0 | D17: =IF(ISBLANK(UW!E251),"",UW!E251) -> 0 | E17: =IF(ISBLANK(UW!F251),"",UW!F251) -> 0 | F17: =IF(ISBLANK(UW!G251),"",UW!G251) -> 0 | G17: =IF(ISBLANK(UW!H251),"",UW!H251) -> 0 | H17: =IF(ISBLANK(UW!I251),"",UW!I251) -> 0 | I17: =IF(ISBLANK(UW!J251),"",UW!J251) -> 0 | J17: =IF(ISBLANK(UW!K251),"",UW!K251) -> 0 | K17: =IF(ISBLANK(UW!L251),"",UW!L251) -> 0 | ... N17: =IF(ISBLANK(UW!O251),"",UW!O251) -> 0
B18: =IF(ISBLANK(UW!C268),"",UW!C268) -> Phys. Occ. As of Year End (Office): | C18: =UW!D269 -> 0 | D18: =IF(ISBLANK(UW!E268),"",UW!E268) -> 0 | E18: =IF(ISBLANK(UW!F268),"",UW!F268) -> 0 | F18: =IF(ISBLANK(UW!G268),"",UW!G268) -> 0 | G18: =IF(ISBLANK(UW!H268),"",UW!H268) -> 0 | H18: =IF(ISBLANK(UW!I268),"",UW!I268) -> 0 | I18: =IF(ISBLANK(UW!J268),"",UW!J268) -> 0 | J18: =IF(ISBLANK(UW!K268),"",UW!K268) -> 0 | K18: =IF(ISBLANK(UW!L268),"",UW!L268) -> 0 | ... N18: =IF(ISBLANK(UW!O268),"",UW!O268) -> 0
B19: =IF(ISBLANK(UW!C285),"",UW!C285) -> Phys. Occ. As of Year End (Expansion): | C19: =UW!D286 -> 0 | D19: =IF(ISBLANK(UW!E285),"",UW!E285) -> 0 | E19: =IF(ISBLANK(UW!F285),"",UW!F285) -> 0 | F19: =IF(ISBLANK(UW!G285),"",UW!G285) -> 0 | G19: =IF(ISBLANK(UW!H285),"",UW!H285) -> 0 | H19: =IF(ISBLANK(UW!I285),"",UW!I285) -> 0 | I19: =IF(ISBLANK(UW!J285),"",UW!J285) -> 0 | J19: =IF(ISBLANK(UW!K285),"",UW!K285) -> 0 | K19: =IF(ISBLANK(UW!L285),"",UW!L285) -> 0 | ... N19: =IF(ISBLANK(UW!O285),"",UW!O285) -> 0
B20: =IF(ISBLANK(UW!C222),"",UW!C222) -> Revenue | C20: =IF(ISBLANK(UW!D222),"",UW!D222) -> Baseline | D20: =IF(ISBLANK(UW!E222),"",UW!E222) -> 1 | E20: =IF(ISBLANK(UW!F222),"",UW!F222) -> 2 | F20: =IF(ISBLANK(UW!G222),"",UW!G222) -> 3 | G20: =IF(ISBLANK(UW!H222),"",UW!H222) -> 4 | H20: =IF(ISBLANK(UW!I222),"",UW!I222) -> 5 | I20: =IF(ISBLANK(UW!J222),"",UW!J222) -> 6 | ... N20: =IF(ISBLANK(UW!O222),"",UW!O222) -> 11
B21: =UW!C229 -> Net Rental Income (Storage) | C21: =IF(ISBLANK(UW!D229),"",UW!D229) -> 0 | D21: =IF(ISBLANK(UW!E229),"",UW!E229) -> 0 | E21: =IF(ISBLANK(UW!F229),"",UW!F229) -> 0 | F21: =IF(ISBLANK(UW!G229),"",UW!G229) -> 0 | G21: =IF(ISBLANK(UW!H229),"",UW!H229) -> 0 | H21: =IF(ISBLANK(UW!I229),"",UW!I229) -> 0 | I21: =IF(ISBLANK(UW!J229),"",UW!J229) -> 0 | J21: =IF(ISBLANK(UW!K229),"",UW!K229) -> 0 | ... N21: =IF(ISBLANK(UW!O229),"",UW!O229) -> 0
B22: =UW!C246 -> Net Rental Income (RV & Parking) | C22: =IF(ISBLANK(UW!D246),"",UW!D246) -> 0 | D22: =IF(ISBLANK(UW!E246),"",UW!E246) -> 0 | E22: =IF(ISBLANK(UW!F246),"",UW!F246) -> 0 | F22: =IF(ISBLANK(UW!G246),"",UW!G246) -> 0 | G22: =IF(ISBLANK(UW!H246),"",UW!H246) -> 0 | H22: =IF(ISBLANK(UW!I246),"",UW!I246) -> 0 | I22: =IF(ISBLANK(UW!J246),"",UW!J246) -> 0 | J22: =IF(ISBLANK(UW!K246),"",UW!K246) -> 0 | ... N22: =IF(ISBLANK(UW!O246),"",UW!O246) -> 0
B23: =UW!C263 -> Net Rental Income (Warehouse) | C23: =IF(ISBLANK(UW!D263),"",UW!D263) -> 0 | D23: =IF(ISBLANK(UW!E263),"",UW!E263) -> 0 | E23: =IF(ISBLANK(UW!F263),"",UW!F263) -> 0 | F23: =IF(ISBLANK(UW!G263),"",UW!G263) -> 0 | G23: =IF(ISBLANK(UW!H263),"",UW!H263) -> 0 | H23: =IF(ISBLANK(UW!I263),"",UW!I263) -> 0 | I23: =IF(ISBLANK(UW!J263),"",UW!J263) -> 0 | J23: =IF(ISBLANK(UW!K263),"",UW!K263) -> 0 | ... N23: =IF(ISBLANK(UW!O263),"",UW!O263) -> 0
B24: =UW!C280 -> Net Rental Income (Office) | C24: =IF(ISBLANK(UW!D280),"",UW!D280) -> 0 | D24: =IF(ISBLANK(UW!E280),"",UW!E280) -> 0 | E24: =IF(ISBLANK(UW!F280),"",UW!F280) -> 0 | F24: =IF(ISBLANK(UW!G280),"",UW!G280) -> 0 | G24: =IF(ISBLANK(UW!H280),"",UW!H280) -> 0 | H24: =IF(ISBLANK(UW!I280),"",UW!I280) -> 0 | I24: =IF(ISBLANK(UW!J280),"",UW!J280) -> 0 | J24: =IF(ISBLANK(UW!K280),"",UW!K280) -> 0 | ... N24: =IF(ISBLANK(UW!O280),"",UW!O280) -> 0
B25: =UW!C297 -> Net Rental Income (Expansion) | C25: =IF(ISBLANK(UW!D297),"",UW!D297) -> 0 | D25: =IF(ISBLANK(UW!E297),"",UW!E297) -> 0 | E25: =IF(ISBLANK(UW!F297),"",UW!F297) -> 0 | F25: =IF(ISBLANK(UW!G297),"",UW!G297) -> 0 | G25: =IF(ISBLANK(UW!H297),"",UW!H297) -> 0 | H25: =IF(ISBLANK(UW!I297),"",UW!I297) -> 0 | I25: =IF(ISBLANK(UW!J297),"",UW!J297) -> 0 | J25: =IF(ISBLANK(UW!K297),"",UW!K297) -> 0 | ... N25: =IF(ISBLANK(UW!O297),"",UW!O297) -> 0
B27: =UW!C313 -> Net Rental Income (Total) | C27: =IF(ISBLANK(UW!D313),"",UW!D313) -> 0 | D27: =IF(ISBLANK(UW!E313),"",UW!E313) -> 0 | E27: =IF(ISBLANK(UW!F313),"",UW!F313) -> 0 | F27: =IF(ISBLANK(UW!G313),"",UW!G313) -> 0 | G27: =IF(ISBLANK(UW!H313),"",UW!H313) -> 0 | H27: =IF(ISBLANK(UW!I313),"",UW!I313) -> 0 | I27: =IF(ISBLANK(UW!J313),"",UW!J313) -> 0 | J27: =IF(ISBLANK(UW!K313),"",UW!K313) -> 0 | ... N27: =IF(ISBLANK(UW!O313),"",UW!O313) -> 0
B28: =IF(ISBLANK(UW!C314),"",UW!C314) -> Net Yield PSM (Year End) | C28: =IF(ISBLANK(UW!D314),"",UW!D314) -> 0 | D28: =IF(ISBLANK(UW!E314),"",UW!E314) -> 0 | E28: =IF(ISBLANK(UW!F314),"",UW!F314) -> 0 | F28: =IF(ISBLANK(UW!G314),"",UW!G314) -> 0 | G28: =IF(ISBLANK(UW!H314),"",UW!H314) -> 0 | H28: =IF(ISBLANK(UW!I314),"",UW!I314) -> 0 | I28: =IF(ISBLANK(UW!J314),"",UW!J314) -> 0 | ... N28: =IF(ISBLANK(UW!O314),"",UW!O314) -> 0
B30: =IF(ISBLANK(UW!C317),"",UW!C317) -> Admin & Late Fees (% of Net Rental Inc.) | C30: =IF(ISBLANK(UW!D317),"",UW!D317) -> 0 | D30: =IF(ISBLANK(UW!E317),"",UW!E317) -> 0 | E30: =IF(ISBLANK(UW!F317),"",UW!F317) -> 0 | F30: =IF(ISBLANK(UW!G317),"",UW!G317) -> 0 | G30: =IF(ISBLANK(UW!H317),"",UW!H317) -> 0 | H30: =IF(ISBLANK(UW!I317),"",UW!I317) -> 0 | I30: =IF(ISBLANK(UW!J317),"",UW!J317) -> 0 | ... N30: =IF(ISBLANK(UW!O317),"",UW!O317) -> 0
B31: =IF(ISBLANK(UW!C318),"",UW!C318) -> Merchandise Sales (% of Net Rental Inc.) | C31: =IF(ISBLANK(UW!D318),"",UW!D318) -> 0 | D31: =IF(ISBLANK(UW!E318),"",UW!E318) -> 0 | E31: =IF(ISBLANK(UW!F318),"",UW!F318) -> 0 | F31: =IF(ISBLANK(UW!G318),"",UW!G318) -> 0 | G31: =IF(ISBLANK(UW!H318),"",UW!H318) -> 0 | H31: =IF(ISBLANK(UW!I318),"",UW!I318) -> 0 | I31: =IF(ISBLANK(UW!J318),"",UW!J318) -> 0 | ... N31: =IF(ISBLANK(UW!O318),"",UW!O318) -> 0
B32: =IF(ISBLANK(UW!C319),"",UW!C319) -> Tenant Insurance | C32: =IF(ISBLANK(UW!D319),"",UW!D319) -> 0 | D32: =IF(ISBLANK(UW!E319),"",UW!E319) -> 0 | E32: =IF(ISBLANK(UW!F319),"",UW!F319) -> 0 | F32: =IF(ISBLANK(UW!G319),"",UW!G319) -> 0 | G32: =IF(ISBLANK(UW!H319),"",UW!H319) -> 0 | H32: =IF(ISBLANK(UW!I319),"",UW!I319) -> 0 | I32: =IF(ISBLANK(UW!J319),"",UW!J319) -> 0 | ... N32: =IF(ISBLANK(UW!O319),"",UW!O319) -> 0
B33: =IF(ISBLANK(UW!C320),"",UW!C320) -> Trailer Hire | C33: =IF(ISBLANK(UW!D320),"",UW!D320) -> 0 | D33: =IF(ISBLANK(UW!E320),"",UW!E320) -> 0 | E33: =IF(ISBLANK(UW!F320),"",UW!F320) -> 0 | F33: =IF(ISBLANK(UW!G320),"",UW!G320) -> 0 | G33: =IF(ISBLANK(UW!H320),"",UW!H320) -> 0 | H33: =IF(ISBLANK(UW!I320),"",UW!I320) -> 0 | I33: =IF(ISBLANK(UW!J320),"",UW!J320) -> 0 | ... N33: =IF(ISBLANK(UW!O320),"",UW!O320) -> 0
B34: =IF(ISBLANK(UW!C321),"",UW!C321) -> Motor Vehicle Hire | C34: =IF(ISBLANK(UW!D321),"",UW!D321) -> 0 | D34: =IF(ISBLANK(UW!E321),"",UW!E321) -> 0 | E34: =IF(ISBLANK(UW!F321),"",UW!F321) -> 0 | F34: =IF(ISBLANK(UW!G321),"",UW!G321) -> 0 | G34: =IF(ISBLANK(UW!H321),"",UW!H321) -> 0 | H34: =IF(ISBLANK(UW!I321),"",UW!I321) -> 0 | I34: =IF(ISBLANK(UW!J321),"",UW!J321) -> 0 | ... N34: =IF(ISBLANK(UW!O321),"",UW!O321) -> 0
B35: =IF(ISBLANK(UW!C322),"",UW!C322) -> Cell Tower | C35: =IF(ISBLANK(UW!D322),"",UW!D322) -> 0 | D35: =IF(ISBLANK(UW!E322),"",UW!E322) -> 0 | E35: =IF(ISBLANK(UW!F322),"",UW!F322) -> 0 | F35: =IF(ISBLANK(UW!G322),"",UW!G322) -> 0 | G35: =IF(ISBLANK(UW!H322),"",UW!H322) -> 0 | H35: =IF(ISBLANK(UW!I322),"",UW!I322) -> 0 | I35: =IF(ISBLANK(UW!J322),"",UW!J322) -> 0 | ... N35: =IF(ISBLANK(UW!O322),"",UW!O322) -> 0
B36: =IF(ISBLANK(UW!C323),"",UW!C323) -> Misc II (% Net Rental Inc.) | C36: =IF(ISBLANK(UW!D323),"",UW!D323) -> 0 | D36: =IF(ISBLANK(UW!E323),"",UW!E323) -> 0 | E36: =IF(ISBLANK(UW!F323),"",UW!F323) -> 0 | F36: =IF(ISBLANK(UW!G323),"",UW!G323) -> 0 | G36: =IF(ISBLANK(UW!H323),"",UW!H323) -> 0 | H36: =IF(ISBLANK(UW!I323),"",UW!I323) -> 0 | I36: =IF(ISBLANK(UW!J323),"",UW!J323) -> 0 | ... N36: =IF(ISBLANK(UW!O323),"",UW!O323) -> 0
B37: =IF(ISBLANK(UW!C324),"",UW!C324) -> Misc II (% Net Rental Inc.) | C37: =IF(ISBLANK(UW!D324),"",UW!D324) -> 0 | D37: =IF(ISBLANK(UW!E324),"",UW!E324) -> 0 | E37: =IF(ISBLANK(UW!F324),"",UW!F324) -> 0 | F37: =IF(ISBLANK(UW!G324),"",UW!G324) -> 0 | G37: =IF(ISBLANK(UW!H324),"",UW!H324) -> 0 | H37: =IF(ISBLANK(UW!I324),"",UW!I324) -> 0 | I37: =IF(ISBLANK(UW!J324),"",UW!J324) -> 0 | ... N37: =IF(ISBLANK(UW!O324),"",UW!O324) -> 0
B38: =IF(ISBLANK(UW!C325),"",UW!C325) -> Other Income | C38: =IF(ISBLANK(UW!D325),"",UW!D325) -> 0 | D38: =IF(ISBLANK(UW!E325),"",UW!E325) -> 0 | E38: =IF(ISBLANK(UW!F325),"",UW!F325) -> 0 | F38: =IF(ISBLANK(UW!G325),"",UW!G325) -> 0 | G38: =IF(ISBLANK(UW!H325),"",UW!H325) -> 0 | H38: =IF(ISBLANK(UW!I325),"",UW!I325) -> 0 | I38: =IF(ISBLANK(UW!J325),"",UW!J325) -> 0 | ... N38: =IF(ISBLANK(UW!O325),"",UW!O325) -> 0
B39: =IF(ISBLANK(UW!C326),"",UW!C326) -> Outgoings Recoveries | C39: =IF(ISBLANK(UW!D326),"",UW!D326) -> 0 | D39: =IF(ISBLANK(UW!E326),"",UW!E326) -> 0 | E39: =IF(ISBLANK(UW!F326),"",UW!F326) -> 0 | F39: =IF(ISBLANK(UW!G326),"",UW!G326) -> 0 | G39: =IF(ISBLANK(UW!H326),"",UW!H326) -> 0 | H39: =IF(ISBLANK(UW!I326),"",UW!I326) -> 0 | I39: =IF(ISBLANK(UW!J326),"",UW!J326) -> 0 | ... N39: =IF(ISBLANK(UW!O326),"",UW!O326) -> 0
B40: =IF(ISBLANK(UW!C327),"",UW!C327) -> Misc III | C40: =IF(ISBLANK(UW!D327),"",UW!D327) -> 0 | D40: =IF(ISBLANK(UW!E327),"",UW!E327) -> 0 | E40: =IF(ISBLANK(UW!F327),"",UW!F327) -> 0 | F40: =IF(ISBLANK(UW!G327),"",UW!G327) -> 0 | G40: =IF(ISBLANK(UW!H327),"",UW!H327) -> 0 | H40: =IF(ISBLANK(UW!I327),"",UW!I327) -> 0 | I40: =IF(ISBLANK(UW!J327),"",UW!J327) -> 0 | ... N40: =IF(ISBLANK(UW!O327),"",UW!O327) -> 0
B41: =IF(ISBLANK(UW!C328),"",UW!C328) -> Total Revenue | C41: =IF(ISBLANK(UW!D328),"",UW!D328) -> 0 | D41: =IF(ISBLANK(UW!E328),"",UW!E328) -> 0 | E41: =IF(ISBLANK(UW!F328),"",UW!F328) -> 0 | F41: =IF(ISBLANK(UW!G328),"",UW!G328) -> 0 | G41: =IF(ISBLANK(UW!H328),"",UW!H328) -> 0 | H41: =IF(ISBLANK(UW!I328),"",UW!I328) -> 0 | I41: =IF(ISBLANK(UW!J328),"",UW!J328) -> 0 | ... N41: =IF(ISBLANK(UW!O328),"",UW!O328) -> 0
... B52: =IF(ISBLANK(UW!C339),"",UW!C339) -> RV GPR | C52: =IF(ISBLANK(UW!D339),"",UW!D339) -> 0 | D52: =IF(ISBLANK(UW!E339),"",UW!E339) -> 0 | E52: =IF(ISBLANK(UW!F339),"",UW!F339) -> 0 | F52: =IF(ISBLANK(UW!G339),"",UW!G339) -> 0 | G52: =IF(ISBLANK(UW!H339),"",UW!H339) -> 0 | H52: =IF(ISBLANK(UW!I339),"",UW!I339) -> 0 | I52: =IF(ISBLANK(UW!J339),"",UW!J339) -> 0 | ... N52: =IF(ISBLANK(UW!O339),"",UW!O339) -> 0
B55: =IF(ISBLANK(UW!C368),"",UW!C368) -> Expenses | C55: =IF(ISBLANK(UW!D368),"",UW!D368) -> Baseline | D55: =IF(ISBLANK(UW!E368),"",UW!E368) -> 1 | E55: =IF(ISBLANK(UW!F368),"",UW!F368) -> 2 | F55: =IF(ISBLANK(UW!G368),"",UW!G368) -> 3 | G55: =IF(ISBLANK(UW!H368),"",UW!H368) -> 4 | H55: =IF(ISBLANK(UW!I368),"",UW!I368) -> 5 | I55: =IF(ISBLANK(UW!J368),"",UW!J368) -> 6 | ... N55: =IF(ISBLANK(UW!O368),"",UW!O368) -> 11
B56: =IF(ISBLANK(UW!C369),"",UW!C369) -> Advertising | C56: =IF(ISBLANK(UW!D369),"",UW!D369) -> 66000 | D56: =IF(ISBLANK(UW!E369),"",UW!E369) -> 0 | E56: =IF(ISBLANK(UW!F369),"",UW!F369) -> 0 | F56: =IF(ISBLANK(UW!G369),"",UW!G369) -> 0 | G56: =IF(ISBLANK(UW!H369),"",UW!H369) -> 0 | H56: =IF(ISBLANK(UW!I369),"",UW!I369) -> 0 | I56: =IF(ISBLANK(UW!J369),"",UW!J369) -> 0 | ... N56: =IF(ISBLANK(UW!O369),"",UW!O369) -> 0
B57: =IF(ISBLANK(UW!C370),"",UW!C370) -> Bad Debt (% of Net Rental Inc.) | C57: =IF(ISBLANK(UW!D370),"",UW!D370) -> 0 | D57: =IF(ISBLANK(UW!E370),"",UW!E370) -> 0 | E57: =IF(ISBLANK(UW!F370),"",UW!F370) -> 0 | F57: =IF(ISBLANK(UW!G370),"",UW!G370) -> 0 | G57: =IF(ISBLANK(UW!H370),"",UW!H370) -> 0 | H57: =IF(ISBLANK(UW!I370),"",UW!I370) -> 0 | I57: =IF(ISBLANK(UW!J370),"",UW!J370) -> 0 | ... N57: =IF(ISBLANK(UW!O370),"",UW!O370) -> 0
B58: =IF(ISBLANK(UW!C371),"",UW!C371) -> Banking Fees | C58: =IF(ISBLANK(UW!D371),"",UW!D371) -> 0 | D58: =IF(ISBLANK(UW!E371),"",UW!E371) -> 979.2 | E58: =IF(ISBLANK(UW!F371),"",UW!F371) -> 998.784 | F58: =IF(ISBLANK(UW!G371),"",UW!G371) -> 1018.7597 | G58: =IF(ISBLANK(UW!H371),"",UW!H371) -> 1039.1349 | H58: =IF(ISBLANK(UW!I371),"",UW!I371) -> 1059.9176 | I58: =IF(ISBLANK(UW!J371),"",UW!J371) -> 1081.1159 | ... N58: =IF(ISBLANK(UW!O371),"",UW!O371) -> 1193.6393
B59: =IF(ISBLANK(UW!C372),"",UW!C372) -> Electricity | C59: =IF(ISBLANK(UW!D372),"",UW!D372) -> 0 | D59: =IF(ISBLANK(UW!E372),"",UW!E372) -> 0 | E59: =IF(ISBLANK(UW!F372),"",UW!F372) -> 0 | F59: =IF(ISBLANK(UW!G372),"",UW!G372) -> 0 | G59: =IF(ISBLANK(UW!H372),"",UW!H372) -> 0 | H59: =IF(ISBLANK(UW!I372),"",UW!I372) -> 0 | I59: =IF(ISBLANK(UW!J372),"",UW!J372) -> 0 | ... N59: =IF(ISBLANK(UW!O372),"",UW!O372) -> 0
B60: =IF(ISBLANK(UW!C373),"",UW!C373) -> Employee Wages | C60: =IF(ISBLANK(UW!D373),"",UW!D373) -> 38400 | D60: =IF(ISBLANK(UW!E373),"",UW!E373) -> 0 | E60: =IF(ISBLANK(UW!F373),"",UW!F373) -> 0 | F60: =IF(ISBLANK(UW!G373),"",UW!G373) -> 0 | G60: =IF(ISBLANK(UW!H373),"",UW!H373) -> 0 | H60: =IF(ISBLANK(UW!I373),"",UW!I373) -> 0 | I60: =IF(ISBLANK(UW!J373),"",UW!J373) -> 0 | ... N60: =IF(ISBLANK(UW!O373),"",UW!O373) -> 0
B61: =IF(ISBLANK(UW!C374),"",UW!C374) -> StoreLocal Tech Fee | C61: =IF(ISBLANK(UW!D374),"",UW!D374) -> 20203.2 | D61: =IF(ISBLANK(UW!E374),"",UW!E374) -> 0 | E61: =IF(ISBLANK(UW!F374),"",UW!F374) -> 0 | F61: =IF(ISBLANK(UW!G374),"",UW!G374) -> 0 | G61: =IF(ISBLANK(UW!H374),"",UW!H374) -> 0 | H61: =IF(ISBLANK(UW!I374),"",UW!I374) -> 0 | I61: =IF(ISBLANK(UW!J374),"",UW!J374) -> 0 | ... N61: =IF(ISBLANK(UW!O374),"",UW!O374) -> 0
B62: =IF(ISBLANK(UW!C375),"",UW!C375) -> Insurance (Self Storage) | C62: =IF(ISBLANK(UW!D375),"",UW!D375) -> 30135 | D62: =IF(ISBLANK(UW!E375),"",UW!E375) -> 0 | E62: =IF(ISBLANK(UW!F375),"",UW!F375) -> 0 | F62: =IF(ISBLANK(UW!G375),"",UW!G375) -> 0 | G62: =IF(ISBLANK(UW!H375),"",UW!H375) -> 0 | H62: =IF(ISBLANK(UW!I375),"",UW!I375) -> 0 | I62: =IF(ISBLANK(UW!J375),"",UW!J375) -> 0 | ... N62: =IF(ISBLANK(UW!O375),"",UW!O375) -> 0
B63: =IF(ISBLANK(UW!C376),"",UW!C376) -> Management Fee | C63: =IF(ISBLANK(UW!D376),"",UW!D376) -> 0 | D63: =IF(ISBLANK(UW!E376),"",UW!E376) -> 0 | E63: =IF(ISBLANK(UW!F376),"",UW!F376) -> 0 | F63: =IF(ISBLANK(UW!G376),"",UW!G376) -> 0 | G63: =IF(ISBLANK(UW!H376),"",UW!H376) -> 0 | H63: =IF(ISBLANK(UW!I376),"",UW!I376) -> 0 | I63: =IF(ISBLANK(UW!J376),"",UW!J376) -> 0 | ... N63: =IF(ISBLANK(UW!O376),"",UW!O376) -> 0
B64: =IF(ISBLANK(UW!C377),"",UW!C377) -> Merchandise (COGS) | C64: =IF(ISBLANK(UW!D377),"",UW!D377) -> 0 | D64: =IF(ISBLANK(UW!E377),"",UW!E377) -> 0 | E64: =IF(ISBLANK(UW!F377),"",UW!F377) -> 0 | F64: =IF(ISBLANK(UW!G377),"",UW!G377) -> 0 | G64: =IF(ISBLANK(UW!H377),"",UW!H377) -> 0 | H64: =IF(ISBLANK(UW!I377),"",UW!I377) -> 0 | I64: =IF(ISBLANK(UW!J377),"",UW!J377) -> 0 | ... N64: =IF(ISBLANK(UW!O377),"",UW!O377) -> 0
B65: =IF(ISBLANK(UW!C378),"",UW!C378) -> Motor Vehicle Expense | C65: =IF(ISBLANK(UW!D378),"",UW!D378) -> 0 | D65: =IF(ISBLANK(UW!E378),"",UW!E378) -> 0 | E65: =IF(ISBLANK(UW!F378),"",UW!F378) -> 0 | F65: =IF(ISBLANK(UW!G378),"",UW!G378) -> 0 | G65: =IF(ISBLANK(UW!H378),"",UW!H378) -> 0 | H65: =IF(ISBLANK(UW!I378),"",UW!I378) -> 0 | I65: =IF(ISBLANK(UW!J378),"",UW!J378) -> 0 | ... N65: =IF(ISBLANK(UW!O378),"",UW!O378) -> 0
B66: =IF(ISBLANK(UW!C379),"",UW!C379) -> Postage | C66: =IF(ISBLANK(UW!D379),"",UW!D379) -> 0 | D66: =IF(ISBLANK(UW!E379),"",UW!E379) -> 0 | E66: =IF(ISBLANK(UW!F379),"",UW!F379) -> 0 | F66: =IF(ISBLANK(UW!G379),"",UW!G379) -> 0 | G66: =IF(ISBLANK(UW!H379),"",UW!H379) -> 0 | H66: =IF(ISBLANK(UW!I379),"",UW!I379) -> 0 | I66: =IF(ISBLANK(UW!J379),"",UW!J379) -> 0 | ... N66: =IF(ISBLANK(UW!O379),"",UW!O379) -> 0
... B78: =IF(ISBLANK(UW!C391),"",UW!C391) -> Total Expenses | C78: =IF(ISBLANK(UW!D391),"",UW!D391) -> 375238.2 | D78: =IF(ISBLANK(UW!E391),"",UW!E391) -> 141154.2 | E78: =IF(ISBLANK(UW!F391),"",UW!F391) -> 148182.53 | F78: =IF(ISBLANK(UW!G391),"",UW!G391) -> 155561.7 | G78: =IF(ISBLANK(UW!H391),"",UW!H391) -> 163309.22 | H78: =IF(ISBLANK(UW!I391),"",UW!I391) -> 171443.51 | I78: =IF(ISBLANK(UW!J391),"",UW!J391) -> 179983.88 | ... N78: =IF(ISBLANK(UW!O391),"",UW!O391) -> 229523.94
B80: =IF(ISBLANK(UW!C395),"",UW!C395) -> Net Operating Income | C80: =IF(ISBLANK(UW!D395),"",UW!D395) -> -375238.2 | D80: =IF(ISBLANK(UW!E395),"",UW!E395) -> -141154.2 | E80: =IF(ISBLANK(UW!F395),"",UW!F395) -> -148182.53 | F80: =IF(ISBLANK(UW!G395),"",UW!G395) -> -155561.7 | G80: =IF(ISBLANK(UW!H395),"",UW!H395) -> -163309.22 | H80: =IF(ISBLANK(UW!I395),"",UW!I395) -> -171443.51 | I80: =IF(ISBLANK(UW!J395),"",UW!J395) -> -179983.88 | ... N80: =IF(ISBLANK(UW!O395),"",UW!O395) -> -229523.94 | Q80: =IF(ISBLANK(UW!R395),"",UW!R395)

Sheet Mini Warehouse Lease-up
C2: Mini Warehouse NLA: | G2: ='Unit Mix Generator'!Q12 -> 0
C3: Mini Warehouse Average Size: | G3: 35
C4: Mini Warehouse Units: | G4: =G2/G3 -> 0
C6: Lease-Up Assumptions
D7: Start Month | G7: =Start_Mth -> FALSE | I7: Lease-Up Pace/Mth | K7: =(G10-G8)/(G9-G7+1)*G2 -> 0
D8: Starting Occupancy | G8: 0 | I8: Lease-Up Pace/Yr | K8: =K7*12 -> 0
D9: Stabilised Month | G9: 36 | I9: Units/Month | K9: =K7/$G$3 -> 0
D10: Stabilised Occupancy | G10: 0.9 | I10: Units/Year | K10: =K8/$G$3 -> 0
D11: Rental Rate | G11: 190
D12: Discount | G12: 0.05
C14: Year | G14: 0 | H14: =ROUNDUP(H20/12,0) -> 1 | I14: =ROUNDUP(I20/12,0) -> 1 | J14: =ROUNDUP(J20/12,0) -> 1 | K14: =ROUNDUP(K20/12,0) -> 1 | L14: =ROUNDUP(L20/12,0) -> 1 | M14: =ROUNDUP(M20/12,0) -> 1 | N14: =ROUNDUP(N20/12,0) -> 1 | O14: =ROUNDUP(O20/12,0) -> 1 | ... EI14: =ROUNDUP(EI20/12,0) -> 11
C15: Month Ending | G15: =UW!D607 -> 46112 | H15: =UW!E607 -> 46142 | I15: =UW!F607 -> 46173 | J15: =UW!G607 -> 46203 | K15: =UW!H607 -> 46234 | L15: =UW!I607 -> 46265 | M15: =UW!J607 -> 46295 | N15: =UW!K607 -> 46326 | ... EI15: =UW!EF607 -> 50130
C17: Occupancy Change: | H17: =IF(AND(H$20>=$G$7,H$20<=$G$9),($G$10-$G$8)/($G$9-$G$7+1),0) -> 0 | I17: =IF(AND(I$20>=$G$7,I$20<=$G$9),($G$10-$G$8)/($G$9-$G$7+1),0) -> 0 | J17: =IF(AND(J$20>=$G$7,J$20<=$G$9),($G$10-$G$8)/($G$9-$G$7+1),0) -> 0 | K17: =IF(AND(K$20>=$G$7,K$20<=$G$9),($G$10-$G$8)/($G$9-$G$7+1),0) -> 0 | L17: =IF(AND(L$20>=$G$7,L$20<=$G$9),($G$10-$G$8)/($G$9-$G$7+1),0) -> 0 | M17: =IF(AND(M$20>=$G$7,M$20<=$G$9),($G$10-$G$8)/($G$9-$G$7+1),0) -> 0 | N17: =IF(AND(N$20>=$G$7,N$20<=$G$9),($G$10-$G$8)/($G$9-$G$7+1),0) -> 0 | O17: =IF(AND(O$20>=$G$7,O$20<=$G$9),($G$10-$G$8)/($G$9-$G$7+1),0) -> 0 | ... EI17: =IF(AND(EI$20>=$G$7,EI$20<=$G$9),($G$10-$G$8)/($G$9-$G$7+1),0) -> 0
D18: Physical Occupancy | G18: =G8 -> 0 | H18: =G18+H17 -> 0 | I18: =H18+I17 -> 0 | J18: =I18+J17 -> 0 | K18: =J18+K17 -> 0 | L18: =K18+L17 -> 0 | M18: =L18+M17 -> 0 | N18: =M18+N17 -> 0 | O18: =N18+O17 -> 0 | ... EI18: =EH18+EI17 -> 0
D19: Economic Occupancy | G19: =G25/G21 -> #DIV/0! | H19: =H25/H21 -> #DIV/0! | I19: =I25/I21 -> #DIV/0! | J19: =J25/J21 -> #DIV/0! | K19: =K25/K21 -> #DIV/0! | L19: =L25/L21 -> #DIV/0! | M19: =M25/M21 -> #DIV/0! | N19: =N25/N21 -> #DIV/0! | ... EI19: =EI25/EI21 -> #DIV/0!
C20: Lease-Up Timeline | G20: 0 | H20: =G20+1 -> 1 | I20: =H20+1 -> 2 | J20: =I20+1 -> 3 | K20: =J20+1 -> 4 | L20: =K20+1 -> 5 | M20: =L20+1 -> 6 | N20: =M20+1 -> 7 | O20: =N20+1 -> 8 | ... EI20: =EH20+1 -> 132
D21: Gross Potential Rent | G21: =UW!D517/12 -> 0 | H21: =OFFSET('Model Inputs & Calcs'!$B$40,,H$14)/12 -> 0 | I21: =OFFSET('Model Inputs & Calcs'!$B$40,,I$14)/12 -> 0 | J21: =OFFSET('Model Inputs & Calcs'!$B$40,,J$14)/12 -> 0 | K21: =OFFSET('Model Inputs & Calcs'!$B$40,,K$14)/12 -> 0 | L21: =OFFSET('Model Inputs & Calcs'!$B$40,,L$14)/12 -> 0 | M21: =OFFSET('Model Inputs & Calcs'!$B$40,,M$14)/12 -> 0 | N21: =OFFSET('Model Inputs & Calcs'!$B$40,,N$14)/12 -> 0 | O21: =OFFSET('Model Inputs & Calcs'!$B$40,,O$14)/12 -> 0 | ... EI21: =OFFSET('Model Inputs & Calcs'!$B$40,,EI$14)/12 -> 0
D22: Vacancy | G22: =-G$21*(1-G$18) -> 0 | H22: =-H$21*(1-H$18) -> 0 | I22: =-I$21*(1-I$18) -> 0 | J22: =-J$21*(1-J$18) -> 0 | K22: =-K$21*(1-K$18) -> 0 | L22: =-L$21*(1-L$18) -> 0 | M22: =-M$21*(1-M$18) -> 0 | N22: =-N$21*(1-N$18) -> 0 | ... EI22: =-EI$21*(1-EI$18) -> 0
D23: Gross Rental Income | G23: =SUM(G21:G22) -> 0 | H23: =SUM(H21:H22) -> 0 | I23: =SUM(I21:I22) -> 0 | J23: =SUM(J21:J22) -> 0 | K23: =SUM(K21:K22) -> 0 | L23: =SUM(L21:L22) -> 0 | M23: =SUM(M21:M22) -> 0 | N23: =SUM(N21:N22) -> 0 | ... EI23: =SUM(EI21:EI22) -> 0
D24: Discount | G24: =G23*-$G$12 -> 0 | H24: =H23*-$G$12 -> 0 | I24: =I23*-$G$12 -> 0 | J24: =J23*-$G$12 -> 0 | K24: =K23*-$G$12 -> 0 | L24: =L23*-$G$12 -> 0 | M24: =M23*-$G$12 -> 0 | N24: =N23*-$G$12 -> 0 | ... EI24: =EI23*-$G$12 -> 0
D25: Net Rental Income | G25: =SUM(G23:G24) -> 0 | H25: =SUM(H23:H24) -> 0 | I25: =SUM(I23:I24) -> 0 | J25: =SUM(J23:J24) -> 0 | K25: =SUM(K23:K24) -> 0 | L25: =SUM(L23:L24) -> 0 | M25: =SUM(M23:M24) -> 0 | N25: =SUM(N23:N24) -> 0 | ... EI25: =SUM(EI23:EI24) -> 0

Sheet BBSW Curve
B2: BBSW Date: | D2: 6.5.2021
B3: T | C3: Yield | D3: NSS | E3: Residual | F3: ß1 | G3: 0.029939221
B4: =30/360 -> 0.083333333 | C4: 0.0002 | D4: =(Beta1)+(Beta2*((1-EXP(-B4/Lambda1))/(B4/Lambda1)))+(Beta3*((((1-EXP(-B4/Lambda1))/(B4/Lambda1)))-(EXP(-B4/Lambda1))))+(Beta4*((((1-EXP(-B4/Lambda2))/(B4/Lambda2)))-(EXP(-B4/Lambda2)))) -> -0.001317788 | E4: =IF(C4>0,POWER(C4-D4,2),"") -> 2.3036804e-06 | F4: ß2 | G4: -0.033598748
B5: =90/360 -> 0.25 | C5: 0.0021 | D5: =(Beta1)+(Beta2*((1-EXP(-B5/Lambda1))/(B5/Lambda1)))+(Beta3*((((1-EXP(-B5/Lambda1))/(B5/Lambda1)))-(EXP(-B5/Lambda1))))+(Beta4*((((1-EXP(-B5/Lambda2))/(B5/Lambda2)))-(EXP(-B5/Lambda2)))) -> 0.0028009043 | E5: =IF(C5>0,POWER(C5-D5,2),"") -> 4.9126686e-07 | F5: ß3 | G5: -0.010520445
B6: =180/360 -> 0.5 | C6: 0.0068 | D6: =(Beta1)+(Beta2*((1-EXP(-B6/Lambda1))/(B6/Lambda1)))+(Beta3*((((1-EXP(-B6/Lambda1))/(B6/Lambda1)))-(EXP(-B6/Lambda1))))+(Beta4*((((1-EXP(-B6/Lambda2))/(B6/Lambda2)))-(EXP(-B6/Lambda2)))) -> 0.0077285592 | E6: =IF(C6>0,POWER(C6-D6,2),"") -> 8.6222211e-07 | F6: ß4 | G6: -0.0078224739
B7: 1 | C7: 0.0118 | D7: =(Beta1)+(Beta2*((1-EXP(-B7/Lambda1))/(B7/Lambda1)))+(Beta3*((((1-EXP(-B7/Lambda1))/(B7/Lambda1)))-(EXP(-B7/Lambda1))))+(Beta4*((((1-EXP(-B7/Lambda2))/(B7/Lambda2)))-(EXP(-B7/Lambda2)))) -> 0.014227094 | E7: =IF(C7>0,POWER(C7-D7,2),"") -> 5.8907875e-06 | F7: λ1 | G7: 0.37977139
B8: =B7+1 -> 2 | D8: =(Beta1)+(Beta2*((1-EXP(-B8/Lambda1))/(B8/Lambda1)))+(Beta3*((((1-EXP(-B8/Lambda1))/(B8/Lambda1)))-(EXP(-B8/Lambda1))))+(Beta4*((((1-EXP(-B8/Lambda2))/(B8/Lambda2)))-(EXP(-B8/Lambda2)))) -> 0.020129871 | E8: =IF(C8>0,POWER(C8-D8,2),"") | F8: λ2 | G8: 3.542711
B9: =B8+1 -> 3 | C9: 0.0258 | D9: =(Beta1)+(Beta2*((1-EXP(-B9/Lambda1))/(B9/Lambda1)))+(Beta3*((((1-EXP(-B9/Lambda1))/(B9/Lambda1)))-(EXP(-B9/Lambda1))))+(Beta4*((((1-EXP(-B9/Lambda2))/(B9/Lambda2)))-(EXP(-B9/Lambda2)))) -> 0.022437567 | E9: =IF(C9>0,POWER(C9-D9,2),"") -> 1.1305955e-05
B10: =B9+1 -> 4 | D10: =(Beta1)+(Beta2*((1-EXP(-B10/Lambda1))/(B10/Lambda1)))+(Beta3*((((1-EXP(-B10/Lambda1))/(B10/Lambda1)))-(EXP(-B10/Lambda1))))+(Beta4*((((1-EXP(-B10/Lambda2))/(B10/Lambda2)))-(EXP(-B10/Lambda2)))) -> 0.023591967 | E10: =IF(C10>0,POWER(C10-D10,2),"")
B11: =B10+1 -> 5 | C11: 0.0289 | D11: =(Beta1)+(Beta2*((1-EXP(-B11/Lambda1))/(B11/Lambda1)))+(Beta3*((((1-EXP(-B11/Lambda1))/(B11/Lambda1)))-(EXP(-B11/Lambda1))))+(Beta4*((((1-EXP(-B11/Lambda2))/(B11/Lambda2)))-(EXP(-B11/Lambda2)))) -> 0.024304237 | E11: =IF(C11>0,POWER(C11-D11,2),"") -> 2.1121035e-05
B12: =B11+1 -> 6 | D12: =(Beta1)+(Beta2*((1-EXP(-B12/Lambda1))/(B12/Lambda1)))+(Beta3*((((1-EXP(-B12/Lambda1))/(B12/Lambda1)))-(EXP(-B12/Lambda1))))+(Beta4*((((1-EXP(-B12/Lambda2))/(B12/Lambda2)))-(EXP(-B12/Lambda2)))) -> 0.02481526 | E12: =IF(C12>0,POWER(C12-D12,2),"")
B13: =B12+1 -> 7 | D13: =(Beta1)+(Beta2*((1-EXP(-B13/Lambda1))/(B13/Lambda1)))+(Beta3*((((1-EXP(-B13/Lambda1))/(B13/Lambda1)))-(EXP(-B13/Lambda1))))+(Beta4*((((1-EXP(-B13/Lambda2))/(B13/Lambda2)))-(EXP(-B13/Lambda2)))) -> 0.025220011 | E13: =IF(C13>0,POWER(C13-D13,2),"")
B14: =B13+1 -> 8 | D14: =(Beta1)+(Beta2*((1-EXP(-B14/Lambda1))/(B14/Lambda1)))+(Beta3*((((1-EXP(-B14/Lambda1))/(B14/Lambda1)))-(EXP(-B14/Lambda1))))+(Beta4*((((1-EXP(-B14/Lambda2))/(B14/Lambda2)))-(EXP(-B14/Lambda2)))) -> 0.025560655 | E14: =IF(C14>0,POWER(C14-D14,2),"")
B15: =B14+1 -> 9 | D15: =(Beta1)+(Beta2*((1-EXP(-B15/Lambda1))/(B15/Lambda1)))+(Beta3*((((1-EXP(-B15/Lambda1))/(B15/Lambda1)))-(EXP(-B15/Lambda1))))+(Beta4*((((1-EXP(-B15/Lambda2))/(B15/Lambda2)))-(EXP(-B15/Lambda2)))) -> 0.025857743 | E15: =IF(C15>0,POWER(C15-D15,2),"")
B16: =B15+1 -> 10 | C16: 0.0312 | D16: =(Beta1)+(Beta2*((1-EXP(-B16/Lambda1))/(B16/Lambda1)))+(Beta3*((((1-EXP(-B16/Lambda1))/(B16/Lambda1)))-(EXP(-B16/Lambda1))))+(Beta4*((((1-EXP(-B16/Lambda2))/(B16/Lambda2)))-(EXP(-B16/Lambda2)))) -> 0.026122173 | E16: =IF(C16>0,POWER(C16-D16,2),"") -> 2.5784323e-05
B17: =B16+1 -> 11 | D17: =(Beta1)+(Beta2*((1-EXP(-B17/Lambda1))/(B17/Lambda1)))+(Beta3*((((1-EXP(-B17/Lambda1))/(B17/Lambda1)))-(EXP(-B17/Lambda1))))+(Beta4*((((1-EXP(-B17/Lambda2))/(B17/Lambda2)))-(EXP(-B17/Lambda2)))) -> 0.02636026 | E17: =IF(C17>0,POWER(C17-D17,2),"")
B18: =B17+1 -> 12 | D18: =(Beta1)+(Beta2*((1-EXP(-B18/Lambda1))/(B18/Lambda1)))+(Beta3*((((1-EXP(-B18/Lambda1))/(B18/Lambda1)))-(EXP(-B18/Lambda1))))+(Beta4*((((1-EXP(-B18/Lambda2))/(B18/Lambda2)))-(EXP(-B18/Lambda2)))) -> 0.026576034 | E18: =IF(C18>0,POWER(C18-D18,2),"")
B19: =B18+1 -> 13 | D19: =(Beta1)+(Beta2*((1-EXP(-B19/Lambda1))/(B19/Lambda1)))+(Beta3*((((1-EXP(-B19/Lambda1))/(B19/Lambda1)))-(EXP(-B19/Lambda1))))+(Beta4*((((1-EXP(-B19/Lambda2))/(B19/Lambda2)))-(EXP(-B19/Lambda2)))) -> 0.026772331 | E19: =IF(C19>0,POWER(C19-D19,2),"") | I19: 6yr Spot | J19: =D9 -> 0.022437567 | L19: =((1+J19)^3/(1+J20)^1)^(1/3)-1 -> 0.017634281
B20: =B19+1 -> 14 | D20: =(Beta1)+(Beta2*((1-EXP(-B20/Lambda1))/(B20/Lambda1)))+(Beta3*((((1-EXP(-B20/Lambda1))/(B20/Lambda1)))-(EXP(-B20/Lambda1))))+(Beta4*((((1-EXP(-B20/Lambda2))/(B20/Lambda2)))-(EXP(-B20/Lambda2)))) -> 0.026951336 | E20: =IF(C20>0,POWER(C20-D20,2),"") | I20: 3yr Spot | J20: =D7 -> 0.014227094
B21: =B20+1 -> 15 | C21: 0.0319 | D21: =(Beta1)+(Beta2*((1-EXP(-B21/Lambda1))/(B21/Lambda1)))+(Beta3*((((1-EXP(-B21/Lambda1))/(B21/Lambda1)))-(EXP(-B21/Lambda1))))+(Beta4*((((1-EXP(-B21/Lambda2))/(B21/Lambda2)))-(EXP(-B21/Lambda2)))) -> 0.027114843 | E21: =IF(C21>0,POWER(C21-D21,2),"") -> 2.289773e-05
D22: Sum | E22: =SUM(E4:E21) -> 9.0657e-05 | I22: 9yr Spot | J22: =D12 -> 0.02481526 | L22: =((1+J22)^6/(1+J23)^3)^(1/3)-1 -> 0.027198482
I23: 6yr spot | J23: =D9 -> 0.022437567
I25: 15yr Spot | J25: =D16 -> 0.026122173 | L25: =((1+J25)^10/(1+J26)^6)^(1/4)-1 -> 0.02808567
I26: 9yr Spot | J26: =D12 -> 0.02481526
I28: 3yr Spot | J28: =C9 -> 0.0258 | L28: =((1+J28)^3/(1+J29)^1)^(1/3)-1 -> 0.021796639
I29: 1yr Spot | J29: =C7 -> 0.0118

Sheet Lease Up Timeline
C2: =UW!E607 -> 46142 | D2: =UW!F607 -> 46173 | E2: =UW!G607 -> 46203 | F2: =UW!H607 -> 46234 | G2: =UW!I607 -> 46265 | H2: =UW!J607 -> 46295 | I2: =UW!K607 -> 46326 | J2: =UW!L607 -> 46356 | ... ED2: =UW!EF607 -> 50130
C3: =UW!E612 -> 1 | D3: =UW!F612 -> 2 | E3: =UW!G612 -> 3 | F3: =UW!H612 -> 4 | G3: =UW!I612 -> 5 | H3: =UW!J612 -> 6 | I3: =UW!K612 -> 7 | J3: =UW!L612 -> 8 | ... ED3: =UW!EF612 -> 132
B4: Total Revenue | C4: =UW!E685 -> 0 | D4: =UW!F685 -> 0 | E4: =UW!G685 -> 0 | F4: =UW!H685 -> 0 | G4: =UW!I685 -> 0 | H4: =UW!J685 -> 0 | I4: =UW!K685 -> 0 | J4: =UW!L685 -> 0 | ... ED4: =UW!EF685 -> 0
B5: Total Property Expenses | C5: =-UW!E712 -> -11762.85 | D5: =-UW!F712 -> -11762.85 | E5: =-UW!G712 -> -11762.85 | F5: =-UW!H712 -> -11762.85 | G5: =-UW!I712 -> -11762.85 | H5: =-UW!J712 -> -11762.85 | I5: =-UW!K712 -> -11762.85 | J5: =-UW!L712 -> -11762.85 | ... ED5: =-UW!EF712 -> -19126.995
B6: NOI | C6: =SUM(C4:C5) -> -11762.85 | D6: =SUM(D4:D5) -> -11762.85 | E6: =SUM(E4:E5) -> -11762.85 | F6: =SUM(F4:F5) -> -11762.85 | G6: =SUM(G4:G5) -> -11762.85 | H6: =SUM(H4:H5) -> -11762.85 | I6: =SUM(I4:I5) -> -11762.85 | J6: =SUM(J4:J5) -> -11762.85 | ... ED6: =SUM(ED4:ED5) -> -19126.995
B8: Replacement Reserves | C8: =UW!E716 -> #DIV/0! | D8: =UW!F716 -> #DIV/0! | E8: =UW!G716 -> #DIV/0! | F8: =UW!H716 -> #DIV/0! | G8: =UW!I716 -> #DIV/0! | H8: =UW!J716 -> #DIV/0! | I8: =UW!K716 -> #DIV/0! | J8: =UW!L716 -> #DIV/0! | ... ED8: =UW!EF716 -> #DIV/0!
B9: CF Before Debt Service | C9: =UW!E717 -> #DIV/0! | D9: =UW!F717 -> #DIV/0! | E9: =UW!G717 -> #DIV/0! | F9: =UW!H717 -> #DIV/0! | G9: =UW!I717 -> #DIV/0! | H9: =UW!J717 -> #DIV/0! | I9: =UW!K717 -> #DIV/0! | J9: =UW!L717 -> #DIV/0! | ... ED9: =UW!EF717 -> #DIV/0!
B11: Debt | C11: =UW!E721 -> 0 | D11: =UW!F721 -> #DIV/0! | E11: =UW!G721 -> #DIV/0! | F11: =UW!H721 -> #DIV/0! | G11: =UW!I721 -> #DIV/0! | H11: =UW!J721 -> #DIV/0! | I11: =UW!K721 -> #DIV/0! | J11: =UW!L721 -> #DIV/0! | ... ED11: =UW!EF721 -> 0
B12: CF After Debt Service | C12: =C11+C9 -> #DIV/0! | D12: =D11+D9 -> #DIV/0! | E12: =E11+E9 -> #DIV/0! | F12: =F11+F9 -> #DIV/0! | G12: =G11+G9 -> #DIV/0! | H12: =H11+H9 -> #DIV/0! | I12: =I11+I9 -> #DIV/0! | J12: =J11+J9 -> #DIV/0! | ... ED12: =ED11+ED9 -> #DIV/0!
B14: OpEx Reserve (Equity) | C14: =UW!E736 -> #DIV/0! | D14: =UW!F736-UW!E736 -> #DIV/0! | E14: =UW!G736-UW!F736 -> #DIV/0! | F14: =UW!H736-UW!G736 -> #DIV/0! | G14: =UW!I736-UW!H736 -> #DIV/0! | H14: =UW!J736-UW!I736 -> #DIV/0! | I14: =UW!K736-UW!J736 -> #DIV/0! | J14: =UW!L736-UW!K736 -> #DIV/0! | K14: =UW!M736-UW!L736 -> #DIV/0! | ... ED14: =UW!EF736-UW!EE736 -> #DIV/0!
B15: Interest Reserve (Equity) | C15: =UW!E737 -> #DIV/0! | D15: =UW!F737-UW!E737 -> #DIV/0! | E15: =UW!G737-UW!F737 -> #DIV/0! | F15: =UW!H737-UW!G737 -> #DIV/0! | G15: =UW!I737-UW!H737 -> #DIV/0! | H15: =UW!J737-UW!I737 -> #DIV/0! | I15: =UW!K737-UW!J737 -> #DIV/0! | J15: =UW!L737-UW!K737 -> #DIV/0! | K15: =UW!M737-UW!L737 -> #DIV/0! | ... ED15: =UW!EF737-UW!EE737 -> #DIV/0!
B16: Cash Flow After Reserves | C16: =SUM(C12:C15) -> #DIV/0! | D16: =SUM(D12:D15) -> #DIV/0! | E16: =SUM(E12:E15) -> #DIV/0! | F16: =SUM(F12:F15) -> #DIV/0! | G16: =SUM(G12:G15) -> #DIV/0! | H16: =SUM(H12:H15) -> #DIV/0! | I16: =SUM(I12:I15) -> #DIV/0! | J16: =SUM(J12:J15) -> #DIV/0! | ... ED16: =SUM(ED12:ED15) -> #DIV/0!
B18: Asset Management Fee | C18: =-UW!E743 -> 0 | D18: =-UW!F743 -> 0 | E18: =-UW!G743 -> 0 | F18: =-UW!H743 -> 0 | G18: =-UW!I743 -> 0 | H18: =-UW!J743 -> 0 | I18: =-UW!K743 -> 0 | J18: =-UW!L743 -> 0 | ... ED18: =-UW!EF743 -> 0
B19: Cash Flow After Fees | C19: =SUM(C16:C18) -> #DIV/0! | D19: =SUM(D16:D18) -> #DIV/0! | E19: =SUM(E16:E18) -> #DIV/0! | F19: =SUM(F16:F18) -> #DIV/0! | G19: =SUM(G16:G18) -> #DIV/0! | H19: =SUM(H16:H18) -> #DIV/0! | I19: =SUM(I16:I18) -> #DIV/0! | J19: =SUM(J16:J18) -> #DIV/0! | ... ED19: =SUM(ED16:ED18) -> #DIV/0!
B21: Fee Reserve | C21: =UW!E746 -> #DIV/0! | D21: =UW!F746 -> #DIV/0! | E21: =UW!G746 -> #DIV/0! | F21: =UW!H746 -> #DIV/0! | G21: =UW!I746 -> #DIV/0! | H21: =UW!J746 -> #DIV/0! | I21: =UW!K746 -> #DIV/0! | J21: =UW!L746 -> #DIV/0! | ... ED21: =UW!EF746 -> #DIV/0!
B22: Net Cash Flow | C22: =IF(C21+C19<0,0,C21+C19) -> #DIV/0! | D22: =SUM(D19:D21) -> #DIV/0! | E22: =SUM(E19:E21) -> #DIV/0! | F22: =SUM(F19:F21) -> #DIV/0! | G22: =SUM(G19:G21) -> #DIV/0! | H22: =SUM(H19:H21) -> #DIV/0! | I22: =SUM(I19:I21) -> #DIV/0! | J22: =SUM(J19:J21) -> #DIV/0! | K22: =SUM(K19:K21) -> #DIV/0! | ... ED22: =SUM(ED19:ED21) -> #DIV/0!
